Workbook

Sheet Input
A1: FUEL ROCK (PTY) LTD
A2: SITE NAME: | B2: ENGEN JETPARK
A4: Daily Management - Input
A6: Month Under Review: | B6: 46143
B8: Day | C8: Date
B10: Friday | C10: 46143 | E10: Copy Day & Date till last day of the month
B11: Saturday | C11: 46144
B12: Sunday | C12: 46145
B13: Monday | C13: 46146
B14: Tuesday | C14: 46147
B15: Wednesday | C15: 46148
B16: Thursday | C16: 46149
B17: Friday | C17: 46150
B18: Saturday | C18: 46151
B19: Sunday | C19: 46152
B20: Monday | C20: 46153
B21: Tuesday | C21: 46154
B22: Wednesday | C22: 46155
... B40: Sunday | C40: 46173
B43: 1 | C43: 2 | D43: 3 | E43: 4 | F43: 5 | G43: 6
A44: Cashiers | B44: Mandla | C44: Caroline | D44: Siyabonga | E44: Thumelo | F44: Cashier 5 | G44: Cashier 6
B47: 1 | C47: 2 | D47: 3 | E47: 4 | F47: 5
A48: Fuel Litres - Opening
A49: - Diesel
A50: - ULP 93
A51: - ULP 95
A54: Creditors
A55: - Aksia Sales
A56: - Albany
A57: - Atlantic Ice
A58: - Bake It Easy
A59: - Bamco Tabacco
A60: - Blue Ribbon
A61: - Catercorp
... A97: - Other 10

Sheet Summary
A1: =+Input!B2 -> ENGEN JETPARK
A3: Monthly Summary | B3: =+Input!B6 -> 46143
A5: DATA: LITRES | B5: Diesel | C5: ULP: 93 | D5: ULP: 95
A6: - Litres Purchased | B6: =+'SS26'!B8 -> 0 | C6: =+'SS26'!C8 -> 0 | D6: =+'SS26'!D8 -> 0
A7: - Litres Sold | B7: =+'SS26'!B9 -> 1659.39 | C7: =+'SS26'!C9 -> 40.06 | D7: =+'SS26'!D9 -> 1920.7
A8: - Closing Dip: ATG | B8: =+'SS26'!B11 -> 0 | C8: =+'SS26'!C11 -> 0 | D8: =+'SS26'!D11 -> 0
A9: - Selling Price | B9: =+'30'!B14 -> 0 | C9: =+'30'!C14 -> 0 | D9: =+'30'!D14 -> 0
A10: - Cost Price | B10: =+'30'!B15 -> 0 | C10: =+'30'!C15 -> 0 | D10: =+'30'!D15 -> 0
A11: - Gross Profit | B11: =+B9-B10 -> 0 | C11: =+C9-C10 -> 0 | D11: =+D9-D10 -> 0
A12: - Gross Profit % | B12: =+B11/B9 -> #DIV/0! | C12: =+C11/C9 -> #DIV/0! | D12: =+D11/D9 -> #DIV/0!
A15: DAY END REPORT | B15: TOTAL | C15: 1 | D15: =+C15+1 -> 2 | E15: =+D15+1 -> 3 | F15: =+E15+1 -> 4 | G15: =+F15+1 -> 5 | H15: =+G15+1 -> 6 | I15: =+H15+1 -> 7 | J15: =+I15+1 -> 8 | K15: =+J15+1 -> 9 | ... AG15: =+AF15+1 -> 31
A16: - Total Sales | B16: =SUM(C16:AG16) -> 0 | C16: =+'1'!B21 -> 0 | D16: =+'2'!B21 -> 0 | E16: =+'3'!B21 -> 0 | F16: =+'4'!B21 -> 0 | G16: =+'5'!B21 -> 0 | H16: =+'6'!B21 -> 0 | I16: =+'7'!B21 -> 0 | J16: =+'8'!B21 -> 0 | K16: =+'9'!B21 -> 0 | L16: =+'10'!B21 -> 0 | M16: =+'11'!B21 -> 0 | N16: =+'12'!B21 -> 0 | O16: =+'13'!B21 -> 0 | P16: =+'14'!B21 -> 0 | Q16: =+'15'!B21 -> 0 | R16: =+'16'!B21 -> 0 | S16: =+'17'!B21 -> 0 | T16: =+'18'!B21 -> 0 | U16: =+'19'!B21 -> 0 | V16: =+'20'!B21 -> 0 | W16: =+'21'!B21 -> 0 | X16: =+'22'!B21 -> 0 | Y16: =+'23'!B21 -> 0 | Z16: =+'24'!B21 -> 0 | AA16: =+'25'!B21 -> 0 | AB16: =+'26'!B21 -> 0 | AC16: =+'27'!B21 -> 0 | AD16: =+'28'!B21 -> 0 | AE16: =+'29'!B21 -> 0 | AF16: =+'30'!B21 -> 0 | AG16: =+'31'!B21 -> 0
A17: - Less: Returns (Show as a negative) | B17: =SUM(C17:AG17) -> 0 | C17: =+'1'!B22 -> 0 | D17: =+'2'!B22 -> 0 | E17: =+'3'!B22 -> 0 | F17: =+'4'!B22 -> 0 | G17: =+'5'!B22 -> 0 | H17: =+'6'!B22 -> 0 | I17: =+'7'!B22 -> 0 | J17: =+'8'!B22 -> 0 | K17: =+'9'!B22 -> 0 | L17: =+'10'!B22 -> 0 | M17: =+'11'!B22 -> 0 | N17: =+'12'!B22 -> 0 | O17: =+'13'!B22 -> 0 | P17: =+'14'!B22 -> 0 | Q17: =+'15'!B22 -> 0 | R17: =+'16'!B22 -> 0 | S17: =+'17'!B22 -> 0 | T17: =+'18'!B22 -> 0 | U17: =+'19'!B22 -> 0 | V17: =+'20'!B22 -> 0 | W17: =+'21'!B22 -> 0 | X17: =+'22'!B22 -> 0 | Y17: =+'23'!B22 -> 0 | Z17: =+'24'!B22 -> 0 | AA17: =+'25'!B22 -> 0 | AB17: =+'26'!B22 -> 0 | AC17: =+'27'!B22 -> 0 | AD17: =+'28'!B22 -> 0 | AE17: =+'29'!B22 -> 0 | AF17: =+'30'!B22 -> 0 | AG17: =+'31'!B22 -> 0
A18: - Total Net Sales | B18: =SUM(B16:B17) -> 0 | C18: =SUM(C16:C17) -> 0 | D18: =SUM(D16:D17) -> 0 | E18: =SUM(E16:E17) -> 0 | F18: =SUM(F16:F17) -> 0 | G18: =SUM(G16:G17) -> 0 | H18: =SUM(H16:H17) -> 0 | I18: =SUM(I16:I17) -> 0 | ... AG18: =SUM(AG16:AG17) -> 0
A21: SALES BY DIVISION | B21: TOTAL | C21: 1 | D21: =+C21+1 -> 2 | E21: =+D21+1 -> 3 | F21: =+E21+1 -> 4 | G21: =+F21+1 -> 5 | H21: =+G21+1 -> 6 | I21: =+H21+1 -> 7 | J21: =+I21+1 -> 8 | K21: =+J21+1 -> 9 | ... AG21: =+AF21+1 -> 31
A22: - Bakery | B22: =SUM(C22:AG22) -> 0 | C22: =+'1'!B27 -> 0 | D22: =+'2'!B27 -> 0 | E22: =+'3'!B27 -> 0 | F22: =+'4'!B27 -> 0 | G22: =+'5'!B27 -> 0 | H22: =+'6'!B27 -> 0 | I22: =+'7'!B27 -> 0 | J22: =+'8'!B27 -> 0 | K22: =+'9'!B27 -> 0 | L22: =+'10'!B27 -> 0 | M22: =+'11'!B27 -> 0 | N22: =+'12'!B27 -> 0 | O22: =+'13'!B27 -> 0 | P22: =+'14'!B27 -> 0 | Q22: =+'15'!B27 -> 0 | R22: =+'16'!B27 -> 0 | S22: =+'17'!B27 -> 0 | T22: =+'18'!B27 -> 0 | U22: =+'19'!B27 -> 0 | V22: =+'20'!B27 -> 0 | W22: =+'21'!B27 -> 0 | X22: =+'22'!B27 -> 0 | Y22: =+'23'!B27 -> 0 | Z22: =+'24'!B27 -> 0 | AA22: =+'25'!B27 -> 0 | AB22: =+'26'!B27 -> 0 | AC22: =+'27'!B27 -> 0 | AD22: =+'28'!B27 -> 0 | AE22: =+'29'!B27 -> 0 | AF22: =+'30'!B27 -> 0 | AG22: =+'31'!B27 -> 0
A23: - Bakpre | B23: =SUM(C23:AG23) -> 0 | C23: =+'1'!B28 -> 0 | D23: =+'2'!B28 -> 0 | E23: =+'3'!B28 -> 0 | F23: =+'4'!B28 -> 0 | G23: =+'5'!B28 -> 0 | H23: =+'6'!B28 -> 0 | I23: =+'7'!B28 -> 0 | J23: =+'8'!B28 -> 0 | K23: =+'9'!B28 -> 0 | L23: =+'10'!B28 -> 0 | M23: =+'11'!B28 -> 0 | N23: =+'12'!B28 -> 0 | O23: =+'13'!B28 -> 0 | P23: =+'14'!B28 -> 0 | Q23: =+'15'!B28 -> 0 | R23: =+'16'!B28 -> 0 | S23: =+'17'!B28 -> 0 | T23: =+'18'!B28 -> 0 | U23: =+'19'!B28 -> 0 | V23: =+'20'!B28 -> 0 | W23: =+'21'!B28 -> 0 | X23: =+'22'!B28 -> 0 | Y23: =+'23'!B28 -> 0 | Z23: =+'24'!B28 -> 0 | AA23: =+'25'!B28 -> 0 | AB23: =+'26'!B28 -> 0 | AC23: =+'27'!B28 -> 0 | AD23: =+'28'!B28 -> 0 | AE23: =+'29'!B28 -> 0 | AF23: =+'30'!B28 -> 0 | AG23: =+'31'!B28 -> 0
A24: - Barist | B24: =SUM(C24:AG24) -> 0 | C24: =+'1'!B29 -> 0 | D24: =+'2'!B29 -> 0 | E24: =+'3'!B29 -> 0 | F24: =+'4'!B29 -> 0 | G24: =+'5'!B29 -> 0 | H24: =+'6'!B29 -> 0 | I24: =+'7'!B29 -> 0 | J24: =+'8'!B29 -> 0 | K24: =+'9'!B29 -> 0 | L24: =+'10'!B29 -> 0 | M24: =+'11'!B29 -> 0 | N24: =+'12'!B29 -> 0 | O24: =+'13'!B29 -> 0 | P24: =+'14'!B29 -> 0 | Q24: =+'15'!B29 -> 0 | R24: =+'16'!B29 -> 0 | S24: =+'17'!B29 -> 0 | T24: =+'18'!B29 -> 0 | U24: =+'19'!B29 -> 0 | V24: =+'20'!B29 -> 0 | W24: =+'21'!B29 -> 0 | X24: =+'22'!B29 -> 0 | Y24: =+'23'!B29 -> 0 | Z24: =+'24'!B29 -> 0 | AA24: =+'25'!B29 -> 0 | AB24: =+'26'!B29 -> 0 | AC24: =+'27'!B29 -> 0 | AD24: =+'28'!B29 -> 0 | AE24: =+'29'!B29 -> 0 | AF24: =+'30'!B29 -> 0 | AG24: =+'31'!B29 -> 0
A25: - Fuel | B25: =SUM(C25:AG25) -> 0 | C25: =+'1'!B30 -> 0 | D25: =+'2'!B30 -> 0 | E25: =+'3'!B30 -> 0 | F25: =+'4'!B30 -> 0 | G25: =+'5'!B30 -> 0 | H25: =+'6'!B30 -> 0 | I25: =+'7'!B30 -> 0 | J25: =+'8'!B30 -> 0 | K25: =+'9'!B30 -> 0 | L25: =+'10'!B30 -> 0 | M25: =+'11'!B30 -> 0 | N25: =+'12'!B30 -> 0 | O25: =+'13'!B30 -> 0 | P25: =+'14'!B30 -> 0 | Q25: =+'15'!B30 -> 0 | R25: =+'16'!B30 -> 0 | S25: =+'17'!B30 -> 0 | T25: =+'18'!B30 -> 0 | U25: =+'19'!B30 -> 0 | V25: =+'20'!B30 -> 0 | W25: =+'21'!B30 -> 0 | X25: =+'22'!B30 -> 0 | Y25: =+'23'!B30 -> 0 | Z25: =+'24'!B30 -> 0 | AA25: =+'25'!B30 -> 0 | AB25: =+'26'!B30 -> 0 | AC25: =+'27'!B30 -> 0 | AD25: =+'28'!B30 -> 0 | AE25: =+'29'!B30 -> 0 | AF25: =+'30'!B30 -> 0 | AG25: =+'31'!B30 -> 0
A26: - Lubes | B26: =SUM(C26:AG26) -> 0 | C26: =+'1'!B31 -> 0 | D26: =+'2'!B31 -> 0 | E26: =+'3'!B31 -> 0 | F26: =+'4'!B31 -> 0 | G26: =+'5'!B31 -> 0 | H26: =+'6'!B31 -> 0 | I26: =+'7'!B31 -> 0 | J26: =+'8'!B31 -> 0 | K26: =+'9'!B31 -> 0 | L26: =+'10'!B31 -> 0 | M26: =+'11'!B31 -> 0 | N26: =+'12'!B31 -> 0 | O26: =+'13'!B31 -> 0 | P26: =+'14'!B31 -> 0 | Q26: =+'15'!B31 -> 0 | R26: =+'16'!B31 -> 0 | S26: =+'17'!B31 -> 0 | T26: =+'18'!B31 -> 0 | U26: =+'19'!B31 -> 0 | V26: =+'20'!B31 -> 0 | W26: =+'21'!B31 -> 0 | X26: =+'22'!B31 -> 0 | Y26: =+'23'!B31 -> 0 | Z26: =+'24'!B31 -> 0 | AA26: =+'25'!B31 -> 0 | AB26: =+'26'!B31 -> 0 | AC26: =+'27'!B31 -> 0 | AD26: =+'28'!B31 -> 0 | AE26: =+'29'!B31 -> 0 | AF26: =+'30'!B31 -> 0 | AG26: =+'31'!B31 -> 0
A27: - VV | B27: =SUM(C27:AG27) -> 0 | C27: =+'1'!B32 -> 0 | D27: =+'2'!B32 -> 0 | E27: =+'3'!B32 -> 0 | F27: =+'4'!B32 -> 0 | G27: =+'5'!B32 -> 0 | H27: =+'6'!B32 -> 0 | I27: =+'7'!B32 -> 0 | J27: =+'8'!B32 -> 0 | K27: =+'9'!B32 -> 0 | L27: =+'10'!B32 -> 0 | M27: =+'11'!B32 -> 0 | N27: =+'12'!B32 -> 0 | O27: =+'13'!B32 -> 0 | P27: =+'14'!B32 -> 0 | Q27: =+'15'!B32 -> 0 | R27: =+'16'!B32 -> 0 | S27: =+'17'!B32 -> 0 | T27: =+'18'!B32 -> 0 | U27: =+'19'!B32 -> 0 | V27: =+'20'!B32 -> 0 | W27: =+'21'!B32 -> 0 | X27: =+'22'!B32 -> 0 | Y27: =+'23'!B32 -> 0 | Z27: =+'24'!B32 -> 0 | AA27: =+'25'!B32 -> 0 | AB27: =+'26'!B32 -> 0 | AC27: =+'27'!B32 -> 0 | AD27: =+'28'!B32 -> 0 | AE27: =+'29'!B32 -> 0 | AF27: =+'30'!B32 -> 0 | AG27: =+'31'!B32 -> 0
A28: - Quickshop | B28: =SUM(C28:AG28) -> 0 | C28: =+'1'!B33 -> 0 | D28: =+'2'!B33 -> 0 | E28: =+'3'!B33 -> 0 | F28: =+'4'!B33 -> 0 | G28: =+'5'!B33 -> 0 | H28: =+'6'!B33 -> 0 | I28: =+'7'!B33 -> 0 | J28: =+'8'!B33 -> 0 | K28: =+'9'!B33 -> 0 | L28: =+'10'!B33 -> 0 | M28: =+'11'!B33 -> 0 | N28: =+'12'!B33 -> 0 | O28: =+'13'!B33 -> 0 | P28: =+'14'!B33 -> 0 | Q28: =+'15'!B33 -> 0 | R28: =+'16'!B33 -> 0 | S28: =+'17'!B33 -> 0 | T28: =+'18'!B33 -> 0 | U28: =+'19'!B33 -> 0 | V28: =+'20'!B33 -> 0 | W28: =+'21'!B33 -> 0 | X28: =+'22'!B33 -> 0 | Y28: =+'23'!B33 -> 0 | Z28: =+'24'!B33 -> 0 | AA28: =+'25'!B33 -> 0 | AB28: =+'26'!B33 -> 0 | AC28: =+'27'!B33 -> 0 | AD28: =+'28'!B33 -> 0 | AE28: =+'29'!B33 -> 0 | AF28: =+'30'!B33 -> 0 | AG28: =+'31'!B33 -> 0
B29: =SUM(B22:B28) -> 0 | C29: =SUM(C22:C28) -> 0 | D29: =SUM(D22:D28) -> 0 | E29: =SUM(E22:E28) -> 0 | F29: =SUM(F22:F28) -> 0 | G29: =SUM(G22:G28) -> 0 | H29: =SUM(H22:H28) -> 0 | I29: =SUM(I22:I28) -> 0 | ... AG29: =SUM(AG22:AG28) -> 0
A32: BANKING | B32: TOTAL
A33: - Cash | B33: =+Bank!AG8+Bank!AG9 -> 11.5
A34: - Cash Drops | B34: =+Bank!AG16 -> 0
A35: - Speedpoint | B35: =+Bank!AG24 -> 19855.45
A36: - Debtors | B36: =+Bank!AG43+Bank!AG44+Bank!AG45 -> 0
A37: - EFT | B37: =+Bank!AG52 -> 0
A38: - Loyalty | B38: =+Bank!AG58 -> 0
A39: - To Settle | B39: =+Bank!AG64 -> 0
A40: - Petty Cash | B40: =-SUM('Petty Cash Report'!B22:AF22) -> 0
A41: - TOTAL BANKING | B41: =SUM(B33:B40) -> 19866.95
A42: - SALES B/FWD | B42: =+B18 -> 0
A43: - OVER / (Under) | B43: =+B41-B42 -> 19866.95

Sheet Dashboard-Performance
B1: =+Input!A1 -> FUEL ROCK (PTY) LTD
B3: Monthly Dashboard | T3: =+Input!B6 -> 46143
B5: Liters Sold: Diesel
O6: LTS SOLD
B7: =+Summary!B7 -> 1659.39 | G7: FUEL RATIOS
B9: Target Litres For The Month | C9: =+'Dashboard-Fuel'!L136 -> 0
B10: As A % Of Target | C10: =+B7/C9 -> #DIV/0!
B12: Liters Sold: ULP 93
B14: =+Summary!C7 -> 40.06
B16: Target Litres For The Month | C16: =+'Dashboard-Fuel'!T136 -> 0
B17: As A % Of Target | C17: =+B14/C16 -> #DIV/0!
B19: Liters Sold: ULP 93
F20: CASHIER SHORTG
B21: =+Summary!D7 -> 1920.7
B23: Target Litres For The Month | C23: =+'Dashboard-Fuel'!P136 -> 0
B24: As A % Of Target | C24: =+B21/C23 -> #DIV/0!
B26: TOTAL LITRES SOLD
B28: =+B7+B14+B21 -> 3620.15
B30: Target Litres For The Month | C30: =+C9+C16+C23 -> 0
B31: As A % Of Target | C31: =+B28/C30 -> #DIV/0!
B33: Quickshop Sales
B35: =+Summary!B22+Summary!B23+Summary!B24+Summary!B28 -> 0
B37: Target Sales For The Month | C37: =+'Dashboard-Retail'!K100+'Dashboard-Retail'!P100 -> 0
B38: As A % Of Target | C38: =+B35/C37 -> #DIV/0!
B40: Cashier Shortages
B43: =+'Cashiers Report'!I37 -> 28206.04

Sheet Dashboard-Fuel
A1: =+Input!B2 -> ENGEN JETPARK
A3: Dashboard: Fuel | B3: =+Input!B6 -> 46143
A104: LITRES SOLD BY GRADE | B104: Diesel | C104: ULP: 95 | D104: ULP: 93 | E104: TOTAL | K104: Diesel | L104: Budget | O104: ULP: 95 | P104: Budget | S104: ULP: 93 | T104: Budget | V104: Budget
A105: 1 | B105: =+'1'!I12 -> 1659.39 | C105: =+'1'!J12 -> 1920.7 | D105: =+'1'!K12 -> 40.06 | E105: =SUM(B105:D105) -> 3620.15 | H105: =+Input!B10 -> Friday | J105: =+A105 -> 1 | K105: =+B105 -> 1659.39 | N105: =+J105 -> 1 | O105: =+C105 -> 1920.7 | R105: =+J105 -> 1 | S105: =+D105 -> 40.06 | V105: =+L105+P105+T105 -> 0
A106: =+A105+1 -> 2 | B106: =+'2'!I12 -> 0 | C106: =+'2'!J12 -> 0 | D106: =+'2'!K12 -> 0 | E106: =SUM(B106:D106) -> 0 | H106: =+Input!B11 -> Saturday | J106: =+A106 -> 2 | K106: =+B106 -> 0 | N106: =+J106 -> 2 | O106: =+C106 -> 0 | R106: =+J106 -> 2 | S106: =+D106 -> 0 | V106: =+L106+P106+T106 -> 0
A107: =+A106+1 -> 3 | B107: =+'3'!I12 -> 0 | C107: =+'3'!J12 -> 0 | D107: =+'3'!K12 -> 0 | E107: =SUM(B107:D107) -> 0 | H107: =+Input!B12 -> Sunday | J107: =+A107 -> 3 | K107: =+B107 -> 0 | N107: =+J107 -> 3 | O107: =+C107 -> 0 | R107: =+J107 -> 3 | S107: =+D107 -> 0 | V107: =+L107+P107+T107 -> 0
A108: =+A107+1 -> 4 | B108: =+'4'!I12 -> 0 | C108: =+'4'!J12 -> 0 | D108: =+'4'!K12 -> 0 | E108: =SUM(B108:D108) -> 0 | H108: =+Input!B13 -> Monday | J108: =+A108 -> 4 | K108: =+B108 -> 0 | N108: =+J108 -> 4 | O108: =+C108 -> 0 | R108: =+J108 -> 4 | S108: =+D108 -> 0 | V108: =+L108+P108+T108 -> 0
A109: =+A108+1 -> 5 | B109: =+'5'!I12 -> 0 | C109: =+'5'!J12 -> 0 | D109: =+'5'!K12 -> 0 | E109: =SUM(B109:D109) -> 0 | H109: =+Input!B14 -> Tuesday | J109: =+A109 -> 5 | K109: =+B109 -> 0 | N109: =+J109 -> 5 | O109: =+C109 -> 0 | R109: =+J109 -> 5 | S109: =+D109 -> 0 | V109: =+L109+P109+T109 -> 0
A110: =+A109+1 -> 6 | B110: =+'6'!I12 -> 0 | C110: =+'6'!J12 -> 0 | D110: =+'6'!K12 -> 0 | E110: =SUM(B110:D110) -> 0 | H110: =+Input!B15 -> Wednesday | J110: =+A110 -> 6 | K110: =+B110 -> 0 | N110: =+J110 -> 6 | O110: =+C110 -> 0 | R110: =+J110 -> 6 | S110: =+D110 -> 0 | V110: =+L110+P110+T110 -> 0
A111: =+A110+1 -> 7 | B111: =+'7'!I12 -> 0 | C111: =+'7'!J12 -> 0 | D111: =+'7'!K12 -> 0 | E111: =SUM(B111:D111) -> 0 | H111: =+Input!B16 -> Thursday | J111: =+A111 -> 7 | K111: =+B111 -> 0 | N111: =+J111 -> 7 | O111: =+C111 -> 0 | R111: =+J111 -> 7 | S111: =+D111 -> 0 | V111: =+L111+P111+T111 -> 0
A112: =+A111+1 -> 8 | B112: =+'8'!I12 -> 0 | C112: =+'8'!J12 -> 0 | D112: =+'8'!K12 -> 0 | E112: =SUM(B112:D112) -> 0 | H112: =+Input!B17 -> Friday | J112: =+A112 -> 8 | K112: =+B112 -> 0 | N112: =+J112 -> 8 | O112: =+C112 -> 0 | R112: =+J112 -> 8 | S112: =+D112 -> 0 | V112: =+L112+P112+T112 -> 0
A113: =+A112+1 -> 9 | B113: =+'9'!I12 -> 0 | C113: =+'9'!J12 -> 0 | D113: =+'9'!K12 -> 0 | E113: =SUM(B113:D113) -> 0 | H113: =+Input!B18 -> Saturday | J113: =+A113 -> 9 | K113: =+B113 -> 0 | N113: =+J113 -> 9 | O113: =+C113 -> 0 | R113: =+J113 -> 9 | S113: =+D113 -> 0 | V113: =+L113+P113+T113 -> 0
A114: =+A113+1 -> 10 | B114: =+'10'!I12 -> 0 | C114: =+'10'!J12 -> 0 | D114: =+'10'!K12 -> 0 | E114: =SUM(B114:D114) -> 0 | H114: =+Input!B19 -> Sunday | J114: =+A114 -> 10 | K114: =+B114 -> 0 | N114: =+J114 -> 10 | O114: =+C114 -> 0 | R114: =+J114 -> 10 | S114: =+D114 -> 0 | V114: =+L114+P114+T114 -> 0
A115: =+A114+1 -> 11 | B115: =+'11'!I12 -> 0 | C115: =+'11'!J12 -> 0 | D115: =+'11'!K12 -> 0 | E115: =SUM(B115:D115) -> 0 | H115: =+Input!B20 -> Monday | J115: =+A115 -> 11 | K115: =+B115 -> 0 | N115: =+J115 -> 11 | O115: =+C115 -> 0 | R115: =+J115 -> 11 | S115: =+D115 -> 0 | V115: =+L115+P115+T115 -> 0
A116: =+A115+1 -> 12 | B116: =+'12'!I12 -> 0 | C116: =+'12'!J12 -> 0 | D116: =+'12'!K12 -> 0 | E116: =SUM(B116:D116) -> 0 | H116: =+Input!B21 -> Tuesday | J116: =+A116 -> 12 | K116: =+B116 -> 0 | N116: =+J116 -> 12 | O116: =+C116 -> 0 | R116: =+J116 -> 12 | S116: =+D116 -> 0 | V116: =+L116+P116+T116 -> 0
A117: =+A116+1 -> 13 | B117: =+'13'!I12 -> 0 | C117: =+'13'!J12 -> 0 | D117: =+'13'!K12 -> 0 | E117: =SUM(B117:D117) -> 0 | H117: =+Input!B22 -> Wednesday | J117: =+A117 -> 13 | K117: =+B117 -> 0 | N117: =+J117 -> 13 | O117: =+C117 -> 0 | R117: =+J117 -> 13 | S117: =+D117 -> 0 | V117: =+L117+P117+T117 -> 0
A118: =+A117+1 -> 14 | B118: =+'14'!I12 -> 0 | C118: =+'14'!J12 -> 0 | D118: =+'14'!K12 -> 0 | E118: =SUM(B118:D118) -> 0 | H118: =+Input!B23 -> Thursday | J118: =+A118 -> 14 | K118: =+B118 -> 0 | N118: =+J118 -> 14 | O118: =+C118 -> 0 | R118: =+J118 -> 14 | S118: =+D118 -> 0 | V118: =+L118+P118+T118 -> 0
A119: =+A118+1 -> 15 | B119: =+'15'!I12 -> 0 | C119: =+'15'!J12 -> 0 | D119: =+'15'!K12 -> 0 | E119: =SUM(B119:D119) -> 0 | H119: =+Input!B24 -> Friday | J119: =+A119 -> 15 | K119: =+B119 -> 0 | N119: =+J119 -> 15 | O119: =+C119 -> 0 | R119: =+J119 -> 15 | S119: =+D119 -> 0 | V119: =+L119+P119+T119 -> 0
A120: =+A119+1 -> 16 | B120: =+'16'!I12 -> 0 | C120: =+'16'!J12 -> 0 | D120: =+'16'!K12 -> 0 | E120: =SUM(B120:D120) -> 0 | H120: =+Input!B25 -> Saturday | J120: =+A120 -> 16 | K120: =+B120 -> 0 | N120: =+J120 -> 16 | O120: =+C120 -> 0 | R120: =+J120 -> 16 | S120: =+D120 -> 0 | V120: =+L120+P120+T120 -> 0
A121: =+A120+1 -> 17 | B121: =+'17'!I12 -> 0 | C121: =+'17'!J12 -> 0 | D121: =+'17'!K12 -> 0 | E121: =SUM(B121:D121) -> 0 | H121: =+Input!B26 -> Sunday | J121: =+A121 -> 17 | K121: =+B121 -> 0 | N121: =+J121 -> 17 | O121: =+C121 -> 0 | R121: =+J121 -> 17 | S121: =+D121 -> 0 | V121: =+L121+P121+T121 -> 0
A122: =+A121+1 -> 18 | B122: =+'18'!I12 -> 0 | C122: =+'18'!J12 -> 0 | D122: =+'18'!K12 -> 0 | E122: =SUM(B122:D122) -> 0 | H122: =+Input!B27 -> Monday | J122: =+A122 -> 18 | K122: =+B122 -> 0 | N122: =+J122 -> 18 | O122: =+C122 -> 0 | R122: =+J122 -> 18 | S122: =+D122 -> 0 | V122: =+L122+P122+T122 -> 0
A123: =+A122+1 -> 19 | B123: =+'19'!I12 -> 0 | C123: =+'19'!J12 -> 0 | D123: =+'19'!K12 -> 0 | E123: =SUM(B123:D123) -> 0 | H123: =+Input!B28 -> Tuesday | J123: =+A123 -> 19 | K123: =+B123 -> 0 | N123: =+J123 -> 19 | O123: =+C123 -> 0 | R123: =+J123 -> 19 | S123: =+D123 -> 0 | V123: =+L123+P123+T123 -> 0
A124: =+A123+1 -> 20 | B124: =+'20'!I12 -> 0 | C124: =+'20'!J12 -> 0 | D124: =+'20'!K12 -> 0 | E124: =SUM(B124:D124) -> 0 | H124: =+Input!B29 -> Wednesday | J124: =+A124 -> 20 | K124: =+B124 -> 0 | N124: =+J124 -> 20 | O124: =+C124 -> 0 | R124: =+J124 -> 20 | S124: =+D124 -> 0 | V124: =+L124+P124+T124 -> 0
A125: =+A124+1 -> 21 | B125: =+'21'!I12 -> 0 | C125: =+'21'!J12 -> 0 | D125: =+'21'!K12 -> 0 | E125: =SUM(B125:D125) -> 0 | H125: =+Input!B30 -> Thursday | J125: =+A125 -> 21 | K125: =+B125 -> 0 | N125: =+J125 -> 21 | O125: =+C125 -> 0 | R125: =+J125 -> 21 | S125: =+D125 -> 0 | V125: =+L125+P125+T125 -> 0
A126: =+A125+1 -> 22 | B126: =+'22'!I12 -> 0 | C126: =+'22'!J12 -> 0 | D126: =+'22'!K12 -> 0 | E126: =SUM(B126:D126) -> 0 | H126: =+Input!B31 -> Friday | J126: =+A126 -> 22 | K126: =+B126 -> 0 | N126: =+J126 -> 22 | O126: =+C126 -> 0 | R126: =+J126 -> 22 | S126: =+D126 -> 0 | V126: =+L126+P126+T126 -> 0
A127: =+A126+1 -> 23 | B127: =+'23'!I12 -> 0 | C127: =+'23'!J12 -> 0 | D127: =+'23'!K12 -> 0 | E127: =SUM(B127:D127) -> 0 | H127: =+Input!B32 -> Saturday | J127: =+A127 -> 23 | K127: =+B127 -> 0 | N127: =+J127 -> 23 | O127: =+C127 -> 0 | R127: =+J127 -> 23 | S127: =+D127 -> 0 | V127: =+L127+P127+T127 -> 0
A128: =+A127+1 -> 24 | B128: =+'24'!I12 -> 0 | C128: =+'24'!J12 -> 0 | D128: =+'24'!K12 -> 0 | E128: =SUM(B128:D128) -> 0 | H128: =+Input!B33 -> Sunday | J128: =+A128 -> 24 | K128: =+B128 -> 0 | N128: =+J128 -> 24 | O128: =+C128 -> 0 | R128: =+J128 -> 24 | S128: =+D128 -> 0 | V128: =+L128+P128+T128 -> 0
A129: =+A128+1 -> 25 | B129: =+'25'!I12 -> 0 | C129: =+'25'!J12 -> 0 | D129: =+'25'!K12 -> 0 | E129: =SUM(B129:D129) -> 0 | H129: =+Input!B34 -> Monday | J129: =+A129 -> 25 | K129: =+B129 -> 0 | N129: =+J129 -> 25 | O129: =+C129 -> 0 | R129: =+J129 -> 25 | S129: =+D129 -> 0 | V129: =+L129+P129+T129 -> 0
A130: =+A129+1 -> 26 | B130: =+'26'!I12 -> 0 | C130: =+'26'!J12 -> 0 | D130: =+'26'!K12 -> 0 | E130: =SUM(B130:D130) -> 0 | H130: =+Input!B35 -> Tuesday | J130: =+A130 -> 26 | K130: =+B130 -> 0 | N130: =+J130 -> 26 | O130: =+C130 -> 0 | R130: =+J130 -> 26 | S130: =+D130 -> 0 | V130: =+L130+P130+T130 -> 0
A131: =+A130+1 -> 27 | B131: =+'27'!I12 -> 0 | C131: =+'27'!J12 -> 0 | D131: =+'27'!K12 -> 0 | E131: =SUM(B131:D131) -> 0 | H131: =+Input!B36 -> Wednesday | J131: =+A131 -> 27 | K131: =+B131 -> 0 | N131: =+J131 -> 27 | O131: =+C131 -> 0 | R131: =+J131 -> 27 | S131: =+D131 -> 0 | V131: =+L131+P131+T131 -> 0
A132: =+A131+1 -> 28 | B132: =+'28'!I12 -> 0 | C132: =+'28'!J12 -> 0 | D132: =+'28'!K12 -> 0 | E132: =SUM(B132:D132) -> 0 | H132: =+Input!B37 -> Thursday | J132: =+A132 -> 28 | K132: =+B132 -> 0 | N132: =+J132 -> 28 | O132: =+C132 -> 0 | R132: =+J132 -> 28 | S132: =+D132 -> 0 | V132: =+L132+P132+T132 -> 0
A133: =+A132+1 -> 29 | B133: =+'29'!I12 -> 0 | C133: =+'29'!J12 -> 0 | D133: =+'29'!K12 -> 0 | E133: =SUM(B133:D133) -> 0 | H133: =+Input!B38 -> Friday | J133: =+A133 -> 29 | K133: =+B133 -> 0 | N133: =+J133 -> 29 | O133: =+C133 -> 0 | R133: =+J133 -> 29 | S133: =+D133 -> 0 | V133: =+L133+P133+T133 -> 0
A134: =+A133+1 -> 30 | B134: =+'30'!I12 -> 0 | C134: =+'30'!J12 -> 0 | D134: =+'30'!K12 -> 0 | E134: =SUM(B134:D134) -> 0 | H134: =+Input!B39 -> Saturday | J134: =+A134 -> 30 | K134: =+B134 -> 0 | N134: =+J134 -> 30 | O134: =+C134 -> 0 | R134: =+J134 -> 30 | S134: =+D134 -> 0 | V134: =+L134+P134+T134 -> 0
A135: =+A134+1 -> 31 | B135: =+'31'!I12 -> 0 | C135: =+'31'!J12 -> 0 | D135: =+'31'!K12 -> 0 | E135: =SUM(B135:D135) -> 0 | H135: =+Input!B40 -> Sunday | J135: =+A135 -> 31 | K135: =+B135 -> 0 | N135: =+J135 -> 31 | O135: =+C135 -> 0 | R135: =+J135 -> 31 | S135: =+D135 -> 0 | V135: =+L135+P135+T135 -> 0
B136: =SUM(B105:B135) -> 1659.39 | C136: =SUM(C105:C135) -> 1920.7 | D136: =SUM(D105:D135) -> 40.06 | E136: =SUM(E105:E135) -> 3620.15 | L136: =SUM(L105:L135) -> 0 | P136: =SUM(P105:P135) -> 0 | T136: =SUM(T105:T135) -> 0 | V136: =SUM(V105:V135) -> 0
A139: CLOSING STOCK | B139: Diesel | C139: ULP: 95 | D139: ULP: 93 | E139: TOTAL
A140: 1 | B140: =+'SS26'!W29 -> 0 | C140: =+'SS26'!W65 -> 0 | D140: =+'SS26'!G101 -> 0 | E140: =SUM(B140:D140) -> 0
A141: =+A140+1 -> 2 | B141: =+'SS26'!W30 -> 0 | C141: =+'SS26'!W66 -> 0 | D141: =+'SS26'!G102 -> 0 | E141: =SUM(B141:D141) -> 0
A142: =+A141+1 -> 3 | B142: =+'SS26'!W31 -> 0 | C142: =+'SS26'!W67 -> 0 | D142: =+'SS26'!G103 -> 0 | E142: =SUM(B142:D142) -> 0
A143: =+A142+1 -> 4 | B143: =+'SS26'!W32 -> 0 | C143: =+'SS26'!W68 -> 0 | D143: =+'SS26'!G104 -> 0 | E143: =SUM(B143:D143) -> 0
A144: =+A143+1 -> 5 | B144: =+'SS26'!W33 -> 0 | C144: =+'SS26'!W69 -> 0 | D144: =+'SS26'!G105 -> 0 | E144: =SUM(B144:D144) -> 0
A145: =+A144+1 -> 6 | B145: =+'SS26'!W34 -> 0 | C145: =+'SS26'!W70 -> 0 | D145: =+'SS26'!G106 -> 0 | E145: =SUM(B145:D145) -> 0
A146: =+A145+1 -> 7 | B146: =+'SS26'!W35 -> 0 | C146: =+'SS26'!W71 -> 0 | D146: =+'SS26'!G107 -> 0 | E146: =SUM(B146:D146) -> 0
A147: =+A146+1 -> 8 | B147: =+'SS26'!W36 -> 0 | C147: =+'SS26'!W72 -> 0 | D147: =+'SS26'!G108 -> 0 | E147: =SUM(B147:D147) -> 0
A148: =+A147+1 -> 9 | B148: =+'SS26'!W37 -> 0 | C148: =+'SS26'!W73 -> 0 | D148: =+'SS26'!G109 -> 0 | E148: =SUM(B148:D148) -> 0
A149: =+A148+1 -> 10 | B149: =+'SS26'!W38 -> 0 | C149: =+'SS26'!W74 -> 0 | D149: =+'SS26'!G110 -> 0 | E149: =SUM(B149:D149) -> 0
A150: =+A149+1 -> 11 | B150: =+'SS26'!W39 -> 0 | C150: =+'SS26'!W75 -> 0 | D150: =+'SS26'!G111 -> 0 | E150: =SUM(B150:D150) -> 0
A151: =+A150+1 -> 12 | B151: =+'SS26'!W40 -> 0 | C151: =+'SS26'!W76 -> 0 | D151: =+'SS26'!G112 -> 0 | E151: =SUM(B151:D151) -> 0
A152: =+A151+1 -> 13 | B152: =+'SS26'!W41 -> 0 | C152: =+'SS26'!W77 -> 0 | D152: =+'SS26'!G113 -> 0 | E152: =SUM(B152:D152) -> 0
... A170: =+A169+1 -> 31 | B170: =+'SS26'!W59 -> 0 | C170: =+'SS26'!W95 -> 0 | D170: =+'SS26'!G131 -> 0 | E170: =SUM(B170:D170) -> 0
B173: 1 | C173: =+B173+1 -> 2 | D173: =+C173+1 -> 3 | E173: =+D173+1 -> 4 | F173: =+E173+1 -> 5 | G173: =+F173+1 -> 6 | H173: =+G173+1 -> 7 | I173: =+H173+1 -> 8 | J173: =+I173+1 -> 9 | ... AF173: =+AE173+1 -> 31
A174: Oil Sales | B174: =+Summary!C26 -> 0 | C174: =+Summary!D26 -> 0 | D174: =+Summary!E26 -> 0 | E174: =+Summary!F26 -> 0 | F174: =+Summary!G26 -> 0 | G174: =+Summary!H26 -> 0 | H174: =+Summary!I26 -> 0 | I174: =+Summary!J26 -> 0 | ... AF174: =+Summary!AG26 -> 0
A175: Budget | B175: =+B177*6% -> 0 | C175: =+C177*6% -> 0 | D175: =+D177*6% -> 0 | E175: =+E177*6% -> 0 | F175: =+F177*6% -> 0 | G175: =+G177*6% -> 0 | H175: =+H177*6% -> 0 | I175: =+I177*6% -> 0 | ... AF175: =+AF177*6% -> 0
A177: Lts Budget | B177: =+V105 -> 0 | C177: =+V106 -> 0 | D177: =+V107 -> 0 | E177: =+V108 -> 0 | F177: =+V109 -> 0 | G177: =+V110 -> 0 | H177: =+V111 -> 0 | I177: =+V112 -> 0 | J177: =+V113 -> 0 | K177: =+V114 -> 0 | L177: =+V115 -> 0 | M177: =+V116 -> 0 | N177: =+V117 -> 0 | O177: =+V118 -> 0 | P177: =+V119 -> 0 | Q177: =+V120 -> 0 | R177: =+V121 -> 0 | S177: =+V122 -> 0 | T177: =+V123 -> 0 | U177: =+V124 -> 0 | V177: =+V125 -> 0 | W177: =+V126 -> 0 | X177: =+V127 -> 0 | Y177: =+V128 -> 0 | Z177: =+V129 -> 0 | AA177: =+V130 -> 0 | AB177: =+V131 -> 0 | AC177: =+V132 -> 0 | AD177: =+V133 -> 0 | AE177: =+V134 -> 0 | AF177: =+V135 -> 0
B180: Diesel | C180: ULP: 95 | D180: ULP: 93 | F180: Diesel | G180: ULP: 95 | H180: ULP: 93
A181: =+A140 -> 1 | B181: =+'1'!B14 -> 23.36 | C181: =+'1'!C14 -> 29.2 | D181: =+'1'!D14 -> 23.25 | F181: =+'1'!B15 -> 21.1987 | G181: =+'1'!C15 -> 26.7753 | H181: =+'1'!D15 -> 21.0887
A182: =+A141 -> 2 | B182: =+'2'!B14 -> 0 | C182: =+'2'!C14 -> 0 | D182: =+'2'!D14 -> 0 | F182: =+'2'!B15 -> 0 | G182: =+'2'!C15 -> 0 | H182: =+'2'!D15 -> 0
A183: =+A142 -> 3 | B183: =+'3'!B14 -> 0 | C183: =+'3'!C14 -> 0 | D183: =+'3'!D14 -> 0 | F183: =+'3'!B15 -> 0 | G183: =+'3'!C15 -> 0 | H183: =+'3'!D15 -> 0
A184: =+A143 -> 4 | B184: =+'4'!B14 -> 0 | C184: =+'4'!C14 -> 0 | D184: =+'4'!D14 -> 0 | F184: =+'4'!B15 -> 0 | G184: =+'4'!C15 -> 0 | H184: =+'4'!D15 -> 0
A185: =+A144 -> 5 | B185: =+'5'!B14 -> 0 | C185: =+'5'!C14 -> 0 | D185: =+'5'!D14 -> 0 | F185: =+'5'!B15 -> 0 | G185: =+'5'!C15 -> 0 | H185: =+'5'!D15 -> 0
A186: =+A145 -> 6 | B186: =+'6'!B14 -> 0 | C186: =+'6'!C14 -> 0 | D186: =+'6'!D14 -> 0 | F186: =+'6'!B15 -> 0 | G186: =+'6'!C15 -> 0 | H186: =+'6'!D15 -> 0
A187: =+A146 -> 7 | B187: =+'7'!B14 -> 0 | C187: =+'7'!C14 -> 0 | D187: =+'7'!D14 -> 0 | F187: =+'7'!B15 -> 0 | G187: =+'7'!C15 -> 0 | H187: =+'7'!D15 -> 0
A188: =+A147 -> 8 | B188: =+'8'!B14 -> 0 | C188: =+'8'!C14 -> 0 | D188: =+'8'!D14 -> 0 | F188: =+'8'!B15 -> 0 | G188: =+'8'!C15 -> 0 | H188: =+'8'!D15 -> 0
A189: =+A148 -> 9 | B189: =+'9'!B14 -> 0 | C189: =+'9'!C14 -> 0 | D189: =+'9'!D14 -> 0 | F189: =+'9'!B15 -> 0 | G189: =+'9'!C15 -> 0 | H189: =+'9'!D15 -> 0
A190: =+A149 -> 10 | B190: =+'10'!B14 -> 0 | C190: =+'10'!C14 -> 0 | D190: =+'10'!D14 -> 0 | F190: =+'10'!B15 -> 0 | G190: =+'10'!C15 -> 0 | H190: =+'10'!D15 -> 0
A191: =+A150 -> 11 | B191: =+'11'!B14 -> 0 | C191: =+'11'!C14 -> 0 | D191: =+'11'!D14 -> 0 | F191: =+'11'!B15 -> 0 | G191: =+'11'!C15 -> 0 | H191: =+'11'!D15 -> 0
A192: =+A151 -> 12 | B192: =+'12'!B14 -> 0 | C192: =+'12'!C14 -> 0 | D192: =+'12'!D14 -> 0 | F192: =+'12'!B15 -> 0 | G192: =+'12'!C15 -> 0 | H192: =+'12'!D15 -> 0
A193: =+A152 -> 13 | B193: =+'13'!B14 -> 0 | C193: =+'13'!C14 -> 0 | D193: =+'13'!D14 -> 0 | F193: =+'13'!B15 -> 0 | G193: =+'13'!C15 -> 0 | H193: =+'13'!D15 -> 0
A194: =+A153 -> 14 | B194: =+'14'!B14 -> 0 | C194: =+'14'!C14 -> 0 | D194: =+'14'!D14 -> 0 | F194: =+'14'!B15 -> 0 | G194: =+'14'!C15 -> 0 | H194: =+'14'!D15 -> 0
A195: =+A154 -> 15 | B195: =+'15'!B14 -> 0 | C195: =+'15'!C14 -> 0 | D195: =+'15'!D14 -> 0 | F195: =+'15'!B15 -> 0 | G195: =+'15'!C15 -> 0 | H195: =+'15'!D15 -> 0
A196: =+A155 -> 16 | B196: =+'16'!B14 -> 0 | C196: =+'16'!C14 -> 0 | D196: =+'16'!D14 -> 0 | F196: =+'16'!B15 -> 0 | G196: =+'16'!C15 -> 0 | H196: =+'16'!D15 -> 0
A197: =+A156 -> 17 | B197: =+'17'!B14 -> 0 | C197: =+'17'!C14 -> 0 | D197: =+'17'!D14 -> 0 | F197: =+'17'!B15 -> 0 | G197: =+'17'!C15 -> 0 | H197: =+'17'!D15 -> 0
A198: =+A157 -> 18 | B198: =+'18'!B14 -> 0 | C198: =+'18'!C14 -> 0 | D198: =+'18'!D14 -> 0 | F198: =+'18'!B15 -> 0 | G198: =+'18'!C15 -> 0 | H198: =+'18'!D15 -> 0
A199: =+A158 -> 19 | B199: =+'19'!B14 -> 0 | C199: =+'19'!C14 -> 0 | D199: =+'19'!D14 -> 0 | F199: =+'19'!B15 -> 0 | G199: =+'19'!C15 -> 0 | H199: =+'19'!D15 -> 0
A200: =+A159 -> 20 | B200: =+'20'!B14 -> 0 | C200: =+'20'!C14 -> 0 | D200: =+'20'!D14 -> 0 | F200: =+'20'!B15 -> 0 | G200: =+'20'!C15 -> 0 | H200: =+'20'!D15 -> 0
A201: =+A160 -> 21 | B201: =+'21'!B14 -> 0 | C201: =+'21'!C14 -> 0 | D201: =+'21'!D14 -> 0 | F201: =+'21'!B15 -> 0 | G201: =+'21'!C15 -> 0 | H201: =+'21'!D15 -> 0
A202: =+A161 -> 22 | B202: =+'22'!B14 -> 0 | C202: =+'22'!C14 -> 0 | D202: =+'22'!D14 -> 0 | F202: =+'22'!B15 -> 0 | G202: =+'22'!C15 -> 0 | H202: =+'22'!D15 -> 0
A203: =+A162 -> 23 | B203: =+'23'!B14 -> 0 | C203: =+'23'!C14 -> 0 | D203: =+'23'!D14 -> 0 | F203: =+'23'!B15 -> 0 | G203: =+'23'!C15 -> 0 | H203: =+'23'!D15 -> 0
A204: =+A163 -> 24 | B204: =+'24'!B14 -> 0 | C204: =+'24'!C14 -> 0 | D204: =+'24'!D14 -> 0 | F204: =+'24'!B15 -> 0 | G204: =+'24'!C15 -> 0 | H204: =+'24'!D15 -> 0
A205: =+A164 -> 25 | B205: =+'25'!B14 -> 0 | C205: =+'25'!C14 -> 0 | D205: =+'25'!D14 -> 0 | F205: =+'25'!B15 -> 0 | G205: =+'25'!C15 -> 0 | H205: =+'25'!D15 -> 0
A206: =+A165 -> 26 | B206: =+'26'!B14 -> 0 | C206: =+'26'!C14 -> 0 | D206: =+'26'!D14 -> 0 | F206: =+'26'!B15 -> 0 | G206: =+'26'!C15 -> 0 | H206: =+'26'!D15 -> 0
A207: =+A166 -> 27 | B207: =+'27'!B14 -> 0 | C207: =+'27'!C14 -> 0 | D207: =+'27'!D14 -> 0 | F207: =+'27'!B15 -> 0 | G207: =+'27'!C15 -> 0 | H207: =+'27'!D15 -> 0
A208: =+A167 -> 28 | B208: =+'28'!B14 -> 0 | C208: =+'28'!C14 -> 0 | D208: =+'28'!D14 -> 0 | F208: =+'28'!B15 -> 0 | G208: =+'28'!C15 -> 0 | H208: =+'28'!D15 -> 0
A209: =+A168 -> 29 | B209: =+'29'!B14 -> 0 | C209: =+'29'!C14 -> 0 | D209: =+'29'!D14 -> 0 | F209: =+'29'!B15 -> 0 | G209: =+'29'!C15 -> 0 | H209: =+'29'!D15 -> 0
A210: =+A169 -> 30 | B210: =+'30'!B14 -> 0 | C210: =+'30'!C14 -> 0 | D210: =+'30'!D14 -> 0 | F210: =+'30'!B15 -> 0 | G210: =+'30'!C15 -> 0 | H210: =+'30'!D15 -> 0
A211: =+A170 -> 31 | B211: =+'31'!B14 -> 0 | C211: =+'31'!C14 -> 0 | D211: =+'31'!D14 -> 0 | F211: =+'31'!B15 -> 0 | G211: =+'31'!C15 -> 0 | H211: =+'31'!D15 -> 0

Sheet Dashboard-Retail
A1: =+Input!B2 -> ENGEN JETPARK
A3: Dashboard: Retail | B3: =+Input!B6 -> 46143
A60: SALES BY DIVISION | B60: 1 | C60: =+B60+1 -> 2 | D60: =+C60+1 -> 3 | E60: =+D60+1 -> 4 | F60: =+E60+1 -> 5 | G60: =+F60+1 -> 6 | H60: =+G60+1 -> 7 | I60: =+H60+1 -> 8 | J60: =+I60+1 -> 9 | ... AF60: =+AE60+1 -> 31
A61: - Bakery | B61: =SUM(Summary!C22:C24) -> 0 | C61: =SUM(Summary!D22:D24) -> 0 | D61: =SUM(Summary!E22:E24) -> 0 | E61: =SUM(Summary!F22:F24) -> 0 | F61: =SUM(Summary!G22:G24) -> 0 | G61: =SUM(Summary!H22:H24) -> 0 | H61: =SUM(Summary!I22:I24) -> 0 | I61: =SUM(Summary!J22:J24) -> 0 | ... AF61: =SUM(Summary!AG22:AG24) -> 0
A62: - VV | B62: =+Summary!C27 -> 0 | C62: =+Summary!D27 -> 0 | D62: =+Summary!E27 -> 0 | E62: =+Summary!F27 -> 0 | F62: =+Summary!G27 -> 0 | G62: =+Summary!H27 -> 0 | H62: =+Summary!I27 -> 0 | I62: =+Summary!J27 -> 0 | ... AF62: =+Summary!AG27 -> 0
A63: - Quickshop | B63: =+Summary!C28 -> 0 | C63: =+Summary!D28 -> 0 | D63: =+Summary!E28 -> 0 | E63: =+Summary!F28 -> 0 | F63: =+Summary!G28 -> 0 | G63: =+Summary!H28 -> 0 | H63: =+Summary!I28 -> 0 | I63: =+Summary!J28 -> 0 | ... AF63: =+Summary!AG28 -> 0
B64: =SUM(B61:B63) -> 0 | C64: =SUM(C61:C63) -> 0 | D64: =SUM(D61:D63) -> 0 | E64: =SUM(E61:E63) -> 0 | F64: =SUM(F61:F63) -> 0 | G64: =SUM(G61:G63) -> 0 | H64: =SUM(H61:H63) -> 0 | I64: =SUM(I61:I63) -> 0 | ... AF64: =SUM(AF61:AF63) -> 0
J67: Bakery | O67: C/Store
B68: Lts | D68: Bakery | F68: Conven | J68: Actual | K68: Budget | O68: Actual | P68: Budget
A69: 1 | B69: =+'Dashboard-Fuel'!V105 -> 0 | C69: 0.3 | D69: =+B69*C69 -> 0 | E69: 0.85 | F69: =+B69*E69 -> 0 | I69: =+A69 -> 1 | J69: =+B61 -> 0 | K69: =+D69 -> 0 | N69: =+I69 -> 1 | O69: =+B63 -> 0 | P69: =+F69 -> 0
A70: =+A69+1 -> 2 | B70: =+'Dashboard-Fuel'!V106 -> 0 | C70: =+$C$69 -> 0.3 | D70: =+B70*C70 -> 0 | E70: =+$E$69 -> 0.85 | F70: =+B70*E70 -> 0 | I70: =+A70 -> 2 | J70: =+C61 -> 0 | K70: =+D70 -> 0 | N70: =+I70 -> 2 | O70: =+C63 -> 0 | P70: 0
A71: =+A70+1 -> 3 | B71: =+'Dashboard-Fuel'!V107 -> 0 | C71: =+$C$69 -> 0.3 | D71: =+B71*C71 -> 0 | E71: =+$E$69 -> 0.85 | F71: =+B71*E71 -> 0 | I71: =+A71 -> 3 | J71: =+D61 -> 0 | K71: =+D71 -> 0 | N71: =+I71 -> 3 | O71: =+D63 -> 0 | P71: =+F71 -> 0
A72: =+A71+1 -> 4 | B72: =+'Dashboard-Fuel'!V108 -> 0 | C72: =+$C$69 -> 0.3 | D72: =+B72*C72 -> 0 | E72: =+$E$69 -> 0.85 | F72: =+B72*E72 -> 0 | I72: =+A72 -> 4 | J72: =+E61 -> 0 | K72: =+D72 -> 0 | N72: =+I72 -> 4 | O72: =+E63 -> 0 | P72: =+F72 -> 0
A73: =+A72+1 -> 5 | B73: =+'Dashboard-Fuel'!V109 -> 0 | C73: =+$C$69 -> 0.3 | D73: =+B73*C73 -> 0 | E73: =+$E$69 -> 0.85 | F73: =+B73*E73 -> 0 | I73: =+A73 -> 5 | J73: =+F61 -> 0 | K73: =+D73 -> 0 | N73: =+I73 -> 5 | O73: =+F63 -> 0 | P73: =+F73 -> 0
A74: =+A73+1 -> 6 | B74: =+'Dashboard-Fuel'!V110 -> 0 | C74: =+$C$69 -> 0.3 | D74: =+B74*C74 -> 0 | E74: =+$E$69 -> 0.85 | F74: =+B74*E74 -> 0 | I74: =+A74 -> 6 | J74: =+G61 -> 0 | K74: =+D74 -> 0 | N74: =+I74 -> 6 | O74: =+G63 -> 0 | P74: =+F74 -> 0
A75: =+A74+1 -> 7 | B75: =+'Dashboard-Fuel'!V111 -> 0 | C75: =+$C$69 -> 0.3 | D75: =+B75*C75 -> 0 | E75: =+$E$69 -> 0.85 | F75: =+B75*E75 -> 0 | I75: =+A75 -> 7 | J75: =+H61 -> 0 | K75: =+D75 -> 0 | N75: =+I75 -> 7 | O75: =+H63 -> 0 | P75: =+F75 -> 0
A76: =+A75+1 -> 8 | B76: =+'Dashboard-Fuel'!V112 -> 0 | C76: =+$C$69 -> 0.3 | D76: =+B76*C76 -> 0 | E76: =+$E$69 -> 0.85 | F76: =+B76*E76 -> 0 | I76: =+A76 -> 8 | J76: =+I61 -> 0 | K76: =+D76 -> 0 | N76: =+I76 -> 8 | O76: =+I63 -> 0 | P76: =+F76 -> 0
A77: =+A76+1 -> 9 | B77: =+'Dashboard-Fuel'!V113 -> 0 | C77: =+$C$69 -> 0.3 | D77: =+B77*C77 -> 0 | E77: =+$E$69 -> 0.85 | F77: =+B77*E77 -> 0 | I77: =+A77 -> 9 | J77: =+J61 -> 0 | K77: =+D77 -> 0 | N77: =+I77 -> 9 | O77: =+J63 -> 0 | P77: =+F77 -> 0
A78: =+A77+1 -> 10 | B78: =+'Dashboard-Fuel'!V114 -> 0 | C78: =+$C$69 -> 0.3 | D78: =+B78*C78 -> 0 | E78: =+$E$69 -> 0.85 | F78: =+B78*E78 -> 0 | I78: =+A78 -> 10 | J78: =+K61 -> 0 | K78: =+D78 -> 0 | N78: =+I78 -> 10 | O78: =+K63 -> 0 | P78: =+F78 -> 0
A79: =+A78+1 -> 11 | B79: =+'Dashboard-Fuel'!V115 -> 0 | C79: =+$C$69 -> 0.3 | D79: =+B79*C79 -> 0 | E79: =+$E$69 -> 0.85 | F79: =+B79*E79 -> 0 | I79: =+A79 -> 11 | J79: =+L61 -> 0 | K79: =+D79 -> 0 | N79: =+I79 -> 11 | O79: =+L63 -> 0 | P79: =+F79 -> 0
A80: =+A79+1 -> 12 | B80: =+'Dashboard-Fuel'!V116 -> 0 | C80: =+$C$69 -> 0.3 | D80: =+B80*C80 -> 0 | E80: =+$E$69 -> 0.85 | F80: =+B80*E80 -> 0 | I80: =+A80 -> 12 | J80: =+M61 -> 0 | K80: =+D80 -> 0 | N80: =+I80 -> 12 | O80: =+M63 -> 0 | P80: =+F80 -> 0
A81: =+A80+1 -> 13 | B81: =+'Dashboard-Fuel'!V117 -> 0 | C81: =+$C$69 -> 0.3 | D81: =+B81*C81 -> 0 | E81: =+$E$69 -> 0.85 | F81: =+B81*E81 -> 0 | I81: =+A81 -> 13 | J81: =+N61 -> 0 | K81: =+D81 -> 0 | N81: =+I81 -> 13 | O81: =+N63 -> 0 | P81: =+F81 -> 0
A82: =+A81+1 -> 14 | B82: =+'Dashboard-Fuel'!V118 -> 0 | C82: =+$C$69 -> 0.3 | D82: =+B82*C82 -> 0 | E82: =+$E$69 -> 0.85 | F82: =+B82*E82 -> 0 | I82: =+A82 -> 14 | J82: =+O61 -> 0 | K82: =+D82 -> 0 | N82: =+I82 -> 14 | O82: =+O63 -> 0 | P82: =+F82 -> 0
A83: =+A82+1 -> 15 | B83: =+'Dashboard-Fuel'!V119 -> 0 | C83: =+$C$69 -> 0.3 | D83: =+B83*C83 -> 0 | E83: =+$E$69 -> 0.85 | F83: =+B83*E83 -> 0 | I83: =+A83 -> 15 | J83: =+P61 -> 0 | K83: =+D83 -> 0 | N83: =+I83 -> 15 | O83: =+P63 -> 0 | P83: =+F83 -> 0
A84: =+A83+1 -> 16 | B84: =+'Dashboard-Fuel'!V120 -> 0 | C84: =+$C$69 -> 0.3 | D84: =+B84*C84 -> 0 | E84: =+$E$69 -> 0.85 | F84: =+B84*E84 -> 0 | I84: =+A84 -> 16 | J84: =+Q61 -> 0 | K84: =+D84 -> 0 | N84: =+I84 -> 16 | O84: =+Q63 -> 0 | P84: =+F84 -> 0
A85: =+A84+1 -> 17 | B85: =+'Dashboard-Fuel'!V121 -> 0 | C85: =+$C$69 -> 0.3 | D85: =+B85*C85 -> 0 | E85: =+$E$69 -> 0.85 | F85: =+B85*E85 -> 0 | I85: =+A85 -> 17 | J85: =+R61 -> 0 | K85: =+D85 -> 0 | N85: =+I85 -> 17 | O85: =+R63 -> 0 | P85: =+F85 -> 0
A86: =+A85+1 -> 18 | B86: =+'Dashboard-Fuel'!V122 -> 0 | C86: =+$C$69 -> 0.3 | D86: =+B86*C86 -> 0 | E86: =+$E$69 -> 0.85 | F86: =+B86*E86 -> 0 | I86: =+A86 -> 18 | J86: =+S61 -> 0 | K86: =+D86 -> 0 | N86: =+I86 -> 18 | O86: =+S63 -> 0 | P86: =+F86 -> 0
A87: =+A86+1 -> 19 | B87: =+'Dashboard-Fuel'!V123 -> 0 | C87: =+$C$69 -> 0.3 | D87: =+B87*C87 -> 0 | E87: =+$E$69 -> 0.85 | F87: =+B87*E87 -> 0 | I87: =+A87 -> 19 | J87: =+T61 -> 0 | K87: =+D87 -> 0 | N87: =+I87 -> 19 | O87: =+T63 -> 0 | P87: =+F87 -> 0
A88: =+A87+1 -> 20 | B88: =+'Dashboard-Fuel'!V124 -> 0 | C88: =+$C$69 -> 0.3 | D88: =+B88*C88 -> 0 | E88: =+$E$69 -> 0.85 | F88: =+B88*E88 -> 0 | I88: =+A88 -> 20 | J88: =+U61 -> 0 | K88: =+D88 -> 0 | N88: =+I88 -> 20 | O88: =+U63 -> 0 | P88: =+F88 -> 0
A89: =+A88+1 -> 21 | B89: =+'Dashboard-Fuel'!V125 -> 0 | C89: =+$C$69 -> 0.3 | D89: =+B89*C89 -> 0 | E89: =+$E$69 -> 0.85 | F89: =+B89*E89 -> 0 | I89: =+A89 -> 21 | J89: =+V61 -> 0 | K89: =+D89 -> 0 | N89: =+I89 -> 21 | O89: =+V63 -> 0 | P89: =+F89 -> 0
A90: =+A89+1 -> 22 | B90: =+'Dashboard-Fuel'!V126 -> 0 | C90: =+$C$69 -> 0.3 | D90: =+B90*C90 -> 0 | E90: =+$E$69 -> 0.85 | F90: =+B90*E90 -> 0 | I90: =+A90 -> 22 | J90: =+W61 -> 0 | K90: =+D90 -> 0 | N90: =+I90 -> 22 | O90: =+W63 -> 0 | P90: =+F90 -> 0
A91: =+A90+1 -> 23 | B91: =+'Dashboard-Fuel'!V127 -> 0 | C91: =+$C$69 -> 0.3 | D91: =+B91*C91 -> 0 | E91: =+$E$69 -> 0.85 | F91: =+B91*E91 -> 0 | I91: =+A91 -> 23 | J91: =+X61 -> 0 | K91: =+D91 -> 0 | N91: =+I91 -> 23 | O91: =+X63 -> 0 | P91: =+F91 -> 0
A92: =+A91+1 -> 24 | B92: =+'Dashboard-Fuel'!V128 -> 0 | C92: =+$C$69 -> 0.3 | D92: =+B92*C92 -> 0 | E92: =+$E$69 -> 0.85 | F92: =+B92*E92 -> 0 | I92: =+A92 -> 24 | J92: =+Y61 -> 0 | K92: =+D92 -> 0 | N92: =+I92 -> 24 | O92: =+Y63 -> 0 | P92: =+F92 -> 0
A93: =+A92+1 -> 25 | B93: =+'Dashboard-Fuel'!V129 -> 0 | C93: =+$C$69 -> 0.3 | D93: =+B93*C93 -> 0 | E93: =+$E$69 -> 0.85 | F93: =+B93*E93 -> 0 | I93: =+A93 -> 25 | J93: =+Z61 -> 0 | K93: =+D93 -> 0 | N93: =+I93 -> 25 | O93: =+Z63 -> 0 | P93: =+F93 -> 0
A94: =+A93+1 -> 26 | B94: =+'Dashboard-Fuel'!V130 -> 0 | C94: =+$C$69 -> 0.3 | D94: =+B94*C94 -> 0 | E94: =+$E$69 -> 0.85 | F94: =+B94*E94 -> 0 | I94: =+A94 -> 26 | J94: =+AA61 -> 0 | K94: =+D94 -> 0 | N94: =+I94 -> 26 | O94: =+AA63 -> 0 | P94: =+F94 -> 0
A95: =+A94+1 -> 27 | B95: =+'Dashboard-Fuel'!V131 -> 0 | C95: =+$C$69 -> 0.3 | D95: =+B95*C95 -> 0 | E95: =+$E$69 -> 0.85 | F95: =+B95*E95 -> 0 | I95: =+A95 -> 27 | J95: =+AB61 -> 0 | K95: =+D95 -> 0 | N95: =+I95 -> 27 | O95: =+AB63 -> 0 | P95: =+F95 -> 0
A96: =+A95+1 -> 28 | B96: =+'Dashboard-Fuel'!V132 -> 0 | C96: =+$C$69 -> 0.3 | D96: =+B96*C96 -> 0 | E96: =+$E$69 -> 0.85 | F96: =+B96*E96 -> 0 | I96: =+A96 -> 28 | J96: =+AC61 -> 0 | K96: =+D96 -> 0 | N96: =+I96 -> 28 | O96: =+AC63 -> 0 | P96: =+F96 -> 0
A97: =+A96+1 -> 29 | B97: =+'Dashboard-Fuel'!V133 -> 0 | C97: =+$C$69 -> 0.3 | D97: =+B97*C97 -> 0 | E97: =+$E$69 -> 0.85 | F97: =+B97*E97 -> 0 | I97: =+A97 -> 29 | J97: =+AD61 -> 0 | K97: =+D97 -> 0 | N97: =+I97 -> 29 | O97: =+AD63 -> 0 | P97: =+F97 -> 0
A98: =+A97+1 -> 30 | B98: =+'Dashboard-Fuel'!V134 -> 0 | C98: =+$C$69 -> 0.3 | D98: =+B98*C98 -> 0 | E98: =+$E$69 -> 0.85 | F98: =+B98*E98 -> 0 | I98: =+A98 -> 30 | J98: =+AE61 -> 0 | K98: =+D98 -> 0 | N98: =+I98 -> 30 | O98: =+AE63 -> 0 | P98: =+F98 -> 0
A99: =+A98+1 -> 31 | B99: =+'Dashboard-Fuel'!V135 -> 0 | C99: =+$C$69 -> 0.3 | D99: =+B99*C99 -> 0 | E99: =+$E$69 -> 0.85 | F99: =+B99*E99 -> 0 | I99: =+A99 -> 31 | J99: =+AF61 -> 0 | K99: =+D99 -> 0 | N99: =+I99 -> 31 | O99: =+AF63 -> 0 | P99: =+F99 -> 0
D100: =SUM(D69:D99) -> 0 | F100: =SUM(F69:F99) -> 0 | J100: =SUM(J69:J99) -> 0 | K100: =SUM(K69:K99) -> 0 | O100: =SUM(O69:O99) -> 0 | P100: =SUM(P69:P99) -> 0

Sheet Cashiers Report
A1: =+Input!B2 -> ENGEN JETPARK
A3: Cashiers Report | C3: =+Input!B6 -> 46143
A5: Day | B5: Date | C5: =+Input!B44 -> Mandla | D5: =+Input!C44 -> Caroline | E5: =+Input!D44 -> Siyabonga | F5: =+Input!E44 -> Thumelo | G5: =+Input!F44 -> Cashier 5 | H5: =+Input!G44 -> Cashier 6 | I5: TOTAL | J5: CT | K5: VARIANCE
A6: =+Input!B10 -> Friday | B6: =+Input!C10 -> 46143 | C6: =+'1'!B53 -> 33206.04 | D6: =+'1'!C53 -> -1000 | E6: =+'1'!D53 -> -1000 | F6: =+'1'!E53 -> -1000 | G6: =+'1'!F53 -> -1000 | H6: =+'1'!G53 -> -1000 | I6: =SUM(C6:H6) -> 28206.04 | J6: =+'1'!H53 -> 28206.04 | K6: =+J6-I6 -> 0
A7: =+Input!B11 -> Saturday | B7: =+Input!C11 -> 46144 | C7: =+'2'!B53 -> 0 | D7: =+'2'!C53 -> 0 | E7: =+'2'!D53 -> 0 | F7: =+'2'!E53 -> 0 | G7: =+'2'!F53 -> 0 | H7: =+'2'!G53 -> 0 | I7: =SUM(C7:H7) -> 0 | J7: =+'2'!H53 -> 0 | K7: =+J7-I7 -> 0
A8: =+Input!B12 -> Sunday | B8: =+Input!C12 -> 46145 | C8: =+'3'!B53 -> 0 | D8: =+'3'!C53 -> 0 | E8: =+'3'!D53 -> 0 | F8: =+'3'!E53 -> 0 | G8: =+'3'!F53 -> 0 | H8: =+'3'!G53 -> 0 | I8: =SUM(C8:H8) -> 0 | J8: =+'3'!H53 -> 0 | K8: =+J8-I8 -> 0
A9: =+Input!B13 -> Monday | B9: =+Input!C13 -> 46146 | C9: =+'4'!B53 -> 0 | D9: =+'4'!C53 -> 0 | E9: =+'4'!D53 -> 0 | F9: =+'4'!E53 -> 0 | G9: =+'4'!F53 -> 0 | H9: =+'4'!G53 -> 0 | I9: =SUM(C9:H9) -> 0 | J9: =+'4'!H53 -> 0 | K9: =+J9-I9 -> 0
A10: =+Input!B14 -> Tuesday | B10: =+Input!C14 -> 46147 | C10: =+'5'!B53 -> 0 | D10: =+'5'!C53 -> 0 | E10: =+'5'!D53 -> 0 | F10: =+'5'!E53 -> 0 | G10: =+'5'!F53 -> 0 | H10: =+'5'!G53 -> 0 | I10: =SUM(C10:H10) -> 0 | J10: =+'5'!H53 -> 0 | K10: =+J10-I10 -> 0
A11: =+Input!B15 -> Wednesday | B11: =+Input!C15 -> 46148 | C11: =+'6'!B53 -> 0 | D11: =+'6'!C53 -> 0 | E11: =+'6'!D53 -> 0 | F11: =+'6'!E53 -> 0 | G11: =+'6'!F53 -> 0 | H11: =+'6'!G53 -> 0 | I11: =SUM(C11:H11) -> 0 | J11: =+'6'!H53 -> 0 | K11: =+J11-I11 -> 0
A12: =+Input!B16 -> Thursday | B12: =+Input!C16 -> 46149 | C12: =+'7'!B53 -> 0 | D12: =+'7'!C53 -> 0 | E12: =+'7'!D53 -> 0 | F12: =+'7'!E53 -> 0 | G12: =+'7'!F53 -> 0 | H12: =+'7'!G53 -> 0 | I12: =SUM(C12:H12) -> 0 | J12: =+'7'!H53 -> 0 | K12: =+J12-I12 -> 0
A13: =+Input!B17 -> Friday | B13: =+Input!C17 -> 46150 | C13: =+'8'!B53 -> 0 | D13: =+'8'!C53 -> 0 | E13: =+'8'!D53 -> 0 | F13: =+'8'!E53 -> 0 | G13: =+'8'!F53 -> 0 | H13: =+'8'!G53 -> 0 | I13: =SUM(C13:H13) -> 0 | J13: =+'8'!H53 -> 0 | K13: =+J13-I13 -> 0
A14: =+Input!B18 -> Saturday | B14: =+Input!C18 -> 46151 | C14: =+'9'!B53 -> 0 | D14: =+'9'!C53 -> 0 | E14: =+'9'!D53 -> 0 | F14: =+'9'!E53 -> 0 | G14: =+'9'!F53 -> 0 | H14: =+'9'!G53 -> 0 | I14: =SUM(C14:H14) -> 0 | J14: =+'9'!H53 -> 0 | K14: =+J14-I14 -> 0
A15: =+Input!B19 -> Sunday | B15: =+Input!C19 -> 46152 | C15: =+'10'!B53 -> 0 | D15: =+'10'!C53 -> 0 | E15: =+'10'!D53 -> 0 | F15: =+'10'!E53 -> 0 | G15: =+'10'!F53 -> 0 | H15: =+'10'!G53 -> 0 | I15: =SUM(C15:H15) -> 0 | J15: =+'10'!H53 -> 0 | K15: =+J15-I15 -> 0
A16: =+Input!B20 -> Monday | B16: =+Input!C20 -> 46153 | C16: =+'11'!B53 -> 0 | D16: =+'11'!C53 -> 0 | E16: =+'11'!D53 -> 0 | F16: =+'11'!E53 -> 0 | G16: =+'11'!F53 -> 0 | H16: =+'11'!G53 -> 0 | I16: =SUM(C16:H16) -> 0 | J16: =+'11'!H53 -> 0 | K16: =+J16-I16 -> 0
A17: =+Input!B21 -> Tuesday | B17: =+Input!C21 -> 46154 | C17: =+'12'!B53 -> 0 | D17: =+'12'!C53 -> 0 | E17: =+'12'!D53 -> 0 | F17: =+'12'!E53 -> 0 | G17: =+'12'!F53 -> 0 | H17: =+'12'!G53 -> 0 | I17: =SUM(C17:H17) -> 0 | J17: =+'12'!H53 -> 0 | K17: =+J17-I17 -> 0
A18: =+Input!B22 -> Wednesday | B18: =+Input!C22 -> 46155 | C18: =+'13'!B53 -> 0 | D18: =+'13'!C53 -> 0 | E18: =+'13'!D53 -> 0 | F18: =+'13'!E53 -> 0 | G18: =+'13'!F53 -> 0 | H18: =+'13'!G53 -> 0 | I18: =SUM(C18:H18) -> 0 | J18: =+'13'!B53 -> 0 | K18: =+J18-I18 -> 0
A19: =+Input!B23 -> Thursday | B19: =+Input!C23 -> 46156 | C19: =+'14'!B53 -> 0 | D19: =+'14'!C53 -> 0 | E19: =+'14'!D53 -> 0 | F19: =+'14'!E53 -> 0 | G19: =+'14'!F53 -> 0 | H19: =+'14'!G53 -> 0 | I19: =SUM(C19:H19) -> 0 | J19: =+'14'!H53 -> 0 | K19: =+J19-I19 -> 0
A20: =+Input!B24 -> Friday | B20: =+Input!C24 -> 46157 | C20: =+'15'!B53 -> 0 | D20: =+'15'!C53 -> 0 | E20: =+'15'!D53 -> 0 | F20: =+'15'!E53 -> 0 | G20: =+'15'!F53 -> 0 | H20: =+'15'!G53 -> 0 | I20: =SUM(C20:H20) -> 0 | J20: =+'15'!H53 -> 0 | K20: =+J20-I20 -> 0
A21: =+Input!B25 -> Saturday | B21: =+Input!C25 -> 46158 | C21: =+'16'!B53 -> 0 | D21: =+'16'!C53 -> 0 | E21: =+'16'!D53 -> 0 | F21: =+'16'!E53 -> 0 | G21: =+'16'!F53 -> 0 | H21: =+'16'!G53 -> 0 | I21: =SUM(C21:H21) -> 0 | J21: =+'16'!H53 -> 0 | K21: =+J21-I21 -> 0
A22: =+Input!B26 -> Sunday | B22: =+Input!C26 -> 46159 | C22: =+'17'!B53 -> 0 | D22: =+'17'!C53 -> 0 | E22: =+'17'!D53 -> 0 | F22: =+'17'!E53 -> 0 | G22: =+'17'!F53 -> 0 | H22: =+'17'!G53 -> 0 | I22: =SUM(C22:H22) -> 0 | J22: =+'17'!H53 -> 0 | K22: =+J22-I22 -> 0
A23: =+Input!B27 -> Monday | B23: =+Input!C27 -> 46160 | C23: =+'18'!B53 -> 0 | D23: =+'18'!C53 -> 0 | E23: =+'18'!D53 -> 0 | F23: =+'18'!E53 -> 0 | G23: =+'18'!F53 -> 0 | H23: =+'18'!G53 -> 0 | I23: =SUM(C23:H23) -> 0 | J23: =+'18'!H53 -> 0 | K23: =+J23-I23 -> 0
A24: =+Input!B28 -> Tuesday | B24: =+Input!C28 -> 46161 | C24: =+'19'!B53 -> 0 | D24: =+'19'!C53 -> 0 | E24: =+'19'!D53 -> 0 | F24: =+'19'!E53 -> 0 | G24: =+'19'!F53 -> 0 | H24: =+'19'!G53 -> 0 | I24: =SUM(C24:H24) -> 0 | J24: =+'19'!H53 -> 0 | K24: =+J24-I24 -> 0
A25: =+Input!B29 -> Wednesday | B25: =+Input!C29 -> 46162 | C25: =+'20'!B53 -> 0 | D25: =+'20'!C53 -> 0 | E25: =+'20'!D53 -> 0 | F25: =+'20'!E53 -> 0 | G25: =+'20'!F53 -> 0 | H25: =+'20'!G53 -> 0 | I25: =SUM(C25:H25) -> 0 | J25: =+'20'!H53 -> 0 | K25: =+J25-I25 -> 0
A26: =+Input!B30 -> Thursday | B26: =+Input!C30 -> 46163 | C26: =+'21'!B53 -> 0 | D26: =+'21'!C53 -> 0 | E26: =+'21'!D53 -> 0 | F26: =+'21'!E53 -> 0 | G26: =+'21'!F53 -> 0 | H26: =+'21'!G53 -> 0 | I26: =SUM(C26:H26) -> 0 | J26: =+'21'!H53 -> 0 | K26: =+J26-I26 -> 0
A27: =+Input!B31 -> Friday | B27: =+Input!C31 -> 46164 | C27: =+'22'!B53 -> 0 | D27: =+'22'!C53 -> 0 | E27: =+'22'!D53 -> 0 | F27: =+'22'!E53 -> 0 | G27: =+'22'!F53 -> 0 | H27: =+'22'!G53 -> 0 | I27: =SUM(C27:H27) -> 0 | J27: =+'22'!H53 -> 0 | K27: =+J27-I27 -> 0
A28: =+Input!B32 -> Saturday | B28: =+Input!C32 -> 46165 | C28: =+'23'!B53 -> 0 | D28: =+'23'!C53 -> 0 | E28: =+'23'!D53 -> 0 | F28: =+'23'!E53 -> 0 | G28: =+'23'!F53 -> 0 | H28: =+'23'!G53 -> 0 | I28: =SUM(C28:H28) -> 0 | J28: =+'23'!H53 -> 0 | K28: =+J28-I28 -> 0
A29: =+Input!B33 -> Sunday | B29: =+Input!C33 -> 46166 | C29: =+'24'!B53 -> 0 | D29: =+'24'!C53 -> 0 | E29: =+'24'!D53 -> 0 | F29: =+'24'!E53 -> 0 | G29: =+'24'!F53 -> 0 | H29: =+'24'!G53 -> 0 | I29: =SUM(C29:H29) -> 0 | J29: =+'24'!H53 -> 0 | K29: =+J29-I29 -> 0
A30: =+Input!B34 -> Monday | B30: =+Input!C34 -> 46167 | C30: =+'25'!B53 -> 0 | D30: =+'25'!C53 -> 0 | E30: =+'25'!D53 -> 0 | F30: =+'25'!E53 -> 0 | G30: =+'25'!F53 -> 0 | H30: =+'25'!G53 -> 0 | I30: =SUM(C30:H30) -> 0 | J30: =+'25'!H53 -> 0 | K30: =+J30-I30 -> 0
A31: =+Input!B35 -> Tuesday | B31: =+Input!C35 -> 46168 | C31: =+'26'!B53 -> 0 | D31: =+'26'!C53 -> 0 | E31: =+'26'!D53 -> 0 | F31: =+'26'!E53 -> 0 | G31: =+'26'!F53 -> 0 | H31: =+'26'!G53 -> 0 | I31: =SUM(C31:H31) -> 0 | J31: =+'26'!H53 -> 0 | K31: =+J31-I31 -> 0
A32: =+Input!B36 -> Wednesday | B32: =+Input!C36 -> 46169 | C32: =+'27'!B53 -> 0 | D32: =+'27'!C53 -> 0 | E32: =+'27'!D53 -> 0 | F32: =+'27'!E53 -> 0 | G32: =+'27'!F53 -> 0 | H32: =+'27'!G53 -> 0 | I32: =SUM(C32:H32) -> 0 | J32: =+'27'!H53 -> 0 | K32: =+J32-I32 -> 0
A33: =+Input!B37 -> Thursday | B33: =+Input!C37 -> 46170 | C33: =+'28'!B53 -> 0 | D33: =+'28'!C53 -> 0 | E33: =+'28'!D53 -> 0 | F33: =+'28'!E53 -> 0 | G33: =+'28'!F53 -> 0 | H33: =+'28'!G53 -> 0 | I33: =SUM(C33:H33) -> 0 | J33: =+'28'!H53 -> 0 | K33: =+J33-I33 -> 0
A34: =+Input!B38 -> Friday | B34: =+Input!C38 -> 46171 | C34: =+'29'!B53 -> 0 | D34: =+'29'!C53 -> 0 | E34: =+'29'!D53 -> 0 | F34: =+'29'!E53 -> 0 | G34: =+'29'!F53 -> 0 | H34: =+'29'!G53 -> 0 | I34: =SUM(C34:H34) -> 0 | J34: =+'29'!H53 -> 0 | K34: =+J34-I34 -> 0
A35: =+Input!B39 -> Saturday | B35: =+Input!C39 -> 46172 | C35: =+'30'!B53 -> 0 | D35: =+'30'!C53 -> 0 | E35: =+'30'!D53 -> 0 | F35: =+'30'!E53 -> 0 | G35: =+'30'!F53 -> 0 | H35: =+'30'!G53 -> 0 | I35: =SUM(C35:H35) -> 0 | J35: =+'30'!H53 -> 0 | K35: =+J35-I35 -> 0
A36: =+Input!B40 -> Sunday | B36: =+Input!C40 -> 46173 | C36: =+'31'!B53 -> 0 | D36: =+'31'!C53 -> 0 | E36: =+'31'!D53 -> 0 | F36: =+'31'!E53 -> 0 | G36: =+'31'!F53 -> 0 | H36: =+'31'!G53 -> 0 | I36: =SUM(C36:H36) -> 0 | J36: =+'31'!H53 -> 0 | K36: =+J36-I36 -> 0
C37: =SUM(C6:C36) -> 33206.04 | D37: =SUM(D6:D36) -> -1000 | E37: =SUM(E6:E36) -> -1000 | F37: =SUM(F6:F36) -> -1000 | G37: =SUM(G6:G36) -> -1000 | H37: =SUM(H6:H36) -> -1000 | I37: =SUM(I6:I36) -> 28206.04 | J37: =SUM(J6:J36) -> 28206.04 | K37: =+J37-I37 -> 0
K38: =SUM(K6:K36)-K37 -> 0

Sheet Petty Cash Report
A1: =+Input!B2 -> ENGEN JETPARK
A3: Petty Cash Analysis | B3: =+Input!B6 -> 46143
A5: PETTY CASH | B5: 1 | C5: =+B5+1 -> 2 | D5: =+C5+1 -> 3 | E5: =+D5+1 -> 4 | F5: =+E5+1 -> 5 | G5: =+F5+1 -> 6 | H5: =+G5+1 -> 7 | I5: =+H5+1 -> 8 | J5: =+I5+1 -> 9 | ... AF5: =+AE5+1 -> 31
A6: - Cleaning | B6: =+'1'!H83 -> 0 | C6: =+'2'!H83 -> 0 | D6: =+'3'!H83 -> 0 | E6: =+'4'!H83 -> 0 | F6: =+'5'!H83 -> 0 | G6: =+'6'!H83 -> 0 | H6: =+'7'!H83 -> 0 | I6: =+'8'!H83 -> 0 | J6: =+'9'!H83 -> 0 | K6: =+'10'!H83 -> 0 | L6: =+'11'!H83 -> 0 | M6: =+'12'!H83 -> 0 | N6: =+'13'!H83 -> 0 | O6: =+'14'!H83 -> 0 | P6: =+'15'!H83 -> 0 | Q6: =+'16'!H83 -> 0 | R6: =+'17'!H83 -> 0 | S6: =+'18'!H83 -> 0 | T6: =+'19'!H83 -> 0 | U6: =+'20'!H83 -> 0 | V6: =+'21'!H83 -> 0 | W6: =+'22'!H83 -> 0 | X6: =+'23'!H83 -> 0 | Y6: =+'24'!H83 -> 0 | Z6: =+'25'!H83 -> 0 | AA6: =+'26'!H83 -> 0 | AB6: =+'27'!H83 -> 0 | AC6: =+'28'!H83 -> 0 | AD6: =+'29'!H83 -> 0 | AE6: =+'30'!H83 -> 0 | AF6: =+'31'!H83 -> 0
A7: - Creditors: Existing | B7: =+'1'!H84 -> 0 | C7: =+'2'!H84 -> 0 | D7: =+'3'!H84 -> 0 | E7: =+'4'!H84 -> 0 | F7: =+'5'!H84 -> 0 | G7: =+'6'!H84 -> 0 | H7: =+'7'!H84 -> 0 | I7: =+'8'!H84 -> 0 | J7: =+'9'!H84 -> 0 | K7: =+'10'!H84 -> 0 | L7: =+'11'!H84 -> 0 | M7: =+'12'!H84 -> 0 | N7: =+'13'!H84 -> 0 | O7: =+'14'!H84 -> 0 | P7: =+'15'!H84 -> 0 | Q7: =+'16'!H84 -> 0 | R7: =+'17'!H84 -> 0 | S7: =+'18'!H84 -> 0 | T7: =+'19'!H84 -> 0 | U7: =+'20'!H84 -> 0 | V7: =+'21'!H84 -> 0 | W7: =+'22'!H84 -> 0 | X7: =+'23'!H84 -> 0 | Y7: =+'24'!H84 -> 0 | Z7: =+'25'!H84 -> 0 | AA7: =+'26'!H84 -> 0 | AB7: =+'27'!H84 -> 0 | AC7: =+'28'!H84 -> 0 | AD7: =+'29'!H84 -> 0 | AE7: =+'30'!H84 -> 0 | AF7: =+'31'!H84 -> 0
A8: - Creditors: New | B8: =+'1'!H85 -> 0 | C8: =+'2'!H85 -> 0 | D8: =+'3'!H85 -> 0 | E8: =+'4'!H85 -> 0 | F8: =+'5'!H85 -> 0 | G8: =+'6'!H85 -> 0 | H8: =+'7'!H85 -> 0 | I8: =+'8'!H85 -> 0 | J8: =+'9'!H85 -> 0 | K8: =+'10'!H85 -> 0 | L8: =+'11'!H85 -> 0 | M8: =+'12'!H85 -> 0 | N8: =+'13'!H85 -> 0 | O8: =+'14'!H85 -> 0 | P8: =+'15'!H85 -> 0 | Q8: =+'16'!H85 -> 0 | R8: =+'17'!H85 -> 0 | S8: =+'18'!H85 -> 0 | T8: =+'19'!H85 -> 0 | U8: =+'20'!H85 -> 0 | V8: =+'21'!H85 -> 0 | W8: =+'22'!H85 -> 0 | X8: =+'23'!H85 -> 0 | Y8: =+'24'!H85 -> 0 | Z8: =+'25'!H85 -> 0 | AA8: =+'26'!H85 -> 0 | AB8: =+'27'!H85 -> 0 | AC8: =+'28'!H85 -> 0 | AD8: =+'29'!H85 -> 0 | AE8: =+'30'!H85 -> 0 | AF8: =+'31'!H85 -> 0
A9: - Forecourt: R & M | B9: =+'1'!H86 -> 0 | C9: =+'2'!H86 -> 0 | D9: =+'3'!H86 -> 0 | E9: =+'4'!H86 -> 0 | F9: =+'5'!H86 -> 0 | G9: =+'6'!H86 -> 0 | H9: =+'7'!H86 -> 0 | I9: =+'8'!H86 -> 0 | J9: =+'9'!H86 -> 0 | K9: =+'10'!H86 -> 0 | L9: =+'11'!H86 -> 0 | M9: =+'12'!H86 -> 0 | N9: =+'13'!H86 -> 0 | O9: =+'14'!H86 -> 0 | P9: =+'15'!H86 -> 0 | Q9: =+'16'!H86 -> 0 | R9: =+'17'!H86 -> 0 | S9: =+'18'!H86 -> 0 | T9: =+'19'!H86 -> 0 | U9: =+'20'!H86 -> 0 | V9: =+'21'!H86 -> 0 | W9: =+'22'!H86 -> 0 | X9: =+'23'!H86 -> 0 | Y9: =+'24'!H86 -> 0 | Z9: =+'25'!H86 -> 0 | AA9: =+'26'!H86 -> 0 | AB9: =+'27'!H86 -> 0 | AC9: =+'28'!H86 -> 0 | AD9: =+'29'!H86 -> 0 | AE9: =+'30'!H86 -> 0 | AF9: =+'31'!H86 -> 0
A10: - Other: Non-Vatable | B10: =+'1'!H87 -> 0 | C10: =+'2'!H87 -> 0 | D10: =+'3'!H87 -> 0 | E10: =+'4'!H87 -> 0 | F10: =+'5'!H87 -> 0 | G10: =+'6'!H87 -> 0 | H10: =+'7'!H87 -> 0 | I10: =+'8'!H87 -> 0 | J10: =+'9'!H87 -> 0 | K10: =+'10'!H87 -> 0 | L10: =+'11'!H87 -> 0 | M10: =+'12'!H87 -> 0 | N10: =+'13'!H87 -> 0 | O10: =+'14'!H87 -> 0 | P10: =+'15'!H87 -> 0 | Q10: =+'16'!H87 -> 0 | R10: =+'17'!H87 -> 0 | S10: =+'18'!H87 -> 0 | T10: =+'19'!H87 -> 0 | U10: =+'20'!H87 -> 0 | V10: =+'21'!H87 -> 0 | W10: =+'22'!H87 -> 0 | X10: =+'23'!H87 -> 0 | Y10: =+'24'!H87 -> 0 | Z10: =+'25'!H87 -> 0 | AA10: =+'26'!H87 -> 0 | AB10: =+'27'!H87 -> 0 | AC10: =+'28'!H87 -> 0 | AD10: =+'29'!H87 -> 0 | AE10: =+'30'!H87 -> 0 | AF10: =+'31'!H87 -> 0
A11: - Other: Non-Vatable | B11: =+'1'!H88 -> 0 | C11: =+'2'!H88 -> 0 | D11: =+'3'!H88 -> 0 | E11: =+'4'!H88 -> 0 | F11: =+'5'!H88 -> 0 | G11: =+'6'!H88 -> 0 | H11: =+'7'!H88 -> 0 | I11: =+'8'!H88 -> 0 | J11: =+'9'!H88 -> 0 | K11: =+'10'!H88 -> 0 | L11: =+'11'!H88 -> 0 | M11: =+'12'!H88 -> 0 | N11: =+'13'!H88 -> 0 | O11: =+'14'!H88 -> 0 | P11: =+'15'!H88 -> 0 | Q11: =+'16'!H88 -> 0 | R11: =+'17'!H88 -> 0 | S11: =+'18'!H88 -> 0 | T11: =+'19'!H88 -> 0 | U11: =+'20'!H88 -> 0 | V11: =+'21'!H88 -> 0 | W11: =+'22'!H88 -> 0 | X11: =+'23'!H88 -> 0 | Y11: =+'24'!H88 -> 0 | Z11: =+'25'!H88 -> 0 | AA11: =+'26'!H88 -> 0 | AB11: =+'27'!H88 -> 0 | AC11: =+'28'!H88 -> 0 | AD11: =+'29'!H88 -> 0 | AE11: =+'30'!H88 -> 0 | AF11: =+'31'!H88 -> 0
A12: - Other: Non-Vatable | B12: =+'1'!H89 -> 0 | C12: =+'2'!H89 -> 0 | D12: =+'3'!H89 -> 0 | E12: =+'4'!H89 -> 0 | F12: =+'5'!H89 -> 0 | G12: =+'6'!H89 -> 0 | H12: =+'7'!H89 -> 0 | I12: =+'8'!H89 -> 0 | J12: =+'9'!H89 -> 0 | K12: =+'10'!H89 -> 0 | L12: =+'11'!H89 -> 0 | M12: =+'12'!H89 -> 0 | N12: =+'13'!H89 -> 0 | O12: =+'14'!H89 -> 0 | P12: =+'15'!H89 -> 0 | Q12: =+'16'!H89 -> 0 | R12: =+'17'!H89 -> 0 | S12: =+'18'!H89 -> 0 | T12: =+'19'!H89 -> 0 | U12: =+'20'!H89 -> 0 | V12: =+'21'!H89 -> 0 | W12: =+'22'!H89 -> 0 | X12: =+'23'!H89 -> 0 | Y12: =+'24'!H89 -> 0 | Z12: =+'25'!H89 -> 0 | AA12: =+'26'!H89 -> 0 | AB12: =+'27'!H89 -> 0 | AC12: =+'28'!H89 -> 0 | AD12: =+'29'!H89 -> 0 | AE12: =+'30'!H89 -> 0 | AF12: =+'31'!H89 -> 0
A13: - Other: Vatable | B13: =+'1'!H90 -> 0 | C13: =+'2'!H90 -> 0 | D13: =+'3'!H90 -> 0 | E13: =+'4'!H90 -> 0 | F13: =+'5'!H90 -> 0 | G13: =+'6'!H90 -> 0 | H13: =+'7'!H90 -> 0 | I13: =+'8'!H90 -> 0 | J13: =+'9'!H90 -> 0 | K13: =+'10'!H90 -> 0 | L13: =+'11'!H90 -> 0 | M13: =+'12'!H90 -> 0 | N13: =+'13'!H90 -> 0 | O13: =+'14'!H90 -> 0 | P13: =+'15'!H90 -> 0 | Q13: =+'16'!H90 -> 0 | R13: =+'17'!H90 -> 0 | S13: =+'18'!H90 -> 0 | T13: =+'19'!H90 -> 0 | U13: =+'20'!H90 -> 0 | V13: =+'21'!H90 -> 0 | W13: =+'22'!H90 -> 0 | X13: =+'23'!H90 -> 0 | Y13: =+'24'!H90 -> 0 | Z13: =+'25'!H90 -> 0 | AA13: =+'26'!H90 -> 0 | AB13: =+'27'!H90 -> 0 | AC13: =+'28'!H90 -> 0 | AD13: =+'29'!H90 -> 0 | AE13: =+'30'!H90 -> 0 | AF13: =+'31'!H90 -> 0
A14: - Other: Vatable | B14: =+'1'!H91 -> 0 | C14: =+'2'!H91 -> 0 | D14: =+'3'!H91 -> 0 | E14: =+'4'!H91 -> 0 | F14: =+'5'!H91 -> 0 | G14: =+'6'!H91 -> 0 | H14: =+'7'!H91 -> 0 | I14: =+'8'!H91 -> 0 | J14: =+'9'!H91 -> 0 | K14: =+'10'!H91 -> 0 | L14: =+'11'!H91 -> 0 | M14: =+'12'!H91 -> 0 | N14: =+'13'!H91 -> 0 | O14: =+'14'!H91 -> 0 | P14: =+'15'!H91 -> 0 | Q14: =+'16'!H91 -> 0 | R14: =+'17'!H91 -> 0 | S14: =+'18'!H91 -> 0 | T14: =+'19'!H91 -> 0 | U14: =+'20'!H91 -> 0 | V14: =+'21'!H91 -> 0 | W14: =+'22'!H91 -> 0 | X14: =+'23'!H91 -> 0 | Y14: =+'24'!H91 -> 0 | Z14: =+'25'!H91 -> 0 | AA14: =+'26'!H91 -> 0 | AB14: =+'27'!H91 -> 0 | AC14: =+'28'!H91 -> 0 | AD14: =+'29'!H91 -> 0 | AE14: =+'30'!H91 -> 0 | AF14: =+'31'!H91 -> 0
A15: - Other: Vatable | B15: =+'1'!H92 -> 0 | C15: =+'2'!H92 -> 0 | D15: =+'3'!H92 -> 0 | E15: =+'4'!H92 -> 0 | F15: =+'5'!H92 -> 0 | G15: =+'6'!H92 -> 0 | H15: =+'7'!H92 -> 0 | I15: =+'8'!H92 -> 0 | J15: =+'9'!H92 -> 0 | K15: =+'10'!H92 -> 0 | L15: =+'11'!H92 -> 0 | M15: =+'12'!H92 -> 0 | N15: =+'13'!H92 -> 0 | O15: =+'14'!H92 -> 0 | P15: =+'15'!H92 -> 0 | Q15: =+'16'!H92 -> 0 | R15: =+'17'!H92 -> 0 | S15: =+'18'!H92 -> 0 | T15: =+'19'!H92 -> 0 | U15: =+'20'!H92 -> 0 | V15: =+'21'!H92 -> 0 | W15: =+'22'!H92 -> 0 | X15: =+'23'!H92 -> 0 | Y15: =+'24'!H92 -> 0 | Z15: =+'25'!H92 -> 0 | AA15: =+'26'!H92 -> 0 | AB15: =+'27'!H92 -> 0 | AC15: =+'28'!H92 -> 0 | AD15: =+'29'!H92 -> 0 | AE15: =+'30'!H92 -> 0 | AF15: =+'31'!H92 -> 0
A16: - Printing & Stationery | B16: =+'1'!H93 -> 0 | C16: =+'2'!H93 -> 0 | D16: =+'3'!H93 -> 0 | E16: =+'4'!H93 -> 0 | F16: =+'5'!H93 -> 0 | G16: =+'6'!H93 -> 0 | H16: =+'7'!H93 -> 0 | I16: =+'8'!H93 -> 0 | J16: =+'9'!H93 -> 0 | K16: =+'10'!H93 -> 0 | L16: =+'11'!H93 -> 0 | M16: =+'12'!H93 -> 0 | N16: =+'13'!H93 -> 0 | O16: =+'14'!H93 -> 0 | P16: =+'15'!H93 -> 0 | Q16: =+'16'!H93 -> 0 | R16: =+'17'!H93 -> 0 | S16: =+'18'!H93 -> 0 | T16: =+'19'!H93 -> 0 | U16: =+'20'!H93 -> 0 | V16: =+'21'!H93 -> 0 | W16: =+'22'!H93 -> 0 | X16: =+'23'!H93 -> 0 | Y16: =+'24'!H93 -> 0 | Z16: =+'25'!H93 -> 0 | AA16: =+'26'!H93 -> 0 | AB16: =+'27'!H93 -> 0 | AC16: =+'28'!H93 -> 0 | AD16: =+'29'!H93 -> 0 | AE16: =+'30'!H93 -> 0 | AF16: =+'31'!H93 -> 0
A17: - Retail: R & M | B17: =+'1'!H94 -> 0 | C17: =+'2'!H94 -> 0 | D17: =+'3'!H94 -> 0 | E17: =+'4'!H94 -> 0 | F17: =+'5'!H94 -> 0 | G17: =+'6'!H94 -> 0 | H17: =+'7'!H94 -> 0 | I17: =+'8'!H94 -> 0 | J17: =+'9'!H94 -> 0 | K17: =+'10'!H94 -> 0 | L17: =+'11'!H94 -> 0 | M17: =+'12'!H94 -> 0 | N17: =+'13'!H94 -> 0 | O17: =+'14'!H94 -> 0 | P17: =+'15'!H94 -> 0 | Q17: =+'16'!H94 -> 0 | R17: =+'17'!H94 -> 0 | S17: =+'18'!H94 -> 0 | T17: =+'19'!H94 -> 0 | U17: =+'20'!H94 -> 0 | V17: =+'21'!H94 -> 0 | W17: =+'22'!H94 -> 0 | X17: =+'23'!H94 -> 0 | Y17: =+'24'!H94 -> 0 | Z17: =+'25'!H94 -> 0 | AA17: =+'26'!H94 -> 0 | AB17: =+'27'!H94 -> 0 | AC17: =+'28'!H94 -> 0 | AD17: =+'29'!H94 -> 0 | AE17: =+'30'!H94 -> 0 | AF17: =+'31'!H94 -> 0
... A21: - Wages | B21: =+'1'!H98 -> 0 | C21: =+'2'!H98 -> 0 | D21: =+'3'!H98 -> 0 | E21: =+'4'!H98 -> 0 | F21: =+'5'!H98 -> 0 | G21: =+'6'!H98 -> 0 | H21: =+'7'!H98 -> 0 | I21: =+'8'!H98 -> 0 | J21: =+'9'!H98 -> 0 | K21: =+'10'!H98 -> 0 | L21: =+'11'!H98 -> 0 | M21: =+'12'!H98 -> 0 | N21: =+'13'!H98 -> 0 | O21: =+'14'!H98 -> 0 | P21: =+'15'!H98 -> 0 | Q21: =+'16'!H98 -> 0 | R21: =+'17'!H98 -> 0 | S21: =+'18'!H98 -> 0 | T21: =+'19'!H98 -> 0 | U21: =+'20'!H98 -> 0 | V21: =+'21'!H98 -> 0 | W21: =+'22'!H98 -> 0 | X21: =+'23'!H98 -> 0 | Y21: =+'24'!H98 -> 0 | Z21: =+'25'!H98 -> 0 | AA21: =+'26'!H98 -> 0 | AB21: =+'27'!H98 -> 0 | AC21: =+'28'!H98 -> 0 | AD21: =+'29'!H98 -> 0 | AE21: =+'30'!H98 -> 0 | AF21: =+'31'!H98 -> 0
A22: - TOTAL | B22: =SUM(B6:B21) -> 0 | C22: =SUM(C6:C21) -> 0 | D22: =SUM(D6:D21) -> 0 | E22: =SUM(E6:E21) -> 0 | F22: =SUM(F6:F21) -> 0 | G22: =SUM(G6:G21) -> 0 | H22: =SUM(H6:H21) -> 0 | I22: =SUM(I6:I21) -> 0 | ... AF22: =SUM(AF6:AF21) -> 0
A23: - TOTAL B/FWD | B23: =+'1'!H82 -> 0 | C23: =+'2'!H82 -> 0 | D23: =+'3'!H82 -> 0 | E23: =+'4'!H82 -> 0 | F23: =+'5'!H82 -> 0 | G23: =+'6'!H82 -> 0 | H23: =+'7'!H82 -> 0 | I23: =+'8'!H82 -> 0 | J23: =+'9'!H82 -> 0 | K23: =+'10'!H82 -> 0 | L23: =+'11'!H82 -> 0 | M23: =+'12'!H82 -> 0 | N23: =+'13'!H82 -> 0 | O23: =+'14'!H82 -> 0 | P23: =+'15'!H82 -> 0 | Q23: =+'16'!H82 -> 0 | R23: =+'17'!H82 -> 0 | S23: =+'18'!H82 -> 0 | T23: =+'19'!H82 -> 0 | U23: =+'20'!H82 -> 0 | V23: =+'21'!H82 -> 0 | W23: =+'22'!H82 -> 0 | X23: =+'23'!H82 -> 0 | Y23: =+'24'!H82 -> 0 | Z23: =+'25'!H82 -> 0 | AA23: =+'26'!H82 -> 0 | AB23: =+'27'!H82 -> 0 | AC23: =+'28'!H82 -> 0 | AD23: =+'29'!H82 -> 0 | AE23: =+'30'!H82 -> 0 | AF23: =+'31'!H82 -> 0
A24: - VARIANCE | B24: =+B22-B23 -> 0 | C24: =+C22-C23 -> 0 | D24: =+D22-D23 -> 0 | E24: =+E22-E23 -> 0 | F24: =+F22-F23 -> 0 | G24: =+G22-G23 -> 0 | H24: =+H22-H23 -> 0 | I24: =+I22-I23 -> 0 | ... AF24: =+AF22-AF23 -> 0
A26: CREDITORS: EXISTING
A27: =+Input!A55 -> - Aksia Sales | B27: =+'1'!H102 -> 0 | C27: =+'2'!H102 -> 0 | D27: =+'3'!H102 -> 0 | E27: =+'4'!H102 -> 0 | F27: =+'5'!H102 -> 0 | G27: =+'6'!H102 -> 0 | H27: =+'7'!H102 -> 0 | I27: =+'8'!H102 -> 0 | J27: =+'9'!H102 -> 0 | K27: =+'10'!H102 -> 0 | L27: =+'11'!H102 -> 0 | M27: =+'12'!H102 -> 0 | N27: =+'13'!H102 -> 0 | O27: =+'14'!H102 -> 0 | P27: =+'15'!H102 -> 0 | Q27: =+'16'!H102 -> 0 | R27: =+'17'!H102 -> 0 | S27: =+'18'!H102 -> 0 | T27: =+'19'!H102 -> 0 | U27: =+'20'!H102 -> 0 | V27: =+'21'!H102 -> 0 | W27: =+'22'!H102 -> 0 | X27: =+'23'!H102 -> 0 | Y27: =+'24'!H102 -> 0 | Z27: =+'25'!H102 -> 0 | AA27: =+'26'!H102 -> 0 | AB27: =+'27'!H102 -> 0 | AC27: =+'28'!H102 -> 0 | AD27: =+'29'!H102 -> 0 | AE27: =+'30'!H102 -> 0 | AF27: =+'31'!H102 -> 0
A28: =+Input!A56 -> - Albany | B28: =+'1'!H103 -> 0 | C28: =+'2'!H103 -> 0 | D28: =+'3'!H103 -> 0 | E28: =+'4'!H103 -> 0 | F28: =+'5'!H103 -> 0 | G28: =+'6'!H103 -> 0 | H28: =+'7'!H103 -> 0 | I28: =+'8'!H103 -> 0 | J28: =+'9'!H103 -> 0 | K28: =+'10'!H103 -> 0 | L28: =+'11'!H103 -> 0 | M28: =+'12'!H103 -> 0 | N28: =+'13'!H103 -> 0 | O28: =+'14'!H103 -> 0 | P28: =+'15'!H103 -> 0 | Q28: =+'16'!H103 -> 0 | R28: =+'17'!H103 -> 0 | S28: =+'18'!H103 -> 0 | T28: =+'19'!H103 -> 0 | U28: =+'20'!H103 -> 0 | V28: =+'21'!H103 -> 0 | W28: =+'22'!H103 -> 0 | X28: =+'23'!H103 -> 0 | Y28: =+'24'!H103 -> 0 | Z28: =+'25'!H103 -> 0 | AA28: =+'26'!H103 -> 0 | AB28: =+'27'!H103 -> 0 | AC28: =+'28'!H103 -> 0 | AD28: =+'29'!H103 -> 0 | AE28: =+'30'!H103 -> 0 | AF28: =+'31'!H103 -> 0
A29: =+Input!A57 -> - Atlantic Ice | B29: =+'1'!H104 -> 0 | C29: =+'2'!H104 -> 0 | D29: =+'3'!H104 -> 0 | E29: =+'4'!H104 -> 0 | F29: =+'5'!H104 -> 0 | G29: =+'6'!H104 -> 0 | H29: =+'7'!H104 -> 0 | I29: =+'8'!H104 -> 0 | J29: =+'9'!H104 -> 0 | K29: =+'10'!H104 -> 0 | L29: =+'11'!H104 -> 0 | M29: =+'12'!H104 -> 0 | N29: =+'13'!H104 -> 0 | O29: =+'14'!H104 -> 0 | P29: =+'15'!H104 -> 0 | Q29: =+'16'!H104 -> 0 | R29: =+'17'!H104 -> 0 | S29: =+'18'!H104 -> 0 | T29: =+'19'!H104 -> 0 | U29: =+'20'!H104 -> 0 | V29: =+'21'!H104 -> 0 | W29: =+'22'!H104 -> 0 | X29: =+'23'!H104 -> 0 | Y29: =+'24'!H104 -> 0 | Z29: =+'25'!H104 -> 0 | AA29: =+'26'!H104 -> 0 | AB29: =+'27'!H104 -> 0 | AC29: =+'28'!H104 -> 0 | AD29: =+'29'!H104 -> 0 | AE29: =+'30'!H104 -> 0 | AF29: =+'31'!H104 -> 0
A30: =+Input!A58 -> - Bake It Easy | B30: =+'1'!H105 -> 0 | C30: =+'2'!H105 -> 0 | D30: =+'3'!H105 -> 0 | E30: =+'4'!H105 -> 0 | F30: =+'5'!H105 -> 0 | G30: =+'6'!H105 -> 0 | H30: =+'7'!H105 -> 0 | I30: =+'8'!H105 -> 0 | J30: =+'9'!H105 -> 0 | K30: =+'10'!H105 -> 0 | L30: =+'11'!H105 -> 0 | M30: =+'12'!H105 -> 0 | N30: =+'13'!H105 -> 0 | O30: =+'14'!H105 -> 0 | P30: =+'15'!H105 -> 0 | Q30: =+'16'!H105 -> 0 | R30: =+'17'!H105 -> 0 | S30: =+'18'!H105 -> 0 | T30: =+'19'!H105 -> 0 | U30: =+'20'!H105 -> 0 | V30: =+'21'!H105 -> 0 | W30: =+'22'!H105 -> 0 | X30: =+'23'!H105 -> 0 | Y30: =+'24'!H105 -> 0 | Z30: =+'25'!H105 -> 0 | AA30: =+'26'!H105 -> 0 | AB30: =+'27'!H105 -> 0 | AC30: =+'28'!H105 -> 0 | AD30: =+'29'!H105 -> 0 | AE30: =+'30'!H105 -> 0 | AF30: =+'31'!H105 -> 0
A31: =+Input!A59 -> - Bamco Tabacco | B31: =+'1'!H106 -> 0 | C31: =+'2'!H106 -> 0 | D31: =+'3'!H106 -> 0 | E31: =+'4'!H106 -> 0 | F31: =+'5'!H106 -> 0 | G31: =+'6'!H106 -> 0 | H31: =+'7'!H106 -> 0 | I31: =+'8'!H106 -> 0 | J31: =+'9'!H106 -> 0 | K31: =+'10'!H106 -> 0 | L31: =+'11'!H106 -> 0 | M31: =+'12'!H106 -> 0 | N31: =+'13'!H106 -> 0 | O31: =+'14'!H106 -> 0 | P31: =+'15'!H106 -> 0 | Q31: =+'16'!H106 -> 0 | R31: =+'17'!H106 -> 0 | S31: =+'18'!H106 -> 0 | T31: =+'19'!H106 -> 0 | U31: =+'20'!H106 -> 0 | V31: =+'21'!H106 -> 0 | W31: =+'22'!H106 -> 0 | X31: =+'23'!H106 -> 0 | Y31: =+'24'!H106 -> 0 | Z31: =+'25'!H106 -> 0 | AA31: =+'26'!H106 -> 0 | AB31: =+'27'!H106 -> 0 | AC31: =+'28'!H106 -> 0 | AD31: =+'29'!H106 -> 0 | AE31: =+'30'!H106 -> 0 | AF31: =+'31'!H106 -> 0
A32: =+Input!A60 -> - Blue Ribbon | B32: =+'1'!H107 -> 0 | C32: =+'2'!H107 -> 0 | D32: =+'3'!H107 -> 0 | E32: =+'4'!H107 -> 0 | F32: =+'5'!H107 -> 0 | G32: =+'6'!H107 -> 0 | H32: =+'7'!H107 -> 0 | I32: =+'8'!H107 -> 0 | J32: =+'9'!H107 -> 0 | K32: =+'10'!H107 -> 0 | L32: =+'11'!H107 -> 0 | M32: =+'12'!H107 -> 0 | N32: =+'13'!H107 -> 0 | O32: =+'14'!H107 -> 0 | P32: =+'15'!H107 -> 0 | Q32: =+'16'!H107 -> 0 | R32: =+'17'!H107 -> 0 | S32: =+'18'!H107 -> 0 | T32: =+'19'!H107 -> 0 | U32: =+'20'!H107 -> 0 | V32: =+'21'!H107 -> 0 | W32: =+'22'!H107 -> 0 | X32: =+'23'!H107 -> 0 | Y32: =+'24'!H107 -> 0 | Z32: =+'25'!H107 -> 0 | AA32: =+'26'!H107 -> 0 | AB32: =+'27'!H107 -> 0 | AC32: =+'28'!H107 -> 0 | AD32: =+'29'!H107 -> 0 | AE32: =+'30'!H107 -> 0 | AF32: =+'31'!H107 -> 0
A33: =+Input!A61 -> - Catercorp | B33: =+'1'!H108 -> 0 | C33: =+'2'!H108 -> 0 | D33: =+'3'!H108 -> 0 | E33: =+'4'!H108 -> 0 | F33: =+'5'!H108 -> 0 | G33: =+'6'!H108 -> 0 | H33: =+'7'!H108 -> 0 | I33: =+'8'!H108 -> 0 | J33: =+'9'!H108 -> 0 | K33: =+'10'!H108 -> 0 | L33: =+'11'!H108 -> 0 | M33: =+'12'!H108 -> 0 | N33: =+'13'!H108 -> 0 | O33: =+'14'!H108 -> 0 | P33: =+'15'!H108 -> 0 | Q33: =+'16'!H108 -> 0 | R33: =+'17'!H108 -> 0 | S33: =+'18'!H108 -> 0 | T33: =+'19'!H108 -> 0 | U33: =+'20'!H108 -> 0 | V33: =+'21'!H108 -> 0 | W33: =+'22'!H108 -> 0 | X33: =+'23'!H108 -> 0 | Y33: =+'24'!H108 -> 0 | Z33: =+'25'!H108 -> 0 | AA33: =+'26'!H108 -> 0 | AB33: =+'27'!H108 -> 0 | AC33: =+'28'!H108 -> 0 | AD33: =+'29'!H108 -> 0 | AE33: =+'30'!H108 -> 0 | AF33: =+'31'!H108 -> 0
A34: =+Input!A62 -> - Checkers | B34: =+'1'!H109 -> 0 | C34: =+'2'!H109 -> 0 | D34: =+'3'!H109 -> 0 | E34: =+'4'!H109 -> 0 | F34: =+'5'!H109 -> 0 | G34: =+'6'!H109 -> 0 | H34: =+'7'!H109 -> 0 | I34: =+'8'!H109 -> 0 | J34: =+'9'!H109 -> 0 | K34: =+'10'!H109 -> 0 | L34: =+'11'!H109 -> 0 | M34: =+'12'!H109 -> 0 | N34: =+'13'!H109 -> 0 | O34: =+'14'!H109 -> 0 | P34: =+'15'!H109 -> 0 | Q34: =+'16'!H109 -> 0 | R34: =+'17'!H109 -> 0 | S34: =+'18'!H109 -> 0 | T34: =+'19'!H109 -> 0 | U34: =+'20'!H109 -> 0 | V34: =+'21'!H109 -> 0 | W34: =+'22'!H109 -> 0 | X34: =+'23'!H109 -> 0 | Y34: =+'24'!H109 -> 0 | Z34: =+'25'!H109 -> 0 | AA34: =+'26'!H109 -> 0 | AB34: =+'27'!H109 -> 0 | AC34: =+'28'!H109 -> 0 | AD34: =+'29'!H109 -> 0 | AE34: =+'30'!H109 -> 0 | AF34: =+'31'!H109 -> 0
A35: =+Input!A63 -> - Clover | B35: =+'1'!H110 -> 0 | C35: =+'2'!H110 -> 0 | D35: =+'3'!H110 -> 0 | E35: =+'4'!H110 -> 0 | F35: =+'5'!H110 -> 0 | G35: =+'6'!H110 -> 0 | H35: =+'7'!H110 -> 0 | I35: =+'8'!H110 -> 0 | J35: =+'9'!H110 -> 0 | K35: =+'10'!H110 -> 0 | L35: =+'11'!H110 -> 0 | M35: =+'12'!H110 -> 0 | N35: =+'13'!H110 -> 0 | O35: =+'14'!H110 -> 0 | P35: =+'15'!H110 -> 0 | Q35: =+'16'!H110 -> 0 | R35: =+'17'!H110 -> 0 | S35: =+'18'!H110 -> 0 | T35: =+'19'!H110 -> 0 | U35: =+'20'!H110 -> 0 | V35: =+'21'!H110 -> 0 | W35: =+'22'!H110 -> 0 | X35: =+'23'!H110 -> 0 | Y35: =+'24'!H110 -> 0 | Z35: =+'25'!H110 -> 0 | AA35: =+'26'!H110 -> 0 | AB35: =+'27'!H110 -> 0 | AC35: =+'28'!H110 -> 0 | AD35: =+'29'!H110 -> 0 | AE35: =+'30'!H110 -> 0 | AF35: =+'31'!H110 -> 0
A36: =+Input!A64 -> - Cool Runnings | B36: =+'1'!H111 -> 0 | C36: =+'2'!H111 -> 0 | D36: =+'3'!H111 -> 0 | E36: =+'4'!H111 -> 0 | F36: =+'5'!H111 -> 0 | G36: =+'6'!H111 -> 0 | H36: =+'7'!H111 -> 0 | I36: =+'8'!H111 -> 0 | J36: =+'9'!H111 -> 0 | K36: =+'10'!H111 -> 0 | L36: =+'11'!H111 -> 0 | M36: =+'12'!H111 -> 0 | N36: =+'13'!H111 -> 0 | O36: =+'14'!H111 -> 0 | P36: =+'15'!H111 -> 0 | Q36: =+'16'!H111 -> 0 | R36: =+'17'!H111 -> 0 | S36: =+'18'!H111 -> 0 | T36: =+'19'!H111 -> 0 | U36: =+'20'!H111 -> 0 | V36: =+'21'!H111 -> 0 | W36: =+'22'!H111 -> 0 | X36: =+'23'!H111 -> 0 | Y36: =+'24'!H111 -> 0 | Z36: =+'25'!H111 -> 0 | AA36: =+'26'!H111 -> 0 | AB36: =+'27'!H111 -> 0 | AC36: =+'28'!H111 -> 0 | AD36: =+'29'!H111 -> 0 | AE36: =+'30'!H111 -> 0 | AF36: =+'31'!H111 -> 0
A37: =+Input!A65 -> - Deep Frozen | B37: =+'1'!H112 -> 0 | C37: =+'2'!H112 -> 0 | D37: =+'3'!H112 -> 0 | E37: =+'4'!H112 -> 0 | F37: =+'5'!H112 -> 0 | G37: =+'6'!H112 -> 0 | H37: =+'7'!H112 -> 0 | I37: =+'8'!H112 -> 0 | J37: =+'9'!H112 -> 0 | K37: =+'10'!H112 -> 0 | L37: =+'11'!H112 -> 0 | M37: =+'12'!H112 -> 0 | N37: =+'13'!H112 -> 0 | O37: =+'14'!H112 -> 0 | P37: =+'15'!H112 -> 0 | Q37: =+'16'!H112 -> 0 | R37: =+'17'!H112 -> 0 | S37: =+'18'!H112 -> 0 | T37: =+'19'!H112 -> 0 | U37: =+'20'!H112 -> 0 | V37: =+'21'!H112 -> 0 | W37: =+'22'!H112 -> 0 | X37: =+'23'!H112 -> 0 | Y37: =+'24'!H112 -> 0 | Z37: =+'25'!H112 -> 0 | AA37: =+'26'!H112 -> 0 | AB37: =+'27'!H112 -> 0 | AC37: =+'28'!H112 -> 0 | AD37: =+'29'!H112 -> 0 | AE37: =+'30'!H112 -> 0 | AF37: =+'31'!H112 -> 0
A38: =+Input!A66 -> - Digistics | B38: =+'1'!H113 -> 0 | C38: =+'2'!H113 -> 0 | D38: =+'3'!H113 -> 0 | E38: =+'4'!H113 -> 0 | F38: =+'5'!H113 -> 0 | G38: =+'6'!H113 -> 0 | H38: =+'7'!H113 -> 0 | I38: =+'8'!H113 -> 0 | J38: =+'9'!H113 -> 0 | K38: =+'10'!H113 -> 0 | L38: =+'11'!H113 -> 0 | M38: =+'12'!H113 -> 0 | N38: =+'13'!H113 -> 0 | O38: =+'14'!H113 -> 0 | P38: =+'15'!H113 -> 0 | Q38: =+'16'!H113 -> 0 | R38: =+'17'!H113 -> 0 | S38: =+'18'!H113 -> 0 | T38: =+'19'!H113 -> 0 | U38: =+'20'!H113 -> 0 | V38: =+'21'!H113 -> 0 | W38: =+'22'!H113 -> 0 | X38: =+'23'!H113 -> 0 | Y38: =+'24'!H113 -> 0 | Z38: =+'25'!H113 -> 0 | AA38: =+'26'!H113 -> 0 | AB38: =+'27'!H113 -> 0 | AC38: =+'28'!H113 -> 0 | AD38: =+'29'!H113 -> 0 | AE38: =+'30'!H113 -> 0 | AF38: =+'31'!H113 -> 0
... A57: =+Input!A85 -> - W Convenience | B57: =+'1'!H132 -> 0 | C57: =+'2'!H132 -> 0 | D57: =+'3'!H132 -> 0 | E57: =+'4'!H132 -> 0 | F57: =+'5'!H132 -> 0 | G57: =+'6'!H132 -> 0 | H57: =+'7'!H132 -> 0 | I57: =+'8'!H132 -> 0 | J57: =+'9'!H132 -> 0 | K57: =+'10'!H132 -> 0 | L57: =+'11'!H132 -> 0 | M57: =+'12'!H132 -> 0 | N57: =+'13'!H132 -> 0 | O57: =+'14'!H132 -> 0 | P57: =+'15'!H132 -> 0 | Q57: =+'16'!H132 -> 0 | R57: =+'17'!H132 -> 0 | S57: =+'18'!H132 -> 0 | T57: =+'19'!H132 -> 0 | U57: =+'20'!H132 -> 0 | V57: =+'21'!H132 -> 0 | W57: =+'22'!H132 -> 0 | X57: =+'23'!H132 -> 0 | Y57: =+'24'!H132 -> 0 | Z57: =+'25'!H132 -> 0 | AA57: =+'26'!H132 -> 0 | AB57: =+'27'!H132 -> 0 | AC57: =+'28'!H132 -> 0 | AD57: =+'29'!H132 -> 0 | AE57: =+'30'!H132 -> 0 | AF57: =+'31'!H132 -> 0
A58: - TOTAL | B58: =SUM(B27:B57) -> 0 | C58: =SUM(C27:C57) -> 0 | D58: =SUM(D27:D57) -> 0 | E58: =SUM(E27:E57) -> 0 | F58: =SUM(F27:F57) -> 0 | G58: =SUM(G27:G57) -> 0 | H58: =SUM(H27:H57) -> 0 | I58: =SUM(I27:I57) -> 0 | ... AF58: =SUM(AF27:AF57) -> 0
A59: - TOTAL B/FWD | B59: =+'1'!H101 -> 0 | C59: =+'2'!H101 -> 0 | D59: =+'3'!H101 -> 0 | E59: =+'4'!H101 -> 0 | F59: =+'5'!H101 -> 0 | G59: =+'6'!H101 -> 0 | H59: =+'7'!H101 -> 0 | I59: =+'8'!H101 -> 0 | J59: =+'9'!H101 -> 0 | K59: =+'10'!H101 -> 0 | L59: =+'11'!H101 -> 0 | M59: =+'12'!H101 -> 0 | N59: =+'13'!H101 -> 0 | O59: =+'14'!H101 -> 0 | P59: =+'15'!H101 -> 0 | Q59: =+'16'!H101 -> 0 | R59: =+'17'!H101 -> 0 | S59: =+'18'!H101 -> 0 | T59: =+'19'!H101 -> 0 | U59: =+'20'!H101 -> 0 | V59: =+'21'!H101 -> 0 | W59: =+'22'!H101 -> 0 | X59: =+'23'!H101 -> 0 | Y59: =+'24'!H101 -> 0 | Z59: =+'25'!H101 -> 0 | AA59: =+'26'!H101 -> 0 | AB59: =+'27'!H101 -> 0 | AC59: =+'28'!H101 -> 0 | AD59: =+'29'!H101 -> 0 | AE59: =+'30'!H101 -> 0 | AF59: =+'31'!H101 -> 0
A60: - VARIANCE | B60: =+B58-B59 -> 0 | C60: =+C58-C59 -> 0 | D60: =+D58-D59 -> 0 | E60: =+E58-E59 -> 0 | F60: =+F58-F59 -> 0 | G60: =+G58-G59 -> 0 | H60: =+H58-H59 -> 0 | I60: =+I58-I59 -> 0 | ... AF60: =+AF58-AF59 -> 0
A62: CREDITORS: NEW (Update Input)
A63: =+Input!A88 -> - Other 1 | B63: =+'1'!H136 -> 0 | C63: =+'2'!H136 -> 0 | D63: =+'3'!H136 -> 0 | E63: =+'4'!H136 -> 0 | F63: =+'5'!H136 -> 0 | G63: =+'6'!H136 -> 0 | H63: =+'7'!H136 -> 0 | I63: =+'8'!H136 -> 0 | J63: =+'9'!H136 -> 0 | K63: =+'10'!H136 -> 0 | L63: =+'11'!H136 -> 0 | M63: =+'12'!H136 -> 0 | N63: =+'13'!H136 -> 0 | O63: =+'14'!H136 -> 0 | P63: =+'15'!H136 -> 0 | Q63: =+'16'!H136 -> 0 | R63: =+'17'!H136 -> 0 | S63: =+'18'!H136 -> 0 | T63: =+'19'!H136 -> 0 | U63: =+'20'!H136 -> 0 | V63: =+'21'!H136 -> 0 | W63: =+'22'!H136 -> 0 | X63: =+'23'!H136 -> 0 | Y63: =+'24'!H136 -> 0 | Z63: =+'25'!H136 -> 0 | AA63: =+'26'!H136 -> 0 | AB63: =+'27'!H136 -> 0 | AC63: =+'28'!H136 -> 0 | AD63: =+'29'!H136 -> 0 | AE63: =+'30'!H136 -> 0 | AF63: =+'31'!H136 -> 0
A64: =+Input!A89 -> - Other 2 | B64: =+'1'!H137 -> 0 | C64: =+'2'!H137 -> 0 | D64: =+'3'!H137 -> 0 | E64: =+'4'!H137 -> 0 | F64: =+'5'!H137 -> 0 | G64: =+'6'!H137 -> 0 | H64: =+'7'!H137 -> 0 | I64: =+'8'!H137 -> 0 | J64: =+'9'!H137 -> 0 | K64: =+'10'!H137 -> 0 | L64: =+'11'!H137 -> 0 | M64: =+'12'!H137 -> 0 | N64: =+'13'!H137 -> 0 | O64: =+'14'!H137 -> 0 | P64: =+'15'!H137 -> 0 | Q64: =+'16'!H137 -> 0 | R64: =+'17'!H137 -> 0 | S64: =+'18'!H137 -> 0 | T64: =+'19'!H137 -> 0 | U64: =+'20'!H137 -> 0 | V64: =+'21'!H137 -> 0 | W64: =+'22'!H137 -> 0 | X64: =+'23'!H137 -> 0 | Y64: =+'24'!H137 -> 0 | Z64: =+'25'!H137 -> 0 | AA64: =+'26'!H137 -> 0 | AB64: =+'27'!H137 -> 0 | AC64: =+'28'!H137 -> 0 | AD64: =+'29'!H137 -> 0 | AE64: =+'30'!H137 -> 0 | AF64: =+'31'!H137 -> 0
A65: =+Input!A90 -> - Other 3 | B65: =+'1'!H138 -> 0 | C65: =+'2'!H138 -> 0 | D65: =+'3'!H138 -> 0 | E65: =+'4'!H138 -> 0 | F65: =+'5'!H138 -> 0 | G65: =+'6'!H138 -> 0 | H65: =+'7'!H138 -> 0 | I65: =+'8'!H138 -> 0 | J65: =+'9'!H138 -> 0 | K65: =+'10'!H138 -> 0 | L65: =+'11'!H138 -> 0 | M65: =+'12'!H138 -> 0 | N65: =+'13'!H138 -> 0 | O65: =+'14'!H138 -> 0 | P65: =+'15'!H138 -> 0 | Q65: =+'16'!H138 -> 0 | R65: =+'17'!H138 -> 0 | S65: =+'18'!H138 -> 0 | T65: =+'19'!H138 -> 0 | U65: =+'20'!H138 -> 0 | V65: =+'21'!H138 -> 0 | W65: =+'22'!H138 -> 0 | X65: =+'23'!H138 -> 0 | Y65: =+'24'!H138 -> 0 | Z65: =+'25'!H138 -> 0 | AA65: =+'26'!H138 -> 0 | AB65: =+'27'!H138 -> 0 | AC65: =+'28'!H138 -> 0 | AD65: =+'29'!H138 -> 0 | AE65: =+'30'!H138 -> 0 | AF65: =+'31'!H138 -> 0
A66: =+Input!A91 -> - Other 4 | B66: =+'1'!H139 -> 0 | C66: =+'2'!H139 -> 0 | D66: =+'3'!H139 -> 0 | E66: =+'4'!H139 -> 0 | F66: =+'5'!H139 -> 0 | G66: =+'6'!H139 -> 0 | H66: =+'7'!H139 -> 0 | I66: =+'8'!H139 -> 0 | J66: =+'9'!H139 -> 0 | K66: =+'10'!H139 -> 0 | L66: =+'11'!H139 -> 0 | M66: =+'12'!H139 -> 0 | N66: =+'13'!H139 -> 0 | O66: =+'14'!H139 -> 0 | P66: =+'15'!H139 -> 0 | Q66: =+'16'!H139 -> 0 | R66: =+'17'!H139 -> 0 | S66: =+'18'!H139 -> 0 | T66: =+'19'!H139 -> 0 | U66: =+'20'!H139 -> 0 | V66: =+'21'!H139 -> 0 | W66: =+'22'!H139 -> 0 | X66: =+'23'!H139 -> 0 | Y66: =+'24'!H139 -> 0 | Z66: =+'25'!H139 -> 0 | AA66: =+'26'!H139 -> 0 | AB66: =+'27'!H139 -> 0 | AC66: =+'28'!H139 -> 0 | AD66: =+'29'!H139 -> 0 | AE66: =+'30'!H139 -> 0 | AF66: =+'31'!H139 -> 0
A67: =+Input!A92 -> - Other 5 | B67: =+'1'!H140 -> 0 | C67: =+'2'!H140 -> 0 | D67: =+'3'!H140 -> 0 | E67: =+'4'!H140 -> 0 | F67: =+'5'!H140 -> 0 | G67: =+'6'!H140 -> 0 | H67: =+'7'!H140 -> 0 | I67: =+'8'!H140 -> 0 | J67: =+'9'!H140 -> 0 | K67: =+'10'!H140 -> 0 | L67: =+'11'!H140 -> 0 | M67: =+'12'!H140 -> 0 | N67: =+'13'!H140 -> 0 | O67: =+'14'!H140 -> 0 | P67: =+'15'!H140 -> 0 | Q67: =+'16'!H140 -> 0 | R67: =+'17'!H140 -> 0 | S67: =+'18'!H140 -> 0 | T67: =+'19'!H140 -> 0 | U67: =+'20'!H140 -> 0 | V67: =+'21'!H140 -> 0 | W67: =+'22'!H140 -> 0 | X67: =+'23'!H140 -> 0 | Y67: =+'24'!H140 -> 0 | Z67: =+'25'!H140 -> 0 | AA67: =+'26'!H140 -> 0 | AB67: =+'27'!H140 -> 0 | AC67: =+'28'!H140 -> 0 | AD67: =+'29'!H140 -> 0 | AE67: =+'30'!H140 -> 0 | AF67: =+'31'!H140 -> 0
A68: =+Input!A93 -> - Other 6 | B68: =+'1'!H141 -> 0 | C68: =+'2'!H141 -> 0 | D68: =+'3'!H141 -> 0 | E68: =+'4'!H141 -> 0 | F68: =+'5'!H141 -> 0 | G68: =+'6'!H141 -> 0 | H68: =+'7'!H141 -> 0 | I68: =+'8'!H141 -> 0 | J68: =+'9'!H141 -> 0 | K68: =+'10'!H141 -> 0 | L68: =+'11'!H141 -> 0 | M68: =+'12'!H141 -> 0 | N68: =+'13'!H141 -> 0 | O68: =+'14'!H141 -> 0 | P68: =+'15'!H141 -> 0 | Q68: =+'16'!H141 -> 0 | R68: =+'17'!H141 -> 0 | S68: =+'18'!H141 -> 0 | T68: =+'19'!H141 -> 0 | U68: =+'20'!H141 -> 0 | V68: =+'21'!H141 -> 0 | W68: =+'22'!H141 -> 0 | X68: =+'23'!H141 -> 0 | Y68: =+'24'!H141 -> 0 | Z68: =+'25'!H141 -> 0 | AA68: =+'26'!H141 -> 0 | AB68: =+'27'!H141 -> 0 | AC68: =+'28'!H141 -> 0 | AD68: =+'29'!H141 -> 0 | AE68: =+'30'!H141 -> 0 | AF68: =+'31'!H141 -> 0
A69: =+Input!A94 -> - Other 7 | B69: =+'1'!H142 -> 0 | C69: =+'2'!H142 -> 0 | D69: =+'3'!H142 -> 0 | E69: =+'4'!H142 -> 0 | F69: =+'5'!H142 -> 0 | G69: =+'6'!H142 -> 0 | H69: =+'7'!H142 -> 0 | I69: =+'8'!H142 -> 0 | J69: =+'9'!H142 -> 0 | K69: =+'10'!H142 -> 0 | L69: =+'11'!H142 -> 0 | M69: =+'12'!H142 -> 0 | N69: =+'13'!H142 -> 0 | O69: =+'14'!H142 -> 0 | P69: =+'15'!H142 -> 0 | Q69: =+'16'!H142 -> 0 | R69: =+'17'!H142 -> 0 | S69: =+'18'!H142 -> 0 | T69: =+'19'!H142 -> 0 | U69: =+'20'!H142 -> 0 | V69: =+'21'!H142 -> 0 | W69: =+'22'!H142 -> 0 | X69: =+'23'!H142 -> 0 | Y69: =+'24'!H142 -> 0 | Z69: =+'25'!H142 -> 0 | AA69: =+'26'!H142 -> 0 | AB69: =+'27'!H142 -> 0 | AC69: =+'28'!H142 -> 0 | AD69: =+'29'!H142 -> 0 | AE69: =+'30'!H142 -> 0 | AF69: =+'31'!H142 -> 0
A70: =+Input!A95 -> - Other 8 | B70: =+'1'!H143 -> 0 | C70: =+'2'!H143 -> 0 | D70: =+'3'!H143 -> 0 | E70: =+'4'!H143 -> 0 | F70: =+'5'!H143 -> 0 | G70: =+'6'!H143 -> 0 | H70: =+'7'!H143 -> 0 | I70: =+'8'!H143 -> 0 | J70: =+'9'!H143 -> 0 | K70: =+'10'!H143 -> 0 | L70: =+'11'!H143 -> 0 | M70: =+'12'!H143 -> 0 | N70: =+'13'!H143 -> 0 | O70: =+'14'!H143 -> 0 | P70: =+'15'!H143 -> 0 | Q70: =+'16'!H143 -> 0 | R70: =+'17'!H143 -> 0 | S70: =+'18'!H143 -> 0 | T70: =+'19'!H143 -> 0 | U70: =+'20'!H143 -> 0 | V70: =+'21'!H143 -> 0 | W70: =+'22'!H143 -> 0 | X70: =+'23'!H143 -> 0 | Y70: =+'24'!H143 -> 0 | Z70: =+'25'!H143 -> 0 | AA70: =+'26'!H143 -> 0 | AB70: =+'27'!H143 -> 0 | AC70: =+'28'!H143 -> 0 | AD70: =+'29'!H143 -> 0 | AE70: =+'30'!H143 -> 0 | AF70: =+'31'!H143 -> 0
A71: =+Input!A96 -> - Other 9 | B71: =+'1'!H144 -> 0 | C71: =+'2'!H144 -> 0 | D71: =+'3'!H144 -> 0 | E71: =+'4'!H144 -> 0 | F71: =+'5'!H144 -> 0 | G71: =+'6'!H144 -> 0 | H71: =+'7'!H144 -> 0 | I71: =+'8'!H144 -> 0 | J71: =+'9'!H144 -> 0 | K71: =+'10'!H144 -> 0 | L71: =+'11'!H144 -> 0 | M71: =+'12'!H144 -> 0 | N71: =+'13'!H144 -> 0 | O71: =+'14'!H144 -> 0 | P71: =+'15'!H144 -> 0 | Q71: =+'16'!H144 -> 0 | R71: =+'17'!H144 -> 0 | S71: =+'18'!H144 -> 0 | T71: =+'19'!H144 -> 0 | U71: =+'20'!H144 -> 0 | V71: =+'21'!H144 -> 0 | W71: =+'22'!H144 -> 0 | X71: =+'23'!H144 -> 0 | Y71: =+'24'!H144 -> 0 | Z71: =+'25'!H144 -> 0 | AA71: =+'26'!H144 -> 0 | AB71: =+'27'!H144 -> 0 | AC71: =+'28'!H144 -> 0 | AD71: =+'29'!H144 -> 0 | AE71: =+'30'!H144 -> 0 | AF71: =+'31'!H144 -> 0
A72: =+Input!A97 -> - Other 10 | B72: =+'1'!H145 -> 0 | C72: =+'2'!H145 -> 0 | D72: =+'3'!H145 -> 0 | E72: =+'4'!H145 -> 0 | F72: =+'5'!H145 -> 0 | G72: =+'6'!H145 -> 0 | H72: =+'7'!H145 -> 0 | I72: =+'8'!H145 -> 0 | J72: =+'9'!H145 -> 0 | K72: =+'10'!H145 -> 0 | L72: =+'11'!H145 -> 0 | M72: =+'12'!H145 -> 0 | N72: =+'13'!H145 -> 0 | O72: =+'14'!H145 -> 0 | P72: =+'15'!H145 -> 0 | Q72: =+'16'!H145 -> 0 | R72: =+'17'!H145 -> 0 | S72: =+'18'!H145 -> 0 | T72: =+'19'!H145 -> 0 | U72: =+'20'!H145 -> 0 | V72: =+'21'!H145 -> 0 | W72: =+'22'!H145 -> 0 | X72: =+'23'!H145 -> 0 | Y72: =+'24'!H145 -> 0 | Z72: =+'25'!H145 -> 0 | AA72: =+'26'!H145 -> 0 | AB72: =+'27'!H145 -> 0 | AC72: =+'28'!H145 -> 0 | AD72: =+'29'!H145 -> 0 | AE72: =+'30'!H145 -> 0 | AF72: =+'31'!H145 -> 0
A73: - TOTAL | B73: =SUM(B63:B72) -> 0 | C73: =SUM(C63:C72) -> 0 | D73: =SUM(D63:D72) -> 0 | E73: =SUM(E63:E72) -> 0 | F73: =SUM(F63:F72) -> 0 | G73: =SUM(G63:G72) -> 0 | H73: =SUM(H63:H72) -> 0 | I73: =SUM(I63:I72) -> 0 | ... AF73: =SUM(AF63:AF72) -> 0
A74: - TOTAL B/FWD | B74: =+'1'!H135 -> 0 | C74: =+'2'!H135 -> 0 | D74: =+'3'!H135 -> 0 | E74: =+'4'!H135 -> 0 | F74: =+'5'!H135 -> 0 | G74: =+'6'!H135 -> 0 | H74: =+'7'!H135 -> 0 | I74: =+'8'!H135 -> 0 | J74: =+'9'!H135 -> 0 | K74: =+'10'!H135 -> 0 | L74: =+'11'!H135 -> 0 | M74: =+'12'!H135 -> 0 | N74: =+'13'!H135 -> 0 | O74: =+'14'!H135 -> 0 | P74: =+'15'!H135 -> 0 | Q74: =+'16'!H135 -> 0 | R74: =+'17'!H135 -> 0 | S74: =+'18'!H135 -> 0 | T74: =+'19'!H135 -> 0 | U74: =+'20'!H135 -> 0 | V74: =+'21'!H135 -> 0 | W74: =+'22'!H135 -> 0 | X74: =+'23'!H135 -> 0 | Y74: =+'24'!H135 -> 0 | Z74: =+'25'!H135 -> 0 | AA74: =+'26'!H135 -> 0 | AB74: =+'27'!H135 -> 0 | AC74: =+'28'!H135 -> 0 | AD74: =+'29'!H135 -> 0 | AE74: =+'30'!H135 -> 0 | AF74: =+'31'!H135 -> 0
A75: - VARIANCE | B75: =+B73-B74 -> 0 | C75: =+C73-C74 -> 0 | D75: =+D73-D74 -> 0 | E75: =+E73-E74 -> 0 | F75: =+F73-F74 -> 0 | G75: =+G73-G74 -> 0 | H75: =+H73-H74 -> 0 | I75: =+I73-I74 -> 0 | ... AF75: =+AF73-AF74 -> 0

Sheet Bank
A1: =+Input!B2 -> ENGEN JETPARK
A3: BANKING SUMMARY | B3: =+Input!B6 -> 46143
A6: CASH RECONCILIATION | B6: 1 | C6: =+B6+1 -> 2 | D6: =+C6+1 -> 3 | E6: =+D6+1 -> 4 | F6: =+E6+1 -> 5 | G6: =+F6+1 -> 6 | H6: =+G6+1 -> 7 | I6: =+H6+1 -> 8 | J6: =+I6+1 -> 9 | ... AF6: =+AE6+1 -> 31 | AG6: TOTAL
A7: - Opening Balance | C7: =+B12 -> 11.5 | D7: =+C12 -> 11.5 | E7: =+D12 -> 11.5 | F7: =+E12 -> 11.5 | G7: =+F12 -> 11.5 | H7: =+G12 -> 11.5 | I7: =+H12 -> 11.5 | J7: =+I12 -> 11.5 | ... AF7: =+AE12 -> 11.5 | AG7: =+B7 -> 0
A8: - Cash: Coins | B8: =+'1'!H57 -> 11.5 | C8: =+'2'!H57 -> 0 | D8: =+'3'!H57 -> 0 | E8: =+'4'!H57 -> 0 | F8: =+'5'!H57 -> 0 | G8: =+'6'!H57 -> 0 | H8: =+'7'!H57 -> 0 | I8: =+'8'!H57 -> 0 | J8: =+'9'!H57 -> 0 | K8: =+'10'!H57 -> 0 | L8: =+'11'!H57 -> 0 | M8: =+'12'!H57 -> 0 | N8: =+'13'!H57 -> 0 | O8: =+'14'!H57 -> 0 | P8: =+'15'!H57 -> 0 | Q8: =+'16'!H57 -> 0 | R8: =+'17'!H57 -> 0 | S8: =+'18'!H57 -> 0 | T8: =+'19'!H57 -> 0 | U8: =+'20'!H57 -> 0 | V8: =+'21'!H57 -> 0 | W8: =+'22'!H57 -> 0 | X8: =+'23'!H57 -> 0 | Y8: =+'24'!H57 -> 0 | Z8: =+'25'!H57 -> 0 | AA8: =+'26'!H57 -> 0 | AB8: =+'27'!H57 -> 0 | AC8: =+'28'!H57 -> 0 | AD8: =+'29'!H57 -> 0 | AE8: =+'30'!H57 -> 0 | AF8: =+'31'!H57 -> 0 | AG8: =SUM(B8:AF8) -> 11.5
A9: - Cash: Till | B9: =+'1'!H58 -> 0 | C9: =+'2'!H58 -> 0 | D9: =+'3'!H58 -> 0 | E9: =+'4'!H58 -> 0 | F9: =+'5'!H58 -> 0 | G9: =+'6'!H58 -> 0 | H9: =+'7'!H58 -> 0 | I9: =+'8'!H58 -> 0 | J9: =+'9'!H58 -> 0 | K9: =+'10'!H58 -> 0 | L9: =+'11'!H58 -> 0 | M9: =+'12'!H58 -> 0 | N9: =+'13'!H58 -> 0 | O9: =+'14'!H58 -> 0 | P9: =+'15'!H58 -> 0 | Q9: =+'16'!H58 -> 0 | R9: =+'17'!H58 -> 0 | S9: =+'18'!H58 -> 0 | T9: =+'19'!H58 -> 0 | U9: =+'20'!H58 -> 0 | V9: =+'21'!H58 -> 0 | W9: =+'22'!H58 -> 0 | X9: =+'23'!H58 -> 0 | Y9: =+'24'!H58 -> 0 | Z9: =+'25'!H58 -> 0 | AA9: =+'26'!H58 -> 0 | AB9: =+'27'!H58 -> 0 | AC9: =+'28'!H58 -> 0 | AD9: =+'29'!H58 -> 0 | AE9: =+'30'!H58 -> 0 | AF9: =+'31'!H58 -> 0 | AG9: =SUM(B9:AF9) -> 0
A10: - Sub Total | B10: =SUM(B7:B9) -> 11.5 | C10: =SUM(C7:C9) -> 11.5 | D10: =SUM(D7:D9) -> 11.5 | E10: =SUM(E7:E9) -> 11.5 | F10: =SUM(F7:F9) -> 11.5 | G10: =SUM(G7:G9) -> 11.5 | H10: =SUM(H7:H9) -> 11.5 | I10: =SUM(I7:I9) -> 11.5 | ... AG10: =SUM(AG7:AG9) -> 11.5
A11: - Banking Slip | AG11: =SUM(B11:AF11) -> 0
A12: - Closing Balance | B12: =+B10-B11 -> 11.5 | C12: =+C10-C11 -> 11.5 | D12: =+D10-D11 -> 11.5 | E12: =+E10-E11 -> 11.5 | F12: =+F10-F11 -> 11.5 | G12: =+G10-G11 -> 11.5 | H12: =+H10-H11 -> 11.5 | I12: =+I10-I11 -> 11.5 | ... AG12: =+AG10-AG11 -> 11.5
A14: CASH DROPS
A15: - Opening Balance | C15: =+B20 -> 0 | D15: =+C20 -> 0 | E15: =+D20 -> 0 | F15: =+E20 -> 0 | G15: =+F20 -> 0 | H15: =+G20 -> 0 | I15: =+H20 -> 0 | J15: =+I20 -> 0 | ... AF15: =+AE20 -> 0 | AG15: =+B15 -> 0
A16: - Safe Drop Total | B16: =+'1'!H60 -> 0 | C16: =+'2'!H60 -> 0 | D16: =+'3'!H60 -> 0 | E16: =+'4'!H60 -> 0 | F16: =+'5'!H60 -> 0 | G16: =+'6'!H60 -> 0 | H16: =+'7'!H60 -> 0 | I16: =+'8'!H60 -> 0 | J16: =+'9'!H60 -> 0 | K16: =+'10'!H60 -> 0 | L16: =+'11'!H60 -> 0 | M16: =+'12'!H60 -> 0 | N16: =+'13'!H60 -> 0 | O16: =+'14'!H60 -> 0 | P16: =+'15'!H60 -> 0 | Q16: =+'16'!H60 -> 0 | R16: =+'17'!H60 -> 0 | S16: =+'18'!H60 -> 0 | T16: =+'19'!H60 -> 0 | U16: =+'20'!H60 -> 0 | V16: =+'21'!H60 -> 0 | W16: =+'22'!H60 -> 0 | X16: =+'23'!H60 -> 0 | Y16: =+'24'!H60 -> 0 | Z16: =+'25'!H60 -> 0 | AA16: =+'26'!H60 -> 0 | AB16: =+'27'!H60 -> 0 | AC16: =+'28'!H60 -> 0 | AD16: =+'29'!H60 -> 0 | AE16: =+'30'!H60 -> 0 | AF16: =+'31'!H60 -> 0 | AG16: =SUM(B16:AF16) -> 0
A17: - Sub Total | B17: =SUM(B15:B16) -> 0 | C17: =SUM(C15:C16) -> 0 | D17: =SUM(D15:D16) -> 0 | E17: =SUM(E15:E16) -> 0 | F17: =SUM(F15:F16) -> 0 | G17: =SUM(G15:G16) -> 0 | H17: =SUM(H15:H16) -> 0 | I17: =SUM(I15:I16) -> 0 | ... AG17: =SUM(AG15:AG16) -> 0
A18: - Uplift Total | AG18: =SUM(B18:AF18) -> 0
A19: - Seq Number | B19: xxxxxx | C19: xxxxxx | D19: xxxxxx | E19: xxxxxx | F19: xxxxxx | G19: xxxxxx | H19: xxxxxx | I19: xxxxxx | J19: xxxxxx | K19: xxxxxx | L19: xxxxxx | M19: xxxxxx | N19: xxxxxx | O19: xxxxxx | P19: xxxxxx | Q19: xxxxxx | R19: xxxxxx | S19: xxxxxx | T19: xxxxxx | U19: xxxxxx | V19: xxxxxx | W19: xxxxxx | X19: xxxxxx | Y19: xxxxxx | Z19: xxxxxx | AA19: xxxxxx | AB19: xxxxxx | AC19: xxxxxx | AD19: xxxxxx | AE19: xxxxxx | AF19: xxxxxx
A20: - Closing Balance | B20: =+B17-B18 -> 0 | C20: =+C17-C18 -> 0 | D20: =+D17-D18 -> 0 | E20: =+E17-E18 -> 0 | F20: =+F17-F18 -> 0 | G20: =+G17-G18 -> 0 | H20: =+H17-H18 -> 0 | I20: =+I17-I18 -> 0 | ... AG20: =+AG17-AG18 -> 0
A22: SPEEDPOINT RECONCILIATION
A23: - Opening Balance | C23: =+B39 -> 19855.45 | D23: =+C39 -> 19855.45 | E23: =+D39 -> 19855.45 | F23: =+E39 -> 19855.45 | G23: =+F39 -> 19855.45 | H23: =+G39 -> 19855.45 | I23: =+H39 -> 19855.45 | J23: =+I39 -> 19855.45 | ... AF23: =+AE39 -> 19855.45 | AG23: =+B23 -> 0
A24: - Speedpoint Total | B24: =+'1'!H63 -> 19855.45 | C24: =+'2'!H63 -> 0 | D24: =+'3'!H63 -> 0 | E24: =+'4'!H63 -> 0 | F24: =+'5'!H63 -> 0 | G24: =+'6'!H63 -> 0 | H24: =+'7'!H63 -> 0 | I24: =+'8'!H63 -> 0 | J24: =+'9'!H63 -> 0 | K24: =+'10'!H63 -> 0 | L24: =+'11'!H63 -> 0 | M24: =+'12'!H63 -> 0 | N24: =+'13'!H63 -> 0 | O24: =+'14'!H63 -> 0 | P24: =+'15'!H63 -> 0 | Q24: =+'16'!H63 -> 0 | R24: =+'17'!H63 -> 0 | S24: =+'18'!H63 -> 0 | T24: =+'19'!H63 -> 0 | U24: =+'20'!H63 -> 0 | V24: =+'21'!H63 -> 0 | W24: =+'22'!H63 -> 0 | X24: =+'23'!H63 -> 0 | Y24: =+'24'!H63 -> 0 | Z24: =+'25'!H63 -> 0 | AA24: =+'26'!H63 -> 0 | AB24: =+'27'!H63 -> 0 | AC24: =+'28'!H63 -> 0 | AD24: =+'29'!H63 -> 0 | AE24: =+'30'!H63 -> 0 | AF24: =+'31'!H63 -> 0 | AG24: =SUM(B24:AF24) -> 19855.45
A25: - Sub Total | B25: =SUM(B23:B24) -> 19855.45 | C25: =SUM(C23:C24) -> 19855.45 | D25: =SUM(D23:D24) -> 19855.45 | E25: =SUM(E23:E24) -> 19855.45 | F25: =SUM(F23:F24) -> 19855.45 | G25: =SUM(G23:G24) -> 19855.45 | H25: =SUM(H23:H24) -> 19855.45 | I25: =SUM(I23:I24) -> 19855.45 | ... AG25: =SUM(AG23:AG24) -> 19855.45
A26: - Bank 1: Total | AG26: =SUM(B26:AF26) -> 0
A27: - Bank 1: Seq No. | B27: xxxxxx
A28: - Bank 2: Total | AG28: =SUM(B28:AF28) -> 0
A29: - Bank 2: Seq No. | B29: xxxxxx
A30: - Bank 3: Total | AG30: =SUM(B30:AF30) -> 0
A31: - Bank 3: Seq No. | B31: xxxxxx
A32: - Bank 4: Total | AG32: =SUM(B32:AF32) -> 0
A33: - Bank 4: Seq No. | B33: xxxxxx
A34: - Bank 5: Total | AG34: =SUM(B34:AF34) -> 0
A35: - Bank 5: Seq No. | B35: xxxxxx
A36: - Bank 6: Total | AG36: =SUM(B36:AF36) -> 0
A37: - Bank 6: Seq No. | B37: xxxxxx
A38: - Banked Total | B38: =+B26+B28+B30+B32+B34+B36 -> 0 | C38: =+C26+C28+C30+C32+C34+C36 -> 0 | D38: =+D26+D28+D30+D32+D34+D36 -> 0 | E38: =+E26+E28+E30+E32+E34+E36 -> 0 | F38: =+F26+F28+F30+F32+F34+F36 -> 0 | G38: =+G26+G28+G30+G32+G34+G36 -> 0 | H38: =+H26+H28+H30+H32+H34+H36 -> 0 | I38: =+I26+I28+I30+I32+I34+I36 -> 0 | ... AG38: =+AG26+AG28+AG30+AG32+AG34+AG36 -> 0
A39: - Closing Balance | B39: =+B25-B38 -> 19855.45 | C39: =+C25-C38 -> 19855.45 | D39: =+D25-D38 -> 19855.45 | E39: =+E25-E38 -> 19855.45 | F39: =+F25-F38 -> 19855.45 | G39: =+G25-G38 -> 19855.45 | H39: =+H25-H38 -> 19855.45 | I39: =+I25-I38 -> 19855.45 | ... AG39: =+AG25-AG38 -> 19855.45
A41: DEBTORS RECONCILIATION
A42: - Opening Balance | C42: =+B46 -> 0 | D42: =+C46 -> 0 | E42: =+D46 -> 0 | F42: =+E46 -> 0 | G42: =+F46 -> 0 | H42: =+G46 -> 0 | I42: =+H46 -> 0 | J42: =+I46 -> 0 | ... AF42: =+AE46 -> 0 | AG42: =+B42 -> 0
A43: - On Account Total | B43: =+'1'!H69 -> 0 | C43: =+'2'!H69 -> 0 | D43: =+'3'!H69 -> 0 | E43: =+'4'!H69 -> 0 | F43: =+'5'!H69 -> 0 | G43: =+'6'!H69 -> 0 | H43: =+'7'!H69 -> 0 | I43: =+'8'!H69 -> 0 | J43: =+'9'!H69 -> 0 | K43: =+'10'!H69 -> 0 | L43: =+'11'!H69 -> 0 | M43: =+'12'!H69 -> 0 | N43: =+'13'!H69 -> 0 | O43: =+'14'!H69 -> 0 | P43: =+'15'!H69 -> 0 | Q43: =+'16'!H69 -> 0 | R43: =+'17'!H69 -> 0 | S43: =+'18'!H69 -> 0 | T43: =+'19'!H69 -> 0 | U43: =+'20'!H69 -> 0 | V43: =+'21'!H69 -> 0 | W43: =+'22'!H69 -> 0 | X43: =+'23'!H69 -> 0 | Y43: =+'24'!H69 -> 0 | Z43: =+'25'!H69 -> 0 | AA43: =+'26'!H69 -> 0 | AB43: =+'27'!H69 -> 0 | AC43: =+'28'!H69 -> 0 | AD43: =+'29'!H69 -> 0 | AE43: =+'30'!H69 -> 0 | AF43: =+'31'!H69 -> 0 | AG43: =SUM(B43:AF43) -> 0
A44: - Debtor Receipts | B44: =+'1'!H70 -> 0 | C44: =+'2'!H70 -> 0 | D44: =+'3'!H70 -> 0 | E44: =+'4'!H70 -> 0 | F44: =+'5'!H70 -> 0 | G44: =+'6'!H70 -> 0 | H44: =+'7'!H70 -> 0 | I44: =+'8'!H70 -> 0 | J44: =+'9'!H70 -> 0 | K44: =+'10'!H70 -> 0 | L44: =+'11'!H70 -> 0 | M44: =+'12'!H70 -> 0 | N44: =+'13'!H70 -> 0 | O44: =+'14'!H70 -> 0 | P44: =+'15'!H70 -> 0 | Q44: =+'16'!H70 -> 0 | R44: =+'17'!H70 -> 0 | S44: =+'18'!H70 -> 0 | T44: =+'19'!H70 -> 0 | U44: =+'20'!H70 -> 0 | V44: =+'21'!H70 -> 0 | W44: =+'22'!H70 -> 0 | X44: =+'23'!H70 -> 0 | Y44: =+'24'!H70 -> 0 | Z44: =+'25'!H70 -> 0 | AA44: =+'26'!H70 -> 0 | AB44: =+'27'!H70 -> 0 | AC44: =+'28'!H70 -> 0 | AD44: =+'29'!H70 -> 0 | AE44: =+'30'!H70 -> 0 | AF44: =+'31'!H70 -> 0 | AG44: =SUM(B44:AF44) -> 0
A45: - Debtor Jnls | AG45: =SUM(B45:AF45) -> 0
A46: - Closing Balance | B46: =SUM(B42:B45) -> 0 | C46: =SUM(C42:C45) -> 0 | D46: =SUM(D42:D45) -> 0 | E46: =SUM(E42:E45) -> 0 | F46: =SUM(F42:F45) -> 0 | G46: =SUM(G42:G45) -> 0 | H46: =SUM(H42:H45) -> 0 | I46: =SUM(I42:I45) -> 0 | ... AG46: =SUM(AG42:AG45) -> 0
A47: - Total: Age Analysis | AG47: =SUM(B47:AF47) -> 0
A48: - Variance | B48: =+B46-B47 -> 0 | C48: =+C46-C47 -> 0 | D48: =+D46-D47 -> 0 | E48: =+E46-E47 -> 0 | F48: =+F46-F47 -> 0 | G48: =+G46-G47 -> 0 | H48: =+H46-H47 -> 0 | I48: =+I46-I47 -> 0 | ... AG48: =+AG46-AG47 -> 0
A50: EFT RECONCILIATION
A51: - Opening Balance | C51: =+B54 -> 0 | D51: =+C54 -> 0 | E51: =+D54 -> 0 | F51: =+E54 -> 0 | G51: =+F54 -> 0 | H51: =+G54 -> 0 | I51: =+H54 -> 0 | J51: =+I54 -> 0 | ... AF51: =+AE54 -> 0 | AG51: =+B51 -> 0
A52: - EFT Total B/Fwd | B52: =+'1'!H74 -> 0 | C52: =+'2'!H74 -> 0 | D52: =+'3'!H74 -> 0 | E52: =+'4'!H74 -> 0 | F52: =+'5'!H74 -> 0 | G52: =+'6'!H74 -> 0 | H52: =+'7'!H74 -> 0 | I52: =+'8'!H74 -> 0 | J52: =+'9'!H74 -> 0 | K52: =+'10'!H74 -> 0 | L52: =+'11'!H74 -> 0 | M52: =+'12'!H74 -> 0 | N52: =+'13'!H74 -> 0 | O52: =+'14'!H74 -> 0 | P52: =+'15'!H74 -> 0 | Q52: =+'16'!H74 -> 0 | R52: =+'17'!H74 -> 0 | S52: =+'18'!H74 -> 0 | T52: =+'19'!H74 -> 0 | U52: =+'20'!H74 -> 0 | V52: =+'21'!H74 -> 0 | W52: =+'22'!H74 -> 0 | X52: =+'23'!H74 -> 0 | Y52: =+'24'!H74 -> 0 | Z52: =+'25'!H74 -> 0 | AA52: =+'26'!H74 -> 0 | AB52: =+'27'!H74 -> 0 | AC52: =+'28'!H74 -> 0 | AD52: =+'29'!H74 -> 0 | AE52: =+'30'!H74 -> 0 | AF52: =+'31'!H74 -> 0 | AG52: =SUM(B52:AF52) -> 0
A53: - Bank Statement Receipt | AG53: =SUM(B53:AF53) -> 0
A54: - Closing Balance | B54: =+B52-B53 -> 0 | C54: =+C52-C53 -> 0 | D54: =+D52-D53 -> 0 | E54: =+E52-E53 -> 0 | F54: =+F52-F53 -> 0 | G54: =+G52-G53 -> 0 | H54: =+H52-H53 -> 0 | I54: =+I52-I53 -> 0 | ... AG54: =+AG52-AG53 -> 0
A56: LOYALTY RECONCILIATION
A57: - Opening Balance | C57: =+B60 -> 0 | D57: =+C60 -> 0 | E57: =+D60 -> 0 | F57: =+E60 -> 0 | G57: =+F60 -> 0 | H57: =+G60 -> 0 | I57: =+H60 -> 0 | J57: =+I60 -> 0 | ... AF57: =+AE60 -> 0 | AG57: =+B57 -> 0
A58: - Loyalty Total | B58: =+'1'!H77 -> 0 | C58: =+'2'!H77 -> 0 | D58: =+'3'!H77 -> 0 | E58: =+'4'!H77 -> 0 | F58: =+'5'!H77 -> 0 | G58: =+'6'!H77 -> 0 | H58: =+'7'!H77 -> 0 | I58: =+'8'!H77 -> 0 | J58: =+'9'!H77 -> 0 | K58: =+'10'!H77 -> 0 | L58: =+'11'!H77 -> 0 | M58: =+'12'!H77 -> 0 | N58: =+'13'!H77 -> 0 | O58: =+'14'!H77 -> 0 | P58: =+'15'!H77 -> 0 | Q58: =+'16'!H77 -> 0 | R58: =+'17'!H77 -> 0 | S58: =+'18'!H77 -> 0 | T58: =+'19'!H77 -> 0 | U58: =+'20'!H77 -> 0 | V58: =+'21'!H77 -> 0 | W58: =+'22'!H77 -> 0 | X58: =+'23'!H77 -> 0 | Y58: =+'24'!H77 -> 0 | Z58: =+'25'!H77 -> 0 | AA58: =+'26'!H77 -> 0 | AB58: =+'27'!H77 -> 0 | AC58: =+'28'!H77 -> 0 | AD58: =+'29'!H77 -> 0 | AE58: =+'30'!H77 -> 0 | AF58: =+'31'!H77 -> 0 | AG58: =SUM(B58:AF58) -> 0
A59: - Bank Statement Receipt | AG59: =SUM(B59:AF59) -> 0
A60: - Closing Balance | B60: =+B58-B59 -> 0 | C60: =+C58-C59 -> 0 | D60: =+D58-D59 -> 0 | E60: =+E58-E59 -> 0 | F60: =+F58-F59 -> 0 | G60: =+G58-G59 -> 0 | H60: =+H58-H59 -> 0 | I60: =+I58-I59 -> 0 | ... AG60: =+AG58-AG59 -> 0
A62: TO SETTLE
A63: - Opening Balance | C63: =+B66 -> 0 | D63: =+C66 -> 0 | E63: =+D66 -> 0 | F63: =+E66 -> 0 | G63: =+F66 -> 0 | H63: =+G66 -> 0 | I63: =+H66 -> 0 | J63: =+I66 -> 0 | ... AF63: =+AE66 -> 0 | AG63: =+B63 -> 0
A64: - To Settle Total | B64: =+'1'!H79 -> 0 | C64: =+'2'!H79 -> 0 | D64: =+'3'!H79 -> 0 | E64: =+'4'!H79 -> 0 | F64: =+'5'!H79 -> 0 | G64: =+'6'!H79 -> 0 | H64: =+'7'!H79 -> 0 | I64: =+'8'!H79 -> 0 | J64: =+'9'!H79 -> 0 | K64: =+'10'!H79 -> 0 | L64: =+'11'!H79 -> 0 | M64: =+'12'!H79 -> 0 | N64: =+'13'!H79 -> 0 | O64: =+'14'!H79 -> 0 | P64: =+'15'!H79 -> 0 | Q64: =+'16'!H79 -> 0 | R64: =+'17'!H79 -> 0 | S64: =+'18'!H79 -> 0 | T64: =+'19'!H79 -> 0 | U64: =+'20'!H79 -> 0 | V64: =+'21'!H79 -> 0 | W64: =+'22'!H79 -> 0 | X64: =+'23'!H79 -> 0 | Y64: =+'24'!H79 -> 0 | Z64: =+'25'!H79 -> 0 | AA64: =+'26'!H79 -> 0 | AB64: =+'27'!H79 -> 0 | AC64: =+'28'!H79 -> 0 | AD64: =+'29'!H79 -> 0 | AE64: =+'30'!H79 -> 0 | AF64: =+'31'!H79 -> 0 | AG64: =SUM(B64:AF64) -> 0
A65: - Receipt: Cash | AG65: =SUM(B65:AF65) -> 0
A66: - Closing Balance | B66: =+B64-B65 -> 0 | C66: =+C64-C65 -> 0 | D66: =+D64-D65 -> 0 | E66: =+E64-E65 -> 0 | F66: =+F64-F65 -> 0 | G66: =+G64-G65 -> 0 | H66: =+H64-H65 -> 0 | I66: =+I64-I65 -> 0 | ... AG66: =+AG64-AG65 -> 0

Sheet SS26
A1: =+Input!B2 -> ENGEN JETPARK
A3: SS26 Report | C3: =+Input!B6 -> 46143
A6: SUMMARY: BY GRADE | B6: Diesel | C6: ULP: 93 | D6: ULP: 95 | E6: TOTAL
A7: - Opening Balance | B7: =+B18+F18 -> 0 | C7: =+D18 -> 0 | D7: =+C18+E18 -> 0 | E7: =SUM(B7:D7) -> 0
A8: - Purchases | B8: =+B19+F19 -> 0 | C8: =+D19 -> 0 | D8: =+C19+E19 -> 0 | E8: =SUM(B8:D8) -> 0
A9: - Litres Sold | B9: =+B20+F20 -> 1659.39 | C9: =+D20 -> 40.06 | D9: =+C20+E20 -> 1920.7 | E9: =SUM(B9:D9) -> 3620.15
A10: - Closing Balance | B10: =+B7+B8-B9 -> -1659.39 | C10: =+C7+C8-C9 -> -40.06 | D10: =+D7+D8-D9 -> -1920.7 | E10: =+E7+E8-E9 -> -3620.15
A11: - ATG | B11: =+B22+F22 -> 0 | C11: =+D22 -> 0 | D11: =+C22+E22 -> 0 | E11: =SUM(B11:D11) -> 0
A12: - Variance | B12: =+B11-B10 -> 1659.39 | C12: =+C11-C10 -> 40.06 | D12: =+D11-D10 -> 1920.7 | E12: =+E11-E10 -> 3620.15
A13: - Control Total | B13: =+B23+F23 -> 1659.39 | C13: =+C23+G23 -> 5540.85 | D13: =+D23+H23 -> 40.06 | E13: =+E23+I23 -> 0
A14: - Variance | B14: =+B13-B12 -> 0 | C14: =+C13-C12 -> 5500.79 | D14: =+D13-D12 -> -1880.64 | E14: =+E13-E12 -> -3620.15
A17: SUMMARY: BY TANK | B17: Tank: 1 | C17: Tank: 2 | D17: Tank: 3 | E17: Tank: 4 | F17: Tank: 5 | G17: TOTAL
A18: - Opening Balance | B18: =+C29 -> 0 | C18: =+C65 -> 0 | D18: =+C101 -> 0 | E18: =+K65 -> 0 | F18: =+K29 -> 0 | G18: =SUM(B18:F18) -> 0
A19: - Purchases | B19: =+D60 -> 0 | C19: =+D96 -> 0 | D19: =+D132 -> 0 | E19: =+L96 -> 0 | F19: =+L60 -> 0 | G19: =SUM(B19:F19) -> 0
A20: - Litres Sold | B20: =+E60 -> 1659.39 | C20: =+E96 -> 1920.7 | D20: =+E132 -> 40.06 | E20: =+M96 -> 0 | F20: =+M60 -> 0 | G20: =SUM(B20:F20) -> 3620.15
A21: - Closing Balance | B21: =+B18+B19-B20 -> -1659.39 | C21: =+C18+C19-C20 -> -1920.7 | D21: =+D18+D19-D20 -> -40.06 | E21: =+E18+E19-E20 -> 0 | F21: =+F18+F19-F20 -> 0 | G21: =+G18+G19-G20 -> -3620.15
A22: - ATG | G22: =SUM(B22:F22) -> 0 | H22: Complete this line every day
A23: - Variance | B23: =+B22-B21 -> 1659.39 | C23: =+C22-C21 -> 1920.7 | D23: =+D22-D21 -> 40.06 | E23: =+E22-E21 -> 0 | F23: =+F22-F21 -> 0 | G23: =+G22-G21 -> 3620.15
A24: - % Variance | B24: =+B23/B22 -> #DIV/0! | C24: =+C23/C22 -> #DIV/0! | D24: =+D23/D22 -> #DIV/0! | E24: =+E23/E22 -> #DIV/0! | F24: =+F23/F22 -> #DIV/0! | G24: =+G23/G22 -> #DIV/0!
C27: TANK 1: DIESEL | K27: TANK 5: DIESEL | S27: TOTAL: DIESEL
C28: O/Bal | D28: Purch | E28: Sold | F28: C/Bal | G28: ATG | H28: Variance | I28: Prog Vari | K28: O/Bal | L28: Purch | M28: Sold | N28: C/Bal | O28: ATG | P28: Variance | Q28: Prog Vari | S28: O/Bal | T28: Purch | U28: Sold | V28: C/Bal | W28: ATG | X28: Variance | Y28: Prog Vari
A29: =+Input!B10 -> Friday | B29: =+Input!C10 -> 46143 | C29: =+Input!B49 -> 0 | D29: =+'1'!B11 -> 0 | E29: =+'1'!B12 -> 1659.39 | F29: =+C29+D29-E29 -> -1659.39 | H29: =+G29-F29 -> 1659.39 | I29: =+H29 -> 1659.39 | K29: =+Input!J49 -> 0 | L29: =+'1'!F11 -> 0 | M29: =+'1'!F12 -> 0 | N29: =+K29+L29-M29 -> 0 | P29: =+O29-N29 -> 0 | Q29: =+P29 -> 0 | S29: =+C29+K29 -> 0 | T29: =+D29+L29 -> 0 | U29: =+E29+M29 -> 1659.39 | V29: =+S29+T29-U29 -> -1659.39 | W29: =+G29+O29 -> 0 | X29: =+W29-V29 -> 1659.39 | Y29: =+X29 -> 1659.39
A30: =+Input!B11 -> Saturday | B30: =+Input!C11 -> 46144 | C30: =+F29 -> -1659.39 | D30: =+'2'!B11 -> 0 | E30: =+'2'!B12 -> 0 | F30: =+C30+D30-E30 -> -1659.39 | H30: =+G30-F30 -> 1659.39 | I30: =+I29+H30 -> 3318.78 | K30: =+N29 -> 0 | L30: =+'2'!F11 -> 0 | M30: =+'2'!F12 -> 0 | N30: =+K30+L30-M30 -> 0 | P30: =+O30-N30 -> 0 | Q30: =+Q29+P30 -> 0 | S30: =+V29 -> -1659.39 | T30: =+D30+L30 -> 0 | U30: =+E30+M30 -> 0 | V30: =+S30+T30-U30 -> -1659.39 | W30: =+G30+O30 -> 0 | X30: =+W30-V30 -> 1659.39 | Y30: =+Y29+X30 -> 3318.78
A31: =+Input!B12 -> Sunday | B31: =+Input!C12 -> 46145 | C31: =+F30 -> -1659.39 | D31: =+'3'!B11 -> 0 | E31: =+'3'!B12 -> 0 | F31: =+C31+D31-E31 -> -1659.39 | H31: =+G31-F31 -> 1659.39 | I31: =+I30+H31 -> 4978.17 | K31: =+N30 -> 0 | L31: =+'3'!F11 -> 0 | M31: =+'3'!F12 -> 0 | N31: =+K31+L31-M31 -> 0 | P31: =+O31-N31 -> 0 | Q31: =+Q30+P31 -> 0 | S31: =+V30 -> -1659.39 | T31: =+D31+L31 -> 0 | U31: =+E31+M31 -> 0 | V31: =+S31+T31-U31 -> -1659.39 | W31: =+G31+O31 -> 0 | X31: =+W31-V31 -> 1659.39 | Y31: =+Y30+X31 -> 4978.17
A32: =+Input!B13 -> Monday | B32: =+Input!C13 -> 46146 | C32: =+F31 -> -1659.39 | D32: =+'4'!B11 -> 0 | E32: =+'4'!B12 -> 0 | F32: =+C32+D32-E32 -> -1659.39 | H32: =+G32-F32 -> 1659.39 | I32: =+I31+H32 -> 6637.56 | K32: =+N31 -> 0 | L32: =+'4'!F11 -> 0 | M32: =+'4'!F12 -> 0 | N32: =+K32+L32-M32 -> 0 | P32: =+O32-N32 -> 0 | Q32: =+Q31+P32 -> 0 | S32: =+V31 -> -1659.39 | T32: =+D32+L32 -> 0 | U32: =+E32+M32 -> 0 | V32: =+S32+T32-U32 -> -1659.39 | W32: =+G32+O32 -> 0 | X32: =+W32-V32 -> 1659.39 | Y32: =+Y31+X32 -> 6637.56
A33: =+Input!B14 -> Tuesday | B33: =+Input!C14 -> 46147 | C33: =+F32 -> -1659.39 | D33: =+'5'!B11 -> 0 | E33: =+'5'!B12 -> 0 | F33: =+C33+D33-E33 -> -1659.39 | H33: =+G33-F33 -> 1659.39 | I33: =+I32+H33 -> 8296.95 | K33: =+N32 -> 0 | L33: =+'5'!F11 -> 0 | M33: =+'5'!F12 -> 0 | N33: =+K33+L33-M33 -> 0 | P33: =+O33-N33 -> 0 | Q33: =+Q32+P33 -> 0 | S33: =+V32 -> -1659.39 | T33: =+D33+L33 -> 0 | U33: =+E33+M33 -> 0 | V33: =+S33+T33-U33 -> -1659.39 | W33: =+G33+O33 -> 0 | X33: =+W33-V33 -> 1659.39 | Y33: =+Y32+X33 -> 8296.95
A34: =+Input!B15 -> Wednesday | B34: =+Input!C15 -> 46148 | C34: =+F33 -> -1659.39 | D34: =+'6'!B11 -> 0 | E34: =+'6'!B12 -> 0 | F34: =+C34+D34-E34 -> -1659.39 | H34: =+G34-F34 -> 1659.39 | I34: =+I33+H34 -> 9956.34 | K34: =+N33 -> 0 | L34: =+'6'!F11 -> 0 | M34: =+'6'!F12 -> 0 | N34: =+K34+L34-M34 -> 0 | P34: =+O34-N34 -> 0 | Q34: =+Q33+P34 -> 0 | S34: =+V33 -> -1659.39 | T34: =+D34+L34 -> 0 | U34: =+E34+M34 -> 0 | V34: =+S34+T34-U34 -> -1659.39 | W34: =+G34+O34 -> 0 | X34: =+W34-V34 -> 1659.39 | Y34: =+Y33+X34 -> 9956.34
A35: =+Input!B16 -> Thursday | B35: =+Input!C16 -> 46149 | C35: =+F34 -> -1659.39 | D35: =+'7'!B11 -> 0 | E35: =+'7'!B12 -> 0 | F35: =+C35+D35-E35 -> -1659.39 | H35: =+G35-F35 -> 1659.39 | I35: =+I34+H35 -> 11615.73 | K35: =+N34 -> 0 | L35: =+'7'!F11 -> 0 | M35: =+'7'!F12 -> 0 | N35: =+K35+L35-M35 -> 0 | P35: =+O35-N35 -> 0 | Q35: =+Q34+P35 -> 0 | S35: =+V34 -> -1659.39 | T35: =+D35+L35 -> 0 | U35: =+E35+M35 -> 0 | V35: =+S35+T35-U35 -> -1659.39 | W35: =+G35+O35 -> 0 | X35: =+W35-V35 -> 1659.39 | Y35: =+Y34+X35 -> 11615.73
A36: =+Input!B17 -> Friday | B36: =+Input!C17 -> 46150 | C36: =+F35 -> -1659.39 | D36: =+'8'!B11 -> 0 | E36: =+'8'!B12 -> 0 | F36: =+C36+D36-E36 -> -1659.39 | H36: =+G36-F36 -> 1659.39 | I36: =+I35+H36 -> 13275.12 | K36: =+N35 -> 0 | L36: =+'8'!F11 -> 0 | M36: =+'8'!F12 -> 0 | N36: =+K36+L36-M36 -> 0 | P36: =+O36-N36 -> 0 | Q36: =+Q35+P36 -> 0 | S36: =+V35 -> -1659.39 | T36: =+D36+L36 -> 0 | U36: =+E36+M36 -> 0 | V36: =+S36+T36-U36 -> -1659.39 | W36: =+G36+O36 -> 0 | X36: =+W36-V36 -> 1659.39 | Y36: =+Y35+X36 -> 13275.12
A37: =+Input!B18 -> Saturday | B37: =+Input!C18 -> 46151 | C37: =+F36 -> -1659.39 | D37: =+'9'!B11 -> 0 | E37: =+'9'!B12 -> 0 | F37: =+C37+D37-E37 -> -1659.39 | H37: =+G37-F37 -> 1659.39 | I37: =+I36+H37 -> 14934.51 | K37: =+N36 -> 0 | L37: =+'9'!F11 -> 0 | M37: =+'9'!F12 -> 0 | N37: =+K37+L37-M37 -> 0 | P37: =+O37-N37 -> 0 | Q37: =+Q36+P37 -> 0 | S37: =+V36 -> -1659.39 | T37: =+D37+L37 -> 0 | U37: =+E37+M37 -> 0 | V37: =+S37+T37-U37 -> -1659.39 | W37: =+G37+O37 -> 0 | X37: =+W37-V37 -> 1659.39 | Y37: =+Y36+X37 -> 14934.51
A38: =+Input!B19 -> Sunday | B38: =+Input!C19 -> 46152 | C38: =+F37 -> -1659.39 | D38: =+'10'!B11 -> 0 | E38: =+'10'!B12 -> 0 | F38: =+C38+D38-E38 -> -1659.39 | H38: =+G38-F38 -> 1659.39 | I38: =+I37+H38 -> 16593.9 | K38: =+N37 -> 0 | L38: =+'10'!F11 -> 0 | M38: =+'10'!F12 -> 0 | N38: =+K38+L38-M38 -> 0 | P38: =+O38-N38 -> 0 | Q38: =+Q37+P38 -> 0 | S38: =+V37 -> -1659.39 | T38: =+D38+L38 -> 0 | U38: =+E38+M38 -> 0 | V38: =+S38+T38-U38 -> -1659.39 | W38: =+G38+O38 -> 0 | X38: =+W38-V38 -> 1659.39 | Y38: =+Y37+X38 -> 16593.9
A39: =+Input!B20 -> Monday | B39: =+Input!C20 -> 46153 | C39: =+F38 -> -1659.39 | D39: =+'11'!B11 -> 0 | E39: =+'11'!B12 -> 0 | F39: =+C39+D39-E39 -> -1659.39 | H39: =+G39-F39 -> 1659.39 | I39: =+I38+H39 -> 18253.29 | K39: =+N38 -> 0 | L39: =+'11'!F11 -> 0 | M39: =+'11'!F12 -> 0 | N39: =+K39+L39-M39 -> 0 | P39: =+O39-N39 -> 0 | Q39: =+Q38+P39 -> 0 | S39: =+V38 -> -1659.39 | T39: =+D39+L39 -> 0 | U39: =+E39+M39 -> 0 | V39: =+S39+T39-U39 -> -1659.39 | W39: =+G39+O39 -> 0 | X39: =+W39-V39 -> 1659.39 | Y39: =+Y38+X39 -> 18253.29
A40: =+Input!B21 -> Tuesday | B40: =+Input!C21 -> 46154 | C40: =+F39 -> -1659.39 | D40: =+'12'!B11 -> 0 | E40: =+'12'!B12 -> 0 | F40: =+C40+D40-E40 -> -1659.39 | H40: =+G40-F40 -> 1659.39 | I40: =+I39+H40 -> 19912.68 | K40: =+N39 -> 0 | L40: =+'12'!F11 -> 0 | M40: =+'12'!F12 -> 0 | N40: =+K40+L40-M40 -> 0 | P40: =+O40-N40 -> 0 | Q40: =+Q39+P40 -> 0 | S40: =+V39 -> -1659.39 | T40: =+D40+L40 -> 0 | U40: =+E40+M40 -> 0 | V40: =+S40+T40-U40 -> -1659.39 | W40: =+G40+O40 -> 0 | X40: =+W40-V40 -> 1659.39 | Y40: =+Y39+X40 -> 19912.68
A41: =+Input!B22 -> Wednesday | B41: =+Input!C22 -> 46155 | C41: =+F40 -> -1659.39 | D41: =+'13'!B11 -> 0 | E41: =+'13'!B12 -> 0 | F41: =+C41+D41-E41 -> -1659.39 | H41: =+G41-F41 -> 1659.39 | I41: =+I40+H41 -> 21572.07 | K41: =+N40 -> 0 | L41: =+'13'!F11 -> 0 | M41: =+'13'!F12 -> 0 | N41: =+K41+L41-M41 -> 0 | P41: =+O41-N41 -> 0 | Q41: =+Q40+P41 -> 0 | S41: =+V40 -> -1659.39 | T41: =+D41+L41 -> 0 | U41: =+E41+M41 -> 0 | V41: =+S41+T41-U41 -> -1659.39 | W41: =+G41+O41 -> 0 | X41: =+W41-V41 -> 1659.39 | Y41: =+Y40+X41 -> 21572.07
A42: =+Input!B23 -> Thursday | B42: =+Input!C23 -> 46156 | C42: =+F41 -> -1659.39 | D42: =+'14'!B11 -> 0 | E42: =+'14'!B12 -> 0 | F42: =+C42+D42-E42 -> -1659.39 | H42: =+G42-F42 -> 1659.39 | I42: =+I41+H42 -> 23231.46 | K42: =+N41 -> 0 | L42: =+'14'!F11 -> 0 | M42: =+'14'!F12 -> 0 | N42: =+K42+L42-M42 -> 0 | P42: =+O42-N42 -> 0 | Q42: =+Q41+P42 -> 0 | S42: =+V41 -> -1659.39 | T42: =+D42+L42 -> 0 | U42: =+E42+M42 -> 0 | V42: =+S42+T42-U42 -> -1659.39 | W42: =+G42+O42 -> 0 | X42: =+W42-V42 -> 1659.39 | Y42: =+Y41+X42 -> 23231.46
A43: =+Input!B24 -> Friday | B43: =+Input!C24 -> 46157 | C43: =+F42 -> -1659.39 | D43: =+'15'!B11 -> 0 | E43: =+'15'!B12 -> 0 | F43: =+C43+D43-E43 -> -1659.39 | H43: =+G43-F43 -> 1659.39 | I43: =+I42+H43 -> 24890.85 | K43: =+N42 -> 0 | L43: =+'15'!F11 -> 0 | M43: =+'15'!F12 -> 0 | N43: =+K43+L43-M43 -> 0 | P43: =+O43-N43 -> 0 | Q43: =+Q42+P43 -> 0 | S43: =+V42 -> -1659.39 | T43: =+D43+L43 -> 0 | U43: =+E43+M43 -> 0 | V43: =+S43+T43-U43 -> -1659.39 | W43: =+G43+O43 -> 0 | X43: =+W43-V43 -> 1659.39 | Y43: =+Y42+X43 -> 24890.85
A44: =+Input!B25 -> Saturday | B44: =+Input!C25 -> 46158 | C44: =+F43 -> -1659.39 | D44: =+'16'!B11 -> 0 | E44: =+'16'!B12 -> 0 | F44: =+C44+D44-E44 -> -1659.39 | H44: =+G44-F44 -> 1659.39 | I44: =+I43+H44 -> 26550.24 | K44: =+N43 -> 0 | L44: =+'16'!F11 -> 0 | M44: =+'16'!F12 -> 0 | N44: =+K44+L44-M44 -> 0 | P44: =+O44-N44 -> 0 | Q44: =+Q43+P44 -> 0 | S44: =+V43 -> -1659.39 | T44: =+D44+L44 -> 0 | U44: =+E44+M44 -> 0 | V44: =+S44+T44-U44 -> -1659.39 | W44: =+G44+O44 -> 0 | X44: =+W44-V44 -> 1659.39 | Y44: =+Y43+X44 -> 26550.24
A45: =+Input!B26 -> Sunday | B45: =+Input!C26 -> 46159 | C45: =+F44 -> -1659.39 | D45: =+'17'!B11 -> 0 | E45: =+'17'!B12 -> 0 | F45: =+C45+D45-E45 -> -1659.39 | H45: =+G45-F45 -> 1659.39 | I45: =+I44+H45 -> 28209.63 | K45: =+N44 -> 0 | L45: =+'17'!F11 -> 0 | M45: =+'17'!F12 -> 0 | N45: =+K45+L45-M45 -> 0 | P45: =+O45-N45 -> 0 | Q45: =+Q44+P45 -> 0 | S45: =+V44 -> -1659.39 | T45: =+D45+L45 -> 0 | U45: =+E45+M45 -> 0 | V45: =+S45+T45-U45 -> -1659.39 | W45: =+G45+O45 -> 0 | X45: =+W45-V45 -> 1659.39 | Y45: =+Y44+X45 -> 28209.63
A46: =+Input!B27 -> Monday | B46: =+Input!C27 -> 46160 | C46: =+F45 -> -1659.39 | D46: =+'18'!B11 -> 0 | E46: =+'18'!B12 -> 0 | F46: =+C46+D46-E46 -> -1659.39 | H46: =+G46-F46 -> 1659.39 | I46: =+I45+H46 -> 29869.02 | K46: =+N45 -> 0 | L46: =+'18'!F11 -> 0 | M46: =+'18'!F12 -> 0 | N46: =+K46+L46-M46 -> 0 | P46: =+O46-N46 -> 0 | Q46: =+Q45+P46 -> 0 | S46: =+V45 -> -1659.39 | T46: =+D46+L46 -> 0 | U46: =+E46+M46 -> 0 | V46: =+S46+T46-U46 -> -1659.39 | W46: =+G46+O46 -> 0 | X46: =+W46-V46 -> 1659.39 | Y46: =+Y45+X46 -> 29869.02
A47: =+Input!B28 -> Tuesday | B47: =+Input!C28 -> 46161 | C47: =+F46 -> -1659.39 | D47: =+'19'!B11 -> 0 | E47: =+'19'!B12 -> 0 | F47: =+C47+D47-E47 -> -1659.39 | H47: =+G47-F47 -> 1659.39 | I47: =+I46+H47 -> 31528.41 | K47: =+N46 -> 0 | L47: =+'19'!F11 -> 0 | M47: =+'19'!F12 -> 0 | N47: =+K47+L47-M47 -> 0 | P47: =+O47-N47 -> 0 | Q47: =+Q46+P47 -> 0 | S47: =+V46 -> -1659.39 | T47: =+D47+L47 -> 0 | U47: =+E47+M47 -> 0 | V47: =+S47+T47-U47 -> -1659.39 | W47: =+G47+O47 -> 0 | X47: =+W47-V47 -> 1659.39 | Y47: =+Y46+X47 -> 31528.41
A48: =+Input!B29 -> Wednesday | B48: =+Input!C29 -> 46162 | C48: =+F47 -> -1659.39 | D48: =+'20'!B11 -> 0 | E48: =+'20'!B12 -> 0 | F48: =+C48+D48-E48 -> -1659.39 | H48: =+G48-F48 -> 1659.39 | I48: =+I47+H48 -> 33187.8 | K48: =+N47 -> 0 | L48: =+'20'!F11 -> 0 | M48: =+'20'!F12 -> 0 | N48: =+K48+L48-M48 -> 0 | P48: =+O48-N48 -> 0 | Q48: =+Q47+P48 -> 0 | S48: =+V47 -> -1659.39 | T48: =+D48+L48 -> 0 | U48: =+E48+M48 -> 0 | V48: =+S48+T48-U48 -> -1659.39 | W48: =+G48+O48 -> 0 | X48: =+W48-V48 -> 1659.39 | Y48: =+Y47+X48 -> 33187.8
A49: =+Input!B30 -> Thursday | B49: =+Input!C30 -> 46163 | C49: =+F48 -> -1659.39 | D49: =+'21'!B11 -> 0 | E49: =+'21'!B12 -> 0 | F49: =+C49+D49-E49 -> -1659.39 | H49: =+G49-F49 -> 1659.39 | I49: =+I48+H49 -> 34847.19 | K49: =+N48 -> 0 | L49: =+'21'!F11 -> 0 | M49: =+'21'!F12 -> 0 | N49: =+K49+L49-M49 -> 0 | P49: =+O49-N49 -> 0 | Q49: =+Q48+P49 -> 0 | S49: =+V48 -> -1659.39 | T49: =+D49+L49 -> 0 | U49: =+E49+M49 -> 0 | V49: =+S49+T49-U49 -> -1659.39 | W49: =+G49+O49 -> 0 | X49: =+W49-V49 -> 1659.39 | Y49: =+Y48+X49 -> 34847.19
A50: =+Input!B31 -> Friday | B50: =+Input!C31 -> 46164 | C50: =+F49 -> -1659.39 | D50: =+'22'!B11 -> 0 | E50: =+'22'!B12 -> 0 | F50: =+C50+D50-E50 -> -1659.39 | H50: =+G50-F50 -> 1659.39 | I50: =+I49+H50 -> 36506.58 | K50: =+N49 -> 0 | L50: =+'22'!F11 -> 0 | M50: =+'22'!F12 -> 0 | N50: =+K50+L50-M50 -> 0 | P50: =+O50-N50 -> 0 | Q50: =+Q49+P50 -> 0 | S50: =+V49 -> -1659.39 | T50: =+D50+L50 -> 0 | U50: =+E50+M50 -> 0 | V50: =+S50+T50-U50 -> -1659.39 | W50: =+G50+O50 -> 0 | X50: =+W50-V50 -> 1659.39 | Y50: =+Y49+X50 -> 36506.58
A51: =+Input!B32 -> Saturday | B51: =+Input!C32 -> 46165 | C51: =+F50 -> -1659.39 | D51: =+'23'!B11 -> 0 | E51: =+'23'!B12 -> 0 | F51: =+C51+D51-E51 -> -1659.39 | H51: =+G51-F51 -> 1659.39 | I51: =+I50+H51 -> 38165.97 | K51: =+N50 -> 0 | L51: =+'23'!F11 -> 0 | M51: =+'23'!F12 -> 0 | N51: =+K51+L51-M51 -> 0 | P51: =+O51-N51 -> 0 | Q51: =+Q50+P51 -> 0 | S51: =+V50 -> -1659.39 | T51: =+D51+L51 -> 0 | U51: =+E51+M51 -> 0 | V51: =+S51+T51-U51 -> -1659.39 | W51: =+G51+O51 -> 0 | X51: =+W51-V51 -> 1659.39 | Y51: =+Y50+X51 -> 38165.97
A52: =+Input!B33 -> Sunday | B52: =+Input!C33 -> 46166 | C52: =+F51 -> -1659.39 | D52: =+'24'!B11 -> 0 | E52: =+'24'!B12 -> 0 | F52: =+C52+D52-E52 -> -1659.39 | H52: =+G52-F52 -> 1659.39 | I52: =+I51+H52 -> 39825.36 | K52: =+N51 -> 0 | L52: =+'24'!F11 -> 0 | M52: =+'24'!F12 -> 0 | N52: =+K52+L52-M52 -> 0 | P52: =+O52-N52 -> 0 | Q52: =+Q51+P52 -> 0 | S52: =+V51 -> -1659.39 | T52: =+D52+L52 -> 0 | U52: =+E52+M52 -> 0 | V52: =+S52+T52-U52 -> -1659.39 | W52: =+G52+O52 -> 0 | X52: =+W52-V52 -> 1659.39 | Y52: =+Y51+X52 -> 39825.36
A53: =+Input!B34 -> Monday | B53: =+Input!C34 -> 46167 | C53: =+F52 -> -1659.39 | D53: =+'25'!B11 -> 0 | E53: =+'25'!B12 -> 0 | F53: =+C53+D53-E53 -> -1659.39 | H53: =+G53-F53 -> 1659.39 | I53: =+I52+H53 -> 41484.75 | K53: =+N52 -> 0 | L53: =+'25'!F11 -> 0 | M53: =+'25'!F12 -> 0 | N53: =+K53+L53-M53 -> 0 | P53: =+O53-N53 -> 0 | Q53: =+Q52+P53 -> 0 | S53: =+V52 -> -1659.39 | T53: =+D53+L53 -> 0 | U53: =+E53+M53 -> 0 | V53: =+S53+T53-U53 -> -1659.39 | W53: =+G53+O53 -> 0 | X53: =+W53-V53 -> 1659.39 | Y53: =+Y52+X53 -> 41484.75
A54: =+Input!B35 -> Tuesday | B54: =+Input!C35 -> 46168 | C54: =+F53 -> -1659.39 | D54: =+'26'!B11 -> 0 | E54: =+'26'!B12 -> 0 | F54: =+C54+D54-E54 -> -1659.39 | H54: =+G54-F54 -> 1659.39 | I54: =+I53+H54 -> 43144.14 | K54: =+N53 -> 0 | L54: =+'26'!F11 -> 0 | M54: =+'26'!F12 -> 0 | N54: =+K54+L54-M54 -> 0 | P54: =+O54-N54 -> 0 | Q54: =+Q53+P54 -> 0 | S54: =+V53 -> -1659.39 | T54: =+D54+L54 -> 0 | U54: =+E54+M54 -> 0 | V54: =+S54+T54-U54 -> -1659.39 | W54: =+G54+O54 -> 0 | X54: =+W54-V54 -> 1659.39 | Y54: =+Y53+X54 -> 43144.14
A55: =+Input!B36 -> Wednesday | B55: =+Input!C36 -> 46169 | C55: =+F54 -> -1659.39 | D55: =+'27'!B11 -> 0 | E55: =+'27'!B12 -> 0 | F55: =+C55+D55-E55 -> -1659.39 | H55: =+G55-F55 -> 1659.39 | I55: =+I54+H55 -> 44803.53 | K55: =+N54 -> 0 | L55: =+'27'!F11 -> 0 | M55: =+'27'!F12 -> 0 | N55: =+K55+L55-M55 -> 0 | P55: =+O55-N55 -> 0 | Q55: =+Q54+P55 -> 0 | S55: =+V54 -> -1659.39 | T55: =+D55+L55 -> 0 | U55: =+E55+M55 -> 0 | V55: =+S55+T55-U55 -> -1659.39 | W55: =+G55+O55 -> 0 | X55: =+W55-V55 -> 1659.39 | Y55: =+Y54+X55 -> 44803.53
A56: =+Input!B37 -> Thursday | B56: =+Input!C37 -> 46170 | C56: =+F55 -> -1659.39 | D56: =+'28'!B11 -> 0 | E56: =+'28'!B12 -> 0 | F56: =+C56+D56-E56 -> -1659.39 | H56: =+G56-F56 -> 1659.39 | I56: =+I55+H56 -> 46462.92 | K56: =+N55 -> 0 | L56: =+'28'!F11 -> 0 | M56: =+'28'!F12 -> 0 | N56: =+K56+L56-M56 -> 0 | P56: =+O56-N56 -> 0 | Q56: =+Q55+P56 -> 0 | S56: =+V55 -> -1659.39 | T56: =+D56+L56 -> 0 | U56: =+E56+M56 -> 0 | V56: =+S56+T56-U56 -> -1659.39 | W56: =+G56+O56 -> 0 | X56: =+W56-V56 -> 1659.39 | Y56: =+Y55+X56 -> 46462.92
A57: =+Input!B38 -> Friday | B57: =+Input!C38 -> 46171 | C57: =+F56 -> -1659.39 | D57: =+'29'!B11 -> 0 | E57: =+'29'!B12 -> 0 | F57: =+C57+D57-E57 -> -1659.39 | H57: =+G57-F57 -> 1659.39 | I57: =+I56+H57 -> 48122.31 | K57: =+N56 -> 0 | L57: =+'29'!F11 -> 0 | M57: =+'29'!F12 -> 0 | N57: =+K57+L57-M57 -> 0 | P57: =+O57-N57 -> 0 | Q57: =+Q56+P57 -> 0 | S57: =+V56 -> -1659.39 | T57: =+D57+L57 -> 0 | U57: =+E57+M57 -> 0 | V57: =+S57+T57-U57 -> -1659.39 | W57: =+G57+O57 -> 0 | X57: =+W57-V57 -> 1659.39 | Y57: =+Y56+X57 -> 48122.31
A58: =+Input!B39 -> Saturday | B58: =+Input!C39 -> 46172 | C58: =+F57 -> -1659.39 | D58: =+'30'!B11 -> 0 | E58: =+'30'!B12 -> 0 | F58: =+C58+D58-E58 -> -1659.39 | H58: =+G58-F58 -> 1659.39 | I58: =+I57+H58 -> 49781.7 | K58: =+N57 -> 0 | L58: =+'30'!F11 -> 0 | M58: =+'30'!F12 -> 0 | N58: =+K58+L58-M58 -> 0 | P58: =+O58-N58 -> 0 | Q58: =+Q57+P58 -> 0 | S58: =+V57 -> -1659.39 | T58: =+D58+L58 -> 0 | U58: =+E58+M58 -> 0 | V58: =+S58+T58-U58 -> -1659.39 | W58: =+G58+O58 -> 0 | X58: =+W58-V58 -> 1659.39 | Y58: =+Y57+X58 -> 49781.7
A59: =+Input!B40 -> Sunday | B59: =+Input!C40 -> 46173 | C59: =+F58 -> -1659.39 | D59: =+'31'!B11 -> 0 | E59: =+'31'!B12 -> 0 | F59: =+C59+D59-E59 -> -1659.39 | H59: =+G59-F59 -> 1659.39 | I59: =+I58+H59 -> 51441.09 | K59: =+N58 -> 0 | L59: =+'31'!F11 -> 0 | M59: =+'31'!F12 -> 0 | N59: =+K59+L59-M59 -> 0 | P59: =+O59-N59 -> 0 | Q59: =+Q58+P59 -> 0 | S59: =+V58 -> -1659.39 | T59: =+D59+L59 -> 0 | U59: =+E59+M59 -> 0 | V59: =+S59+T59-U59 -> -1659.39 | W59: =+G59+O59 -> 0 | X59: =+W59-V59 -> 1659.39 | Y59: =+Y58+X59 -> 51441.09
C60: =+C29 -> 0 | D60: =SUM(D29:D59) -> 0 | E60: =SUM(E29:E59) -> 1659.39 | F60: =+C60+D60-E60 -> -1659.39 | G60: =+B22 -> 0 | H60: =+G60-F60 -> 1659.39 | I60: =+G60-F60 -> 1659.39 | K60: =+K29 -> 0 | L60: =SUM(L29:L59) -> 0 | M60: =SUM(M29:M59) -> 0 | N60: =+K60+L60-M60 -> 0 | O60: =+F22 -> 0 | P60: =+O60-N60 -> 0 | Q60: =+O60-N60 -> 0 | S60: =+S29 -> 0 | T60: =SUM(T29:T59) -> 0 | U60: =SUM(U29:U59) -> 1659.39 | V60: =+S60+T60-U60 -> -1659.39 | W60: =+G60+O60 -> 0 | X60: =+W60-V60 -> 1659.39 | Y60: =+W60-V60 -> 1659.39
C63: TANK 2: ULP 95 | K63: TANK 4 : ULP 95 | S63: TOTAL: ULP 95
C64: O/Bal | D64: Purch | E64: Sold | F64: C/Bal | G64: ATG | H64: Variance | I64: Prog Vari | K64: O/Bal | L64: Purch | M64: Sold | N64: C/Bal | O64: ATG | P64: Variance | Q64: Prog Vari | S64: O/Bal | T64: Purch | U64: Sold | V64: C/Bal | W64: ATG | X64: Variance | Y64: Prog Vari
A65: =+Input!B10 -> Friday | B65: =+Input!C10 -> 46143 | C65: =+Input!B93 -> 0 | D65: =+'1'!C11 -> 0 | E65: =+'1'!C12 -> 1920.7 | F65: =+C65+D65-E65 -> -1920.7 | H65: =+G65-F65 -> 1920.7 | I65: =+H65 -> 1920.7 | K65: =+Input!J93 -> 0 | L65: =+'1'!E11 -> 0 | M65: =+'1'!E12 -> 0 | N65: =+K65+L65-M65 -> 0 | P65: =+O65-N65 -> 0 | Q65: =+P65 -> 0 | S65: =+C65+K65 -> 0 | T65: =+D65+L65 -> 0 | U65: =+E65+M65 -> 1920.7 | V65: =+S65+T65-U65 -> -1920.7 | W65: =+G65+O65 -> 0 | X65: =+W65-V65 -> 1920.7 | Y65: =+X65 -> 1920.7
A66: =+Input!B11 -> Saturday | B66: =+Input!C11 -> 46144 | C66: =+F65 -> -1920.7 | D66: =+'2'!C11 -> 0 | E66: =+'2'!C12 -> 0 | F66: =+C66+D66-E66 -> -1920.7 | H66: =+G66-F66 -> 1920.7 | I66: =+I65+H66 -> 3841.4 | K66: =+N65 -> 0 | L66: =+'2'!E11 -> 0 | M66: =+'2'!E12 -> 0 | N66: =+K66+L66-M66 -> 0 | P66: =+O66-N66 -> 0 | Q66: =+Q65+P66 -> 0 | S66: =+V65 -> -1920.7 | T66: =+D66+L66 -> 0 | U66: =+E66+M66 -> 0 | V66: =+S66+T66-U66 -> -1920.7 | W66: =+G66+O66 -> 0 | X66: =+W66-V66 -> 1920.7 | Y66: =+Y65+X66 -> 3841.4
A67: =+Input!B12 -> Sunday | B67: =+Input!C12 -> 46145 | C67: =+F66 -> -1920.7 | D67: =+'3'!C11 -> 0 | E67: =+'3'!C12 -> 0 | F67: =+C67+D67-E67 -> -1920.7 | H67: =+G67-F67 -> 1920.7 | I67: =+I66+H67 -> 5762.1 | K67: =+N66 -> 0 | L67: =+'3'!E11 -> 0 | M67: =+'3'!E12 -> 0 | N67: =+K67+L67-M67 -> 0 | P67: =+O67-N67 -> 0 | Q67: =+Q66+P67 -> 0 | S67: =+V66 -> -1920.7 | T67: =+D67+L67 -> 0 | U67: =+E67+M67 -> 0 | V67: =+S67+T67-U67 -> -1920.7 | W67: =+G67+O67 -> 0 | X67: =+W67-V67 -> 1920.7 | Y67: =+Y66+X67 -> 5762.1
A68: =+Input!B13 -> Monday | B68: =+Input!C13 -> 46146 | C68: =+F67 -> -1920.7 | D68: =+'4'!C11 -> 0 | E68: =+'4'!C12 -> 0 | F68: =+C68+D68-E68 -> -1920.7 | H68: =+G68-F68 -> 1920.7 | I68: =+I67+H68 -> 7682.8 | K68: =+N67 -> 0 | L68: =+'4'!E11 -> 0 | M68: =+'4'!E12 -> 0 | N68: =+K68+L68-M68 -> 0 | P68: =+O68-N68 -> 0 | Q68: =+Q67+P68 -> 0 | S68: =+V67 -> -1920.7 | T68: =+D68+L68 -> 0 | U68: =+E68+M68 -> 0 | V68: =+S68+T68-U68 -> -1920.7 | W68: =+G68+O68 -> 0 | X68: =+W68-V68 -> 1920.7 | Y68: =+Y67+X68 -> 7682.8
A69: =+Input!B14 -> Tuesday | B69: =+Input!C14 -> 46147 | C69: =+F68 -> -1920.7 | D69: =+'5'!C11 -> 0 | E69: =+'5'!C12 -> 0 | F69: =+C69+D69-E69 -> -1920.7 | H69: =+G69-F69 -> 1920.7 | I69: =+I68+H69 -> 9603.5 | K69: =+N68 -> 0 | L69: =+'5'!E11 -> 0 | M69: =+'5'!E12 -> 0 | N69: =+K69+L69-M69 -> 0 | P69: =+O69-N69 -> 0 | Q69: =+Q68+P69 -> 0 | S69: =+V68 -> -1920.7 | T69: =+D69+L69 -> 0 | U69: =+E69+M69 -> 0 | V69: =+S69+T69-U69 -> -1920.7 | W69: =+G69+O69 -> 0 | X69: =+W69-V69 -> 1920.7 | Y69: =+Y68+X69 -> 9603.5
A70: =+Input!B15 -> Wednesday | B70: =+Input!C15 -> 46148 | C70: =+F69 -> -1920.7 | D70: =+'6'!C11 -> 0 | E70: =+'6'!C12 -> 0 | F70: =+C70+D70-E70 -> -1920.7 | H70: =+G70-F70 -> 1920.7 | I70: =+I69+H70 -> 11524.2 | K70: =+N69 -> 0 | L70: =+'6'!E11 -> 0 | M70: =+'6'!E12 -> 0 | N70: =+K70+L70-M70 -> 0 | P70: =+O70-N70 -> 0 | Q70: =+Q69+P70 -> 0 | S70: =+V69 -> -1920.7 | T70: =+D70+L70 -> 0 | U70: =+E70+M70 -> 0 | V70: =+S70+T70-U70 -> -1920.7 | W70: =+G70+O70 -> 0 | X70: =+W70-V70 -> 1920.7 | Y70: =+Y69+X70 -> 11524.2
A71: =+Input!B16 -> Thursday | B71: =+Input!C16 -> 46149 | C71: =+F70 -> -1920.7 | D71: =+'7'!C11 -> 0 | E71: =+'7'!C12 -> 0 | F71: =+C71+D71-E71 -> -1920.7 | H71: =+G71-F71 -> 1920.7 | I71: =+I70+H71 -> 13444.9 | K71: =+N70 -> 0 | L71: =+'7'!E11 -> 0 | M71: =+'7'!E12 -> 0 | N71: =+K71+L71-M71 -> 0 | P71: =+O71-N71 -> 0 | Q71: =+Q70+P71 -> 0 | S71: =+V70 -> -1920.7 | T71: =+D71+L71 -> 0 | U71: =+E71+M71 -> 0 | V71: =+S71+T71-U71 -> -1920.7 | W71: =+G71+O71 -> 0 | X71: =+W71-V71 -> 1920.7 | Y71: =+Y70+X71 -> 13444.9
A72: =+Input!B17 -> Friday | B72: =+Input!C17 -> 46150 | C72: =+F71 -> -1920.7 | D72: =+'8'!C11 -> 0 | E72: =+'8'!C12 -> 0 | F72: =+C72+D72-E72 -> -1920.7 | H72: =+G72-F72 -> 1920.7 | I72: =+I71+H72 -> 15365.6 | K72: =+N71 -> 0 | L72: =+'8'!E11 -> 0 | M72: =+'8'!E12 -> 0 | N72: =+K72+L72-M72 -> 0 | P72: =+O72-N72 -> 0 | Q72: =+Q71+P72 -> 0 | S72: =+V71 -> -1920.7 | T72: =+D72+L72 -> 0 | U72: =+E72+M72 -> 0 | V72: =+S72+T72-U72 -> -1920.7 | W72: =+G72+O72 -> 0 | X72: =+W72-V72 -> 1920.7 | Y72: =+Y71+X72 -> 15365.6
A73: =+Input!B18 -> Saturday | B73: =+Input!C18 -> 46151 | C73: =+F72 -> -1920.7 | D73: =+'9'!C11 -> 0 | E73: =+'9'!C12 -> 0 | F73: =+C73+D73-E73 -> -1920.7 | H73: =+G73-F73 -> 1920.7 | I73: =+I72+H73 -> 17286.3 | K73: =+N72 -> 0 | L73: =+'9'!E11 -> 0 | M73: =+'9'!E12 -> 0 | N73: =+K73+L73-M73 -> 0 | P73: =+O73-N73 -> 0 | Q73: =+Q72+P73 -> 0 | S73: =+V72 -> -1920.7 | T73: =+D73+L73 -> 0 | U73: =+E73+M73 -> 0 | V73: =+S73+T73-U73 -> -1920.7 | W73: =+G73+O73 -> 0 | X73: =+W73-V73 -> 1920.7 | Y73: =+Y72+X73 -> 17286.3
A74: =+Input!B19 -> Sunday | B74: =+Input!C19 -> 46152 | C74: =+F73 -> -1920.7 | D74: =+'10'!C11 -> 0 | E74: =+'10'!C12 -> 0 | F74: =+C74+D74-E74 -> -1920.7 | H74: =+G74-F74 -> 1920.7 | I74: =+I73+H74 -> 19207 | K74: =+N73 -> 0 | L74: =+'10'!E11 -> 0 | M74: =+'10'!E12 -> 0 | N74: =+K74+L74-M74 -> 0 | P74: =+O74-N74 -> 0 | Q74: =+Q73+P74 -> 0 | S74: =+V73 -> -1920.7 | T74: =+D74+L74 -> 0 | U74: =+E74+M74 -> 0 | V74: =+S74+T74-U74 -> -1920.7 | W74: =+G74+O74 -> 0 | X74: =+W74-V74 -> 1920.7 | Y74: =+Y73+X74 -> 19207
A75: =+Input!B20 -> Monday | B75: =+Input!C20 -> 46153 | C75: =+F74 -> -1920.7 | D75: =+'11'!C11 -> 0 | E75: =+'11'!C12 -> 0 | F75: =+C75+D75-E75 -> -1920.7 | H75: =+G75-F75 -> 1920.7 | I75: =+I74+H75 -> 21127.7 | K75: =+N74 -> 0 | L75: =+'11'!E11 -> 0 | M75: =+'11'!E12 -> 0 | N75: =+K75+L75-M75 -> 0 | P75: =+O75-N75 -> 0 | Q75: =+Q74+P75 -> 0 | S75: =+V74 -> -1920.7 | T75: =+D75+L75 -> 0 | U75: =+E75+M75 -> 0 | V75: =+S75+T75-U75 -> -1920.7 | W75: =+G75+O75 -> 0 | X75: =+W75-V75 -> 1920.7 | Y75: =+Y74+X75 -> 21127.7
A76: =+Input!B21 -> Tuesday | B76: =+Input!C21 -> 46154 | C76: =+F75 -> -1920.7 | D76: =+'12'!C11 -> 0 | E76: =+'12'!C12 -> 0 | F76: =+C76+D76-E76 -> -1920.7 | H76: =+G76-F76 -> 1920.7 | I76: =+I75+H76 -> 23048.4 | K76: =+N75 -> 0 | L76: =+'12'!E11 -> 0 | M76: =+'12'!E12 -> 0 | N76: =+K76+L76-M76 -> 0 | P76: =+O76-N76 -> 0 | Q76: =+Q75+P76 -> 0 | S76: =+V75 -> -1920.7 | T76: =+D76+L76 -> 0 | U76: =+E76+M76 -> 0 | V76: =+S76+T76-U76 -> -1920.7 | W76: =+G76+O76 -> 0 | X76: =+W76-V76 -> 1920.7 | Y76: =+Y75+X76 -> 23048.4
A77: =+Input!B22 -> Wednesday | B77: =+Input!C22 -> 46155 | C77: =+F76 -> -1920.7 | D77: =+'13'!C11 -> 0 | E77: =+'13'!C12 -> 0 | F77: =+C77+D77-E77 -> -1920.7 | H77: =+G77-F77 -> 1920.7 | I77: =+I76+H77 -> 24969.1 | K77: =+N76 -> 0 | L77: =+'13'!E11 -> 0 | M77: =+'13'!E12 -> 0 | N77: =+K77+L77-M77 -> 0 | P77: =+O77-N77 -> 0 | Q77: =+Q76+P77 -> 0 | S77: =+V76 -> -1920.7 | T77: =+D77+L77 -> 0 | U77: =+E77+M77 -> 0 | V77: =+S77+T77-U77 -> -1920.7 | W77: =+G77+O77 -> 0 | X77: =+W77-V77 -> 1920.7 | Y77: =+Y76+X77 -> 24969.1
A78: =+Input!B23 -> Thursday | B78: =+Input!C23 -> 46156 | C78: =+F77 -> -1920.7 | D78: =+'14'!C11 -> 0 | E78: =+'14'!C12 -> 0 | F78: =+C78+D78-E78 -> -1920.7 | H78: =+G78-F78 -> 1920.7 | I78: =+I77+H78 -> 26889.8 | K78: =+N77 -> 0 | L78: =+'14'!E11 -> 0 | M78: =+'14'!E12 -> 0 | N78: =+K78+L78-M78 -> 0 | P78: =+O78-N78 -> 0 | Q78: =+Q77+P78 -> 0 | S78: =+V77 -> -1920.7 | T78: =+D78+L78 -> 0 | U78: =+E78+M78 -> 0 | V78: =+S78+T78-U78 -> -1920.7 | W78: =+G78+O78 -> 0 | X78: =+W78-V78 -> 1920.7 | Y78: =+Y77+X78 -> 26889.8
A79: =+Input!B24 -> Friday | B79: =+Input!C24 -> 46157 | C79: =+F78 -> -1920.7 | D79: =+'15'!C11 -> 0 | E79: =+'15'!C12 -> 0 | F79: =+C79+D79-E79 -> -1920.7 | H79: =+G79-F79 -> 1920.7 | I79: =+I78+H79 -> 28810.5 | K79: =+N78 -> 0 | L79: =+'15'!E11 -> 0 | M79: =+'15'!E12 -> 0 | N79: =+K79+L79-M79 -> 0 | P79: =+O79-N79 -> 0 | Q79: =+Q78+P79 -> 0 | S79: =+V78 -> -1920.7 | T79: =+D79+L79 -> 0 | U79: =+E79+M79 -> 0 | V79: =+S79+T79-U79 -> -1920.7 | W79: =+G79+O79 -> 0 | X79: =+W79-V79 -> 1920.7 | Y79: =+Y78+X79 -> 28810.5
A80: =+Input!B25 -> Saturday | B80: =+Input!C25 -> 46158 | C80: =+F79 -> -1920.7 | D80: =+'16'!C11 -> 0 | E80: =+'16'!C12 -> 0 | F80: =+C80+D80-E80 -> -1920.7 | H80: =+G80-F80 -> 1920.7 | I80: =+I79+H80 -> 30731.2 | K80: =+N79 -> 0 | L80: =+'16'!E11 -> 0 | M80: =+'16'!E12 -> 0 | N80: =+K80+L80-M80 -> 0 | P80: =+O80-N80 -> 0 | Q80: =+Q79+P80 -> 0 | S80: =+V79 -> -1920.7 | T80: =+D80+L80 -> 0 | U80: =+E80+M80 -> 0 | V80: =+S80+T80-U80 -> -1920.7 | W80: =+G80+O80 -> 0 | X80: =+W80-V80 -> 1920.7 | Y80: =+Y79+X80 -> 30731.2
A81: =+Input!B26 -> Sunday | B81: =+Input!C26 -> 46159 | C81: =+F80 -> -1920.7 | D81: =+'17'!C11 -> 0 | E81: =+'17'!C12 -> 0 | F81: =+C81+D81-E81 -> -1920.7 | H81: =+G81-F81 -> 1920.7 | I81: =+I80+H81 -> 32651.9 | K81: =+N80 -> 0 | L81: =+'17'!E11 -> 0 | M81: =+'17'!E12 -> 0 | N81: =+K81+L81-M81 -> 0 | P81: =+O81-N81 -> 0 | Q81: =+Q80+P81 -> 0 | S81: =+V80 -> -1920.7 | T81: =+D81+L81 -> 0 | U81: =+E81+M81 -> 0 | V81: =+S81+T81-U81 -> -1920.7 | W81: =+G81+O81 -> 0 | X81: =+W81-V81 -> 1920.7 | Y81: =+Y80+X81 -> 32651.9
A82: =+Input!B27 -> Monday | B82: =+Input!C27 -> 46160 | C82: =+F81 -> -1920.7 | D82: =+'18'!C11 -> 0 | E82: =+'18'!C12 -> 0 | F82: =+C82+D82-E82 -> -1920.7 | H82: =+G82-F82 -> 1920.7 | I82: =+I81+H82 -> 34572.6 | K82: =+N81 -> 0 | L82: =+'18'!E11 -> 0 | M82: =+'18'!E12 -> 0 | N82: =+K82+L82-M82 -> 0 | P82: =+O82-N82 -> 0 | Q82: =+Q81+P82 -> 0 | S82: =+V81 -> -1920.7 | T82: =+D82+L82 -> 0 | U82: =+E82+M82 -> 0 | V82: =+S82+T82-U82 -> -1920.7 | W82: =+G82+O82 -> 0 | X82: =+W82-V82 -> 1920.7 | Y82: =+Y81+X82 -> 34572.6
A83: =+Input!B28 -> Tuesday | B83: =+Input!C28 -> 46161 | C83: =+F82 -> -1920.7 | D83: =+'19'!C11 -> 0 | E83: =+'19'!C12 -> 0 | F83: =+C83+D83-E83 -> -1920.7 | H83: =+G83-F83 -> 1920.7 | I83: =+I82+H83 -> 36493.3 | K83: =+N82 -> 0 | L83: =+'19'!E11 -> 0 | M83: =+'19'!E12 -> 0 | N83: =+K83+L83-M83 -> 0 | P83: =+O83-N83 -> 0 | Q83: =+Q82+P83 -> 0 | S83: =+V82 -> -1920.7 | T83: =+D83+L83 -> 0 | U83: =+E83+M83 -> 0 | V83: =+S83+T83-U83 -> -1920.7 | W83: =+G83+O83 -> 0 | X83: =+W83-V83 -> 1920.7 | Y83: =+Y82+X83 -> 36493.3
A84: =+Input!B29 -> Wednesday | B84: =+Input!C29 -> 46162 | C84: =+F83 -> -1920.7 | D84: =+'20'!C11 -> 0 | E84: =+'20'!C12 -> 0 | F84: =+C84+D84-E84 -> -1920.7 | H84: =+G84-F84 -> 1920.7 | I84: =+I83+H84 -> 38414 | K84: =+N83 -> 0 | L84: =+'20'!E11 -> 0 | M84: =+'20'!E12 -> 0 | N84: =+K84+L84-M84 -> 0 | P84: =+O84-N84 -> 0 | Q84: =+Q83+P84 -> 0 | S84: =+V83 -> -1920.7 | T84: =+D84+L84 -> 0 | U84: =+E84+M84 -> 0 | V84: =+S84+T84-U84 -> -1920.7 | W84: =+G84+O84 -> 0 | X84: =+W84-V84 -> 1920.7 | Y84: =+Y83+X84 -> 38414
A85: =+Input!B30 -> Thursday | B85: =+Input!C30 -> 46163 | C85: =+F84 -> -1920.7 | D85: =+'21'!C11 -> 0 | E85: =+'21'!C12 -> 0 | F85: =+C85+D85-E85 -> -1920.7 | H85: =+G85-F85 -> 1920.7 | I85: =+I84+H85 -> 40334.7 | K85: =+N84 -> 0 | L85: =+'21'!E11 -> 0 | M85: =+'21'!E12 -> 0 | N85: =+K85+L85-M85 -> 0 | P85: =+O85-N85 -> 0 | Q85: =+Q84+P85 -> 0 | S85: =+V84 -> -1920.7 | T85: =+D85+L85 -> 0 | U85: =+E85+M85 -> 0 | V85: =+S85+T85-U85 -> -1920.7 | W85: =+G85+O85 -> 0 | X85: =+W85-V85 -> 1920.7 | Y85: =+Y84+X85 -> 40334.7
A86: =+Input!B31 -> Friday | B86: =+Input!C31 -> 46164 | C86: =+F85 -> -1920.7 | D86: =+'22'!C11 -> 0 | E86: =+'22'!C12 -> 0 | F86: =+C86+D86-E86 -> -1920.7 | H86: =+G86-F86 -> 1920.7 | I86: =+I85+H86 -> 42255.4 | K86: =+N85 -> 0 | L86: =+'22'!E11 -> 0 | M86: =+'22'!E12 -> 0 | N86: =+K86+L86-M86 -> 0 | P86: =+O86-N86 -> 0 | Q86: =+Q85+P86 -> 0 | S86: =+V85 -> -1920.7 | T86: =+D86+L86 -> 0 | U86: =+E86+M86 -> 0 | V86: =+S86+T86-U86 -> -1920.7 | W86: =+G86+O86 -> 0 | X86: =+W86-V86 -> 1920.7 | Y86: =+Y85+X86 -> 42255.4
A87: =+Input!B32 -> Saturday | B87: =+Input!C32 -> 46165 | C87: =+F86 -> -1920.7 | D87: =+'23'!C11 -> 0 | E87: =+'23'!C12 -> 0 | F87: =+C87+D87-E87 -> -1920.7 | H87: =+G87-F87 -> 1920.7 | I87: =+I86+H87 -> 44176.1 | K87: =+N86 -> 0 | L87: =+'23'!E11 -> 0 | M87: =+'23'!E12 -> 0 | N87: =+K87+L87-M87 -> 0 | P87: =+O87-N87 -> 0 | Q87: =+Q86+P87 -> 0 | S87: =+V86 -> -1920.7 | T87: =+D87+L87 -> 0 | U87: =+E87+M87 -> 0 | V87: =+S87+T87-U87 -> -1920.7 | W87: =+G87+O87 -> 0 | X87: =+W87-V87 -> 1920.7 | Y87: =+Y86+X87 -> 44176.1
A88: =+Input!B33 -> Sunday | B88: =+Input!C33 -> 46166 | C88: =+F87 -> -1920.7 | D88: =+'24'!C11 -> 0 | E88: =+'24'!C12 -> 0 | F88: =+C88+D88-E88 -> -1920.7 | H88: =+G88-F88 -> 1920.7 | I88: =+I87+H88 -> 46096.8 | K88: =+N87 -> 0 | L88: =+'24'!E11 -> 0 | M88: =+'24'!E12 -> 0 | N88: =+K88+L88-M88 -> 0 | P88: =+O88-N88 -> 0 | Q88: =+Q87+P88 -> 0 | S88: =+V87 -> -1920.7 | T88: =+D88+L88 -> 0 | U88: =+E88+M88 -> 0 | V88: =+S88+T88-U88 -> -1920.7 | W88: =+G88+O88 -> 0 | X88: =+W88-V88 -> 1920.7 | Y88: =+Y87+X88 -> 46096.8
A89: =+Input!B34 -> Monday | B89: =+Input!C34 -> 46167 | C89: =+F88 -> -1920.7 | D89: =+'25'!C11 -> 0 | E89: =+'25'!C12 -> 0 | F89: =+C89+D89-E89 -> -1920.7 | H89: =+G89-F89 -> 1920.7 | I89: =+I88+H89 -> 48017.5 | K89: =+N88 -> 0 | L89: =+'25'!E11 -> 0 | M89: =+'25'!E12 -> 0 | N89: =+K89+L89-M89 -> 0 | P89: =+O89-N89 -> 0 | Q89: =+Q88+P89 -> 0 | S89: =+V88 -> -1920.7 | T89: =+D89+L89 -> 0 | U89: =+E89+M89 -> 0 | V89: =+S89+T89-U89 -> -1920.7 | W89: =+G89+O89 -> 0 | X89: =+W89-V89 -> 1920.7 | Y89: =+Y88+X89 -> 48017.5
A90: =+Input!B35 -> Tuesday | B90: =+Input!C35 -> 46168 | C90: =+F89 -> -1920.7 | D90: =+'26'!C11 -> 0 | E90: =+'26'!C12 -> 0 | F90: =+C90+D90-E90 -> -1920.7 | H90: =+G90-F90 -> 1920.7 | I90: =+I89+H90 -> 49938.2 | K90: =+N89 -> 0 | L90: =+'26'!E11 -> 0 | M90: =+'26'!E12 -> 0 | N90: =+K90+L90-M90 -> 0 | P90: =+O90-N90 -> 0 | Q90: =+Q89+P90 -> 0 | S90: =+V89 -> -1920.7 | T90: =+D90+L90 -> 0 | U90: =+E90+M90 -> 0 | V90: =+S90+T90-U90 -> -1920.7 | W90: =+G90+O90 -> 0 | X90: =+W90-V90 -> 1920.7 | Y90: =+Y89+X90 -> 49938.2
A91: =+Input!B36 -> Wednesday | B91: =+Input!C36 -> 46169 | C91: =+F90 -> -1920.7 | D91: =+'27'!C11 -> 0 | E91: =+'27'!C12 -> 0 | F91: =+C91+D91-E91 -> -1920.7 | H91: =+G91-F91 -> 1920.7 | I91: =+I90+H91 -> 51858.9 | K91: =+N90 -> 0 | L91: =+'27'!E11 -> 0 | M91: =+'27'!E12 -> 0 | N91: =+K91+L91-M91 -> 0 | P91: =+O91-N91 -> 0 | Q91: =+Q90+P91 -> 0 | S91: =+V90 -> -1920.7 | T91: =+D91+L91 -> 0 | U91: =+E91+M91 -> 0 | V91: =+S91+T91-U91 -> -1920.7 | W91: =+G91+O91 -> 0 | X91: =+W91-V91 -> 1920.7 | Y91: =+Y90+X91 -> 51858.9
A92: =+Input!B37 -> Thursday | B92: =+Input!C37 -> 46170 | C92: =+F91 -> -1920.7 | D92: =+'28'!C11 -> 0 | E92: =+'28'!C12 -> 0 | F92: =+C92+D92-E92 -> -1920.7 | H92: =+G92-F92 -> 1920.7 | I92: =+I91+H92 -> 53779.6 | K92: =+N91 -> 0 | L92: =+'28'!E11 -> 0 | M92: =+'28'!E12 -> 0 | N92: =+K92+L92-M92 -> 0 | P92: =+O92-N92 -> 0 | Q92: =+Q91+P92 -> 0 | S92: =+V91 -> -1920.7 | T92: =+D92+L92 -> 0 | U92: =+E92+M92 -> 0 | V92: =+S92+T92-U92 -> -1920.7 | W92: =+G92+O92 -> 0 | X92: =+W92-V92 -> 1920.7 | Y92: =+Y91+X92 -> 53779.6
A93: =+Input!B38 -> Friday | B93: =+Input!C38 -> 46171 | C93: =+F92 -> -1920.7 | D93: =+'29'!C11 -> 0 | E93: =+'29'!C12 -> 0 | F93: =+C93+D93-E93 -> -1920.7 | H93: =+G93-F93 -> 1920.7 | I93: =+I92+H93 -> 55700.3 | K93: =+N92 -> 0 | L93: =+'29'!E11 -> 0 | M93: =+'29'!E12 -> 0 | N93: =+K93+L93-M93 -> 0 | P93: =+O93-N93 -> 0 | Q93: =+Q92+P93 -> 0 | S93: =+V92 -> -1920.7 | T93: =+D93+L93 -> 0 | U93: =+E93+M93 -> 0 | V93: =+S93+T93-U93 -> -1920.7 | W93: =+G93+O93 -> 0 | X93: =+W93-V93 -> 1920.7 | Y93: =+Y92+X93 -> 55700.3
A94: =+Input!B39 -> Saturday | B94: =+Input!C39 -> 46172 | C94: =+F93 -> -1920.7 | D94: =+'30'!C11 -> 0 | E94: =+'30'!C12 -> 0 | F94: =+C94+D94-E94 -> -1920.7 | H94: =+G94-F94 -> 1920.7 | I94: =+I93+H94 -> 57621 | K94: =+N93 -> 0 | L94: =+'30'!E11 -> 0 | M94: =+'30'!E12 -> 0 | N94: =+K94+L94-M94 -> 0 | P94: =+O94-N94 -> 0 | Q94: =+Q93+P94 -> 0 | S94: =+V93 -> -1920.7 | T94: =+D94+L94 -> 0 | U94: =+E94+M94 -> 0 | V94: =+S94+T94-U94 -> -1920.7 | W94: =+G94+O94 -> 0 | X94: =+W94-V94 -> 1920.7 | Y94: =+Y93+X94 -> 57621
A95: =+Input!B40 -> Sunday | B95: =+Input!C40 -> 46173 | C95: =+F94 -> -1920.7 | D95: =+'31'!C11 -> 0 | E95: =+'31'!C12 -> 0 | F95: =+C95+D95-E95 -> -1920.7 | H95: =+G95-F95 -> 1920.7 | I95: =+I94+H95 -> 59541.7 | K95: =+N94 -> 0 | L95: =+'31'!E11 -> 0 | M95: =+'31'!E12 -> 0 | N95: =+K95+L95-M95 -> 0 | P95: =+O95-N95 -> 0 | Q95: =+Q94+P95 -> 0 | S95: =+V94 -> -1920.7 | T95: =+D95+L95 -> 0 | U95: =+E95+M95 -> 0 | V95: =+S95+T95-U95 -> -1920.7 | W95: =+G95+O95 -> 0 | X95: =+W95-V95 -> 1920.7 | Y95: =+Y94+X95 -> 59541.7
C96: =+C65 -> 0 | D96: =SUM(D65:D95) -> 0 | E96: =SUM(E65:E95) -> 1920.7 | F96: =+C96+D96-E96 -> -1920.7 | G96: =+C22 -> 0 | H96: =+G96-F96 -> 1920.7 | I96: =+G96-F96 -> 1920.7 | K96: =+K65 -> 0 | L96: =SUM(L65:L95) -> 0 | M96: =SUM(M65:M95) -> 0 | N96: =+K96+L96-M96 -> 0 | O96: =+E22 -> 0 | P96: =+O96-N96 -> 0 | Q96: =+O96-N96 -> 0 | S96: =+S65 -> 0 | T96: =SUM(T65:T95) -> 0 | U96: =SUM(U65:U95) -> 1920.7 | V96: =+S96+T96-U96 -> -1920.7 | W96: =+G96+O96 -> 0 | X96: =+W96-V96 -> 1920.7 | Y96: =+W96-V96 -> 1920.7
C99: TANK 3: ULP 93
C100: O/Bal | D100: Purch | E100: Sold | F100: C/Bal | G100: ATG | H100: Variance | I100: Prog Vari
A101: =+Input!B10 -> Friday | B101: =+Input!C10 -> 46143 | C101: =+Input!R49 -> 0 | D101: =+'1'!D11 -> 0 | E101: =+'1'!D12 -> 40.06 | F101: =+C101+D101-E101 -> -40.06 | H101: =+G101-F101 -> 40.06 | I101: =+H101 -> 40.06
A102: =+Input!B11 -> Saturday | B102: =+Input!C11 -> 46144 | C102: =+F101 -> -40.06 | D102: =+'2'!D11 -> 0 | E102: =+'2'!D12 -> 0 | F102: =+C102+D102-E102 -> -40.06 | H102: =+G102-F102 -> 40.06 | I102: =+I101+H102 -> 80.12
A103: =+Input!B12 -> Sunday | B103: =+Input!C12 -> 46145 | C103: =+F102 -> -40.06 | D103: =+'3'!D11 -> 0 | E103: =+'3'!D12 -> 0 | F103: =+C103+D103-E103 -> -40.06 | H103: =+G103-F103 -> 40.06 | I103: =+I102+H103 -> 120.18
A104: =+Input!B13 -> Monday | B104: =+Input!C13 -> 46146 | C104: =+F103 -> -40.06 | D104: =+'4'!D11 -> 0 | E104: =+'4'!D12 -> 0 | F104: =+C104+D104-E104 -> -40.06 | H104: =+G104-F104 -> 40.06 | I104: =+I103+H104 -> 160.24
A105: =+Input!B14 -> Tuesday | B105: =+Input!C14 -> 46147 | C105: =+F104 -> -40.06 | D105: =+'5'!D11 -> 0 | E105: =+'5'!D12 -> 0 | F105: =+C105+D105-E105 -> -40.06 | H105: =+G105-F105 -> 40.06 | I105: =+I104+H105 -> 200.3
A106: =+Input!B15 -> Wednesday | B106: =+Input!C15 -> 46148 | C106: =+F105 -> -40.06 | D106: =+'6'!D11 -> 0 | E106: =+'6'!D12 -> 0 | F106: =+C106+D106-E106 -> -40.06 | H106: =+G106-F106 -> 40.06 | I106: =+I105+H106 -> 240.36
A107: =+Input!B16 -> Thursday | B107: =+Input!C16 -> 46149 | C107: =+F106 -> -40.06 | D107: =+'7'!D11 -> 0 | E107: =+'7'!D12 -> 0 | F107: =+C107+D107-E107 -> -40.06 | H107: =+G107-F107 -> 40.06 | I107: =+I106+H107 -> 280.42
A108: =+Input!B17 -> Friday | B108: =+Input!C17 -> 46150 | C108: =+F107 -> -40.06 | D108: =+'8'!D11 -> 0 | E108: =+'8'!D12 -> 0 | F108: =+C108+D108-E108 -> -40.06 | H108: =+G108-F108 -> 40.06 | I108: =+I107+H108 -> 320.48
A109: =+Input!B18 -> Saturday | B109: =+Input!C18 -> 46151 | C109: =+F108 -> -40.06 | D109: =+'9'!D11 -> 0 | E109: =+'9'!D12 -> 0 | F109: =+C109+D109-E109 -> -40.06 | H109: =+G109-F109 -> 40.06 | I109: =+I108+H109 -> 360.54
A110: =+Input!B19 -> Sunday | B110: =+Input!C19 -> 46152 | C110: =+F109 -> -40.06 | D110: =+'10'!D11 -> 0 | E110: =+'10'!D12 -> 0 | F110: =+C110+D110-E110 -> -40.06 | H110: =+G110-F110 -> 40.06 | I110: =+I109+H110 -> 400.6
A111: =+Input!B20 -> Monday | B111: =+Input!C20 -> 46153 | C111: =+F110 -> -40.06 | D111: =+'11'!D11 -> 0 | E111: =+'11'!D12 -> 0 | F111: =+C111+D111-E111 -> -40.06 | H111: =+G111-F111 -> 40.06 | I111: =+I110+H111 -> 440.66
...

Sheet Daily Template
A1: =+Input!B2 -> ENGEN JETPARK
A3: Daily Analysis
B5: Day | C5: Date
A6: UNDER REVIEW | B6: 6 | C6: 46148
I8: SUMMARY
B9: Tank: 1 | C9: Tank: 2 | D9: Tank: 3 | E9: Tank: 4 | F9: Tank: 5 | G9: TOTAL | I9: Diesel | J9: ULP: 95 | K9: ULP: 93 | L9: TOTAL
A10: DATA: LITRES | B10: ULP95 | C10: Diesel | D10: ULP93 | E10: Diesel | F10: ULP95
A11: - Litres Purchased | G11: =SUM(B11:F11) -> 0
A12: - Litres Sold | G12: =SUM(B12:F12) -> 0 | I12: =+B12+F12 -> 0 | J12: =+C12+E12 -> 0 | K12: =+D12 -> 0 | L12: =SUM(I12:K12) -> 0
A13: - Closing Dip | G13: =SUM(B13:F13) -> 0 | I13: =+I12/L12 -> #DIV/0! | J13: =+J12/L12 -> #DIV/0! | K13: =+K12/L12 -> #DIV/0! | L13: =SUM(I13:K13) -> #DIV/0!
A14: - Selling Price | B14: 23.36 | C14: 29.2 | D14: 23.25 | E14: 29.2 | F14: 23.36
A15: - Cost Price | B15: 21.1987 | C15: 26.7753 | D15: 21.0887 | E15: 26.7753 | F15: =+B15 -> 21.1987
A16: - Gross Profit | B16: =+B14-B15 -> 2.1613 | C16: =+C14-C15 -> 2.4247 | D16: =+D14-D15 -> 2.1613 | E16: =+E14-E15 -> 2.4247 | F16: =+F14-F15 -> 2.1613
A17: - Gross Profit % | B17: =+B16/B14 -> 0.092521404 | C17: =+C16/C14 -> 0.083037671 | D17: =+D16/D14 -> 0.09295914 | E17: =+E16/E14 -> 0.083037671 | F17: =+F16/F14 -> 0.092521404
A20: DAY END REPORT
A21: - Total Sales
A22: - Less: Returns (Show as a negative)
A23: - Total Net Sales | B23: =SUM(B21:B22) -> 0
A26: SALES BY DIVISION | B26: =SUM(B27:B33) -> 0 | C26: =SUM(C27:C33) -> #DIV/0!
A27: - Bakery | C27: =+B27/$B$26 -> #DIV/0!
A28: - Bakpre | C28: =+B28/$B$26 -> #DIV/0!
A29: - Barist | C29: =+B29/$B$26 -> #DIV/0!
A30: - Fuel | C30: =+B30/$B$26 -> #DIV/0!
A31: - Lubes | C31: =+B31/$B$26 -> #DIV/0!
A32: - VV | C32: =+B32/$B$26 -> #DIV/0!
A33: - Quickshop | B33: =+B23-B27-B28-B29-B30-B31-B32 -> 0 | C33: =+B33/$B$26 -> #DIV/0!
A35: CONTROL TOTAL | B35: =+B23-B26 -> 0 | C35: - Must be zero
A38: CASHIERS RECONCILIATION
A40: Cashier Name | B40: =+Input!B44 -> Mandla | C40: =+Input!C44 -> Caroline | D40: =+Input!D44 -> Siyabonga | E40: =+Input!E44 -> Thumelo | F40: =+Input!F44 -> Cashier 5 | G40: =+Input!G44 -> Cashier 6 | H40: TOTAL | I40: CT
A41: Shift Number
A43: DAY END REPORT
A44: - Total Sales | H44: =SUM(B44:G44) -> 0
A45: - Less: Returns (Show as a negative) | H45: =SUM(B45:G45) -> 0
A46: - Total Net Sales | B46: =SUM(B44:B45) -> 0 | C46: =SUM(C44:C45) -> 0 | D46: =SUM(D44:D45) -> 0 | E46: =SUM(E44:E45) -> 0 | F46: =SUM(F44:F45) -> 0 | G46: =SUM(G44:G45) -> 0 | H46: =SUM(H44:H45) -> 0 | I46: =+B23-H46 -> 0 | J46: Must be Zero
A48: SUMMARY
A49: - Net Sales | B49: =+B46 -> 0 | C49: =+C46 -> 0 | D49: =+D46 -> 0 | E49: =+E46 -> 0 | F49: =+F46 -> 0 | G49: =+G46 -> 0 | H49: =SUM(B49:G49) -> 0
A50: - Banking | B50: =+B56+B63+B68 -> 0 | C50: =+C56+C63+C68 -> 0 | D50: =+D56+D63+D68 -> 0 | E50: =+E56+E63+E68 -> 0 | F50: =+F56+F63+F68 -> 0 | G50: =+G56+G63+G68 -> 0 | H50: =SUM(B50:G50) -> 0
A51: - Adjustments | B51: =+B73 -> 0 | C51: =+C73 -> 0 | D51: =+D73 -> 0 | E51: =+E73 -> 0 | F51: =+F73 -> 0 | G51: =+G73 -> 0 | H51: =SUM(B51:G51) -> 0
A52: - Petty Cash | B52: =-B82 -> 0 | C52: =-C82 -> 0 | D52: =-D82 -> 0 | E52: =-E82 -> 0 | F52: =-F82 -> 0 | G52: =-G82 -> 0 | H52: =SUM(B52:G52) -> 0
A53: - (OVER) / UNDER | B53: =+B49-B50-B51+B52 -> 0 | C53: =+C49-C50-C51+C52 -> 0 | D53: =+D49-D50-D51+D52 -> 0 | E53: =+E49-E50-E51+E52 -> 0 | F53: =+F49-F50-F51+F52 -> 0 | G53: =+G49-G50-G51+G52 -> 0 | H53: =+H49-H50-H51+H52 -> 0
A56: CASH | B56: =+B59+B60 -> 0 | C56: =+C59+C60 -> 0 | D56: =+D59+D60 -> 0 | E56: =+E59+E60 -> 0 | F56: =+F59+F60 -> 0 | G56: =+G59+G60 -> 0 | H56: =+H59+H60 -> 0
A57: - Cash: Coins | H57: =SUM(B57:G57) -> 0
A58: - Cash: Till | H58: =SUM(B58:G58) -> 0
A59: - Sub Total | B59: =SUM(B57:B58) -> 0 | C59: =SUM(C57:C58) -> 0 | D59: =SUM(D57:D58) -> 0 | E59: =SUM(E57:E58) -> 0 | F59: =SUM(F57:F58) -> 0 | G59: =SUM(G57:G58) -> 0 | H59: =SUM(H57:H58) -> 0
A60: - Cash drops | H60: =SUM(B60:G60) -> 0
A63: SPEDPOINTS | H63: =SUM(B63:G63) -> 0
A64: - Fleet Cards | H64: =SUM(B64:G64) -> 0
A65: - Net Speedpoints | B65: =+B63-B64 -> 0 | C65: =+C63-C64 -> 0 | D65: =+D63-D64 -> 0 | E65: =+E63-E64 -> 0 | F65: =+F63-F64 -> 0 | G65: =+G63-G64 -> 0 | H65: =+H63-H64 -> 0
A68: DEBTORS | B68: =SUM(B69:B70) -> 0 | C68: =SUM(C69:C70) -> 0 | D68: =SUM(D69:D70) -> 0 | E68: =SUM(E69:E70) -> 0 | F68: =SUM(F69:F70) -> 0 | G68: =SUM(G69:G70) -> 0 | H68: =SUM(H69:H70) -> 0
A69: - On Account | H69: =SUM(B69:G69) -> 0
A70: - Account Receipts (Show as a negative) | H70: =SUM(B70:G70) -> 0
A73: ADJUSTMENTS | B73: =SUM(B74:B79) -> 0 | C73: =SUM(C74:C79) -> 0 | D73: =SUM(D74:D79) -> 0 | E73: =SUM(E74:E79) -> 0 | F73: =SUM(F74:F79) -> 0 | G73: =SUM(G74:G79) -> 0 | H73: =SUM(H74:H79) -> 0 | J73: Comment
A74: - EFT | H74: =SUM(B74:G74) -> 0
A75: - Contamination | H75: =SUM(B75:G75) -> 0
A76: - Drive Off | H76: =SUM(B76:G76) -> 0
A77: - Loyalty | H77: =SUM(B77:G77) -> 0
A78: - Other | H78: =SUM(B78:G78) -> 0
A79: - To Settle | H79: =SUM(B79:G79) -> 0
A82: PETTY CASH | B82: =SUM(B83:B98) -> 0 | C82: =SUM(C83:C98) -> 0 | D82: =SUM(D83:D98) -> 0 | E82: =SUM(E83:E98) -> 0 | F82: =SUM(F83:F98) -> 0 | G82: =SUM(G83:G98) -> 0 | H82: =SUM(H83:H98) -> 0
A83: - Cleaning | H83: =SUM(B83:G83) -> 0
A84: - Creditors: Existing | B84: =+B101 -> 0 | C84: =+C101 -> 0 | D84: =+D101 -> 0 | E84: =+E101 -> 0 | F84: =+F101 -> 0 | G84: =+G101 -> 0 | H84: =SUM(B84:G84) -> 0
A85: - Creditors: New | B85: =+B135 -> 0 | C85: =+C135 -> 0 | D85: =+D135 -> 0 | E85: =+E135 -> 0 | F85: =+F135 -> 0 | G85: =+G135 -> 0 | H85: =SUM(B85:G85) -> 0
A86: - Forecourt: R & M | H86: =SUM(B86:G86) -> 0
A87: - Other: Non-Vatable | H87: =SUM(B87:G87) -> 0
A88: - Other: Non-Vatable | H88: =SUM(B88:G88) -> 0
A89: - Other: Non-Vatable | H89: =SUM(B89:G89) -> 0
A90: - Other: Vatable | H90: =SUM(B90:G90) -> 0
A91: - Other: Vatable | H91: =SUM(B91:G91) -> 0
A92: - Other: Vatable | H92: =SUM(B92:G92) -> 0
A93: - Printing & Stationery | H93: =SUM(B93:G93) -> 0
A94: - Retail: R & M | H94: =SUM(B94:G94) -> 0
A95: - Salaries | H95: =SUM(B95:G95) -> 0
A96: - Staff Transport | H96: =SUM(B96:G96) -> 0
A97: - Staff Welfare | H97: =SUM(B97:G97) -> 0
A98: - Wages | H98: =SUM(B98:G98) -> 0
A101: CREDITORS: EXISTING | B101: =SUM(B102:B132) -> 0 | C101: =SUM(C102:C132) -> 0 | D101: =SUM(D102:D132) -> 0 | E101: =SUM(E102:E132) -> 0 | F101: =SUM(F102:F132) -> 0 | G101: =SUM(G102:G132) -> 0 | H101: =SUM(H102:H132) -> 0
A102: =+Input!A55 -> - Aksia Sales | H102: =SUM(B102:G102) -> 0
A103: =+Input!A56 -> - Albany | H103: =SUM(B103:G103) -> 0
A104: =+Input!A57 -> - Atlantic Ice | H104: =SUM(B104:G104) -> 0
A105: =+Input!A58 -> - Bake It Easy | H105: =SUM(B105:G105) -> 0
A106: =+Input!A59 -> - Bamco Tabacco | H106: =SUM(B106:G106) -> 0
A107: =+Input!A60 -> - Blue Ribbon | H107: =SUM(B107:G107) -> 0
A108: =+Input!A61 -> - Catercorp | H108: =SUM(B108:G108) -> 0
A109: =+Input!A62 -> - Checkers | H109: =SUM(B109:G109) -> 0
A110: =+Input!A63 -> - Clover | H110: =SUM(B110:G110) -> 0
A111: =+Input!A64 -> - Cool Runnings | H111: =SUM(B111:G111) -> 0
A112: =+Input!A65 -> - Deep Frozen | H112: =SUM(B112:G112) -> 0
A113: =+Input!A66 -> - Digistics | H113: =SUM(B113:G113) -> 0
... A132: =+Input!A85 -> - W Convenience | H132: =SUM(B132:G132) -> 0
A135: CREDITORS: NEW (Update Input) | B135: =SUM(B136:B145) -> 0 | C135: =SUM(C136:C145) -> 0 | D135: =SUM(D136:D145) -> 0 | E135: =SUM(E136:E145) -> 0 | F135: =SUM(F136:F145) -> 0 | G135: =SUM(G136:G145) -> 0 | H135: =SUM(H136:H145) -> 0
A136: =+Input!A88 -> - Other 1 | H136: =SUM(B136:G136) -> 0
A137: =+Input!A89 -> - Other 2 | H137: =SUM(B137:G137) -> 0
A138: =+Input!A90 -> - Other 3 | H138: =SUM(B138:G138) -> 0
A139: =+Input!A91 -> - Other 4 | H139: =SUM(B139:G139) -> 0
A140: =+Input!A92 -> - Other 5 | H140: =SUM(B140:G140) -> 0
A141: =+Input!A93 -> - Other 6 | H141: =SUM(B141:G141) -> 0
A142: =+Input!A94 -> - Other 7 | H142: =SUM(B142:G142) -> 0
A143: =+Input!A95 -> - Other 8 | H143: =SUM(B143:G143) -> 0
A144: =+Input!A96 -> - Other 9 | H144: =SUM(B144:G144) -> 0
A145: =+Input!A97 -> - Other 10 | H145: =SUM(B145:G145) -> 0

Sheet 1
A1: =+Input!B2 -> ENGEN JETPARK
A3: Daily Analysis
B5: Day | C5: Date
A6: UNDER REVIEW | B6: =+Input!B10 -> Friday | C6: =+Input!C10 -> 46143
I8: SUMMARY
B9: Tank: 1 | C9: Tank: 2 | D9: Tank: 3 | E9: Tank: 4 | F9: Tank: 5 | G9: TOTAL | I9: Diesel | J9: ULP: 95 | K9: ULP: 93 | L9: TOTAL
A10: DATA: LITRES | B10: ULP95 | C10: Diesel | D10: ULP93 | E10: Diesel | F10: ULP95
A11: - Litres Purchased | B11: 0 | C11: 0 | D11: 0 | E11: 0 | F11: 0 | G11: =SUM(B11:F11) -> 0
A12: - Litres Sold | B12: 1659.39 | C12: 1920.7 | D12: 40.06 | G12: =SUM(B12:F12) -> 3620.15 | I12: =+B12+F12 -> 1659.39 | J12: =+C12+E12 -> 1920.7 | K12: =+D12 -> 40.06 | L12: =SUM(I12:K12) -> 3620.15
A13: - Closing Dip | B13: 10411 | C13: 4101 | D13: 2361 | E13: 4146 | F13: 10341 | G13: =SUM(B13:F13) -> 31360 | I13: =+I12/L12 -> 0.45837603 | J13: =+J12/L12 -> 0.53055813 | K13: =+K12/L12 -> 0.01106584 | L13: =SUM(I13:K13) -> 1
A14: - Selling Price | B14: 23.36 | C14: 29.2 | D14: 23.25 | E14: 29.2 | F14: 23.36
A15: - Cost Price | B15: 21.1987 | C15: 26.7753 | D15: 21.0887 | E15: 26.7753 | F15: =+B15 -> 21.1987
A16: - Gross Profit | B16: =+B14-B15 -> 2.1613 | C16: =+C14-C15 -> 2.4247 | D16: =+D14-D15 -> 2.1613 | E16: =+E14-E15 -> 2.4247 | F16: =+F14-F15 -> 2.1613
A17: - Gross Profit % | B17: =+B16/B14 -> 0.092521404 | C17: =+C16/C14 -> 0.083037671 | D17: =+D16/D14 -> 0.09295914 | E17: =+E16/E14 -> 0.083037671 | F17: =+F16/F14 -> 0.092521404
A20: DAY END REPORT
A21: - Total Sales
A22: - Less: Returns (Show as a negative)
A23: - Total Net Sales | B23: =SUM(B21:B22) -> 0
A26: SALES BY DIVISION | B26: =SUM(B27:B33) -> 0 | C26: =SUM(C27:C33) -> #DIV/0!
A27: - Bakery | C27: =+B27/$B$26 -> #DIV/0!
A28: - Bakpre | C28: =+B28/$B$26 -> #DIV/0!
A29: - Barist | C29: =+B29/$B$26 -> #DIV/0!
A30: - Fuel | C30: =+B30/$B$26 -> #DIV/0!
A31: - Lubes | C31: =+B31/$B$26 -> #DIV/0!
A32: - VV | C32: =+B32/$B$26 -> #DIV/0!
A33: - Quickshop | B33: =+B23-B27-B28-B29-B30-B31-B32 -> 0 | C33: =+B33/$B$26 -> #DIV/0!
A35: CONTROL TOTAL | B35: =+B23-B26 -> 0 | C35: - Must be zero
A38: CASHIERS RECONCILIATION
A40: Cashier Name | B40: =+Input!B44 -> Mandla | C40: =+Input!C44 -> Caroline | D40: =+Input!D44 -> Siyabonga | E40: =+Input!E44 -> Thumelo | F40: =+Input!F44 -> Cashier 5 | G40: =+Input!G44 -> Cashier 6 | H40: TOTAL | I40: CT
A41: Shift Number
A43: DAY END REPORT
A44: - Total Sales | B44: 32878 | H44: =SUM(B44:G44) -> 32878
A45: - Less: Returns (Show as a negative) | H45: =SUM(B45:G45) -> 0
A46: - Total Net Sales | B46: =SUM(B44:B45) -> 32878 | C46: =SUM(C44:C45) -> 0 | D46: =SUM(D44:D45) -> 0 | E46: =SUM(E44:E45) -> 0 | F46: =SUM(F44:F45) -> 0 | G46: =SUM(G44:G45) -> 0 | H46: =SUM(H44:H45) -> 32878 | I46: =+B23-H46 -> -32878 | J46: Must be Zero
A48: SUMMARY
A49: - Net Sales | B49: =+B46 -> 32878 | C49: =+C46 -> 0 | D49: =+D46 -> 0 | E49: =+E46 -> 0 | F49: =+F46 -> 0 | G49: =+G46 -> 0 | H49: =SUM(B49:G49) -> 32878
A50: - Banking | B50: 0 | C50: =+C56+C63+C68 -> 1000 | D50: =+D56+D63+D68 -> 1000 | E50: =+E56+E63+E68 -> 1000 | F50: =+F56+F63+F68 -> 1000 | G50: =+G56+G63+G68 -> 1000 | H50: =SUM(B50:G50) -> 5000
A51: - Adjustments | B51: =+B73 -> 0 | C51: =+C73 -> 0 | D51: =+D73 -> 0 | E51: =+E73 -> 0 | F51: =+F73 -> 0 | G51: =+G73 -> 0 | H51: =SUM(B51:G51) -> 0
A52: - Petty Cash | B52: 328.04 | C52: =-C82 -> 0 | D52: =-D82 -> 0 | E52: =-E82 -> 0 | F52: =-F82 -> 0 | G52: =-G82 -> 0 | H52: =SUM(B52:G52) -> 328.04
A53: - (OVER) / UNDER | B53: =+B49-B50-B51+B52 -> 33206.04 | C53: =+C49-C50-C51+C52 -> -1000 | D53: =+D49-D50-D51+D52 -> -1000 | E53: =+E49-E50-E51+E52 -> -1000 | F53: =+F49-F50-F51+F52 -> -1000 | G53: =+G49-G50-G51+G52 -> -1000 | H53: =+H49-H50-H51+H52 -> 28206.04
A56: CASH | B56: =+B59+B60 -> 11.5 | C56: =+C59+C60 -> 0 | D56: =+D59+D60 -> 0 | E56: =+E59+E60 -> 0 | F56: =+F59+F60 -> 0 | G56: =+G59+G60 -> 0 | H56: =+H59+H60 -> 11.5
A57: - Cash: Coins | B57: 11.5 | H57: =SUM(B57:G57) -> 11.5
A58: - Cash: Till | H58: =SUM(B58:G58) -> 0
A59: - Sub Total | B59: =SUM(B57:B58) -> 11.5 | C59: =SUM(C57:C58) -> 0 | D59: =SUM(D57:D58) -> 0 | E59: =SUM(E57:E58) -> 0 | F59: =SUM(F57:F58) -> 0 | G59: =SUM(G57:G58) -> 0 | H59: =SUM(H57:H58) -> 11.5
A60: - Cash drops | H60: =SUM(B60:G60) -> 0
A63: SPEDPOINTS | B63: 14855.45 | C63: 1000 | D63: 1000 | E63: 1000 | F63: 1000 | G63: 1000 | H63: =SUM(B63:G63) -> 19855.45
A64: - Fleet Cards | B64: 60154.4 | H64: =SUM(B64:G64) -> 60154.4
A65: - Net Speedpoints | B65: =+B63-B64 -> -45298.95 | C65: =+C63-C64 -> 1000 | D65: =+D63-D64 -> 1000 | E65: =+E63-E64 -> 1000 | F65: =+F63-F64 -> 1000 | G65: =+G63-G64 -> 1000 | H65: =+H63-H64 -> -40298.95
A68: DEBTORS | B68: =SUM(B69:B70) -> 0 | C68: =SUM(C69:C70) -> 0 | D68: =SUM(D69:D70) -> 0 | E68: =SUM(E69:E70) -> 0 | F68: =SUM(F69:F70) -> 0 | G68: =SUM(G69:G70) -> 0 | H68: =SUM(H69:H70) -> 0
A69: - On Account | H69: =SUM(B69:G69) -> 0
A70: - Account Receipts (Show as a negative) | H70: =SUM(B70:G70) -> 0
A73: ADJUSTMENTS | B73: =SUM(B74:B79) -> 0 | C73: =SUM(C74:C79) -> 0 | D73: =SUM(D74:D79) -> 0 | E73: =SUM(E74:E79) -> 0 | F73: =SUM(F74:F79) -> 0 | G73: =SUM(G74:G79) -> 0 | H73: =SUM(H74:H79) -> 0 | J73: Comment
A74: - EFT | H74: =SUM(B74:G74) -> 0
A75: - Contamination | H75: =SUM(B75:G75) -> 0
A76: - Drive Off | H76: =SUM(B76:G76) -> 0
A77: - Loyalty | H77: =SUM(B77:G77) -> 0
A78: - Other | H78: =SUM(B78:G78) -> 0
A79: - To Settle | H79: =SUM(B79:G79) -> 0
A82: PETTY CASH | B82: =SUM(B83:B98) -> 0 | C82: =SUM(C83:C98) -> 0 | D82: =SUM(D83:D98) -> 0 | E82: =SUM(E83:E98) -> 0 | F82: =SUM(F83:F98) -> 0 | G82: =SUM(G83:G98) -> 0 | H82: =SUM(H83:H98) -> 0
A83: - Cleaning | H83: =SUM(B83:G83) -> 0
A84: - Creditors: Existing | B84: =+B101 -> 0 | C84: =+C101 -> 0 | D84: =+D101 -> 0 | E84: =+E101 -> 0 | F84: =+F101 -> 0 | G84: =+G101 -> 0 | H84: =SUM(B84:G84) -> 0
A85: - Creditors: New | B85: =+B135 -> 0 | C85: =+C135 -> 0 | D85: =+D135 -> 0 | E85: =+E135 -> 0 | F85: =+F135 -> 0 | G85: =+G135 -> 0 | H85: =SUM(B85:G85) -> 0
A86: - Forecourt: R & M | H86: =SUM(B86:G86) -> 0
A87: - Other: Non-Vatable | H87: =SUM(B87:G87) -> 0
A88: - Other: Non-Vatable | H88: =SUM(B88:G88) -> 0
A89: - Other: Non-Vatable | H89: =SUM(B89:G89) -> 0
A90: - Other: Vatable | H90: =SUM(B90:G90) -> 0
A91: - Other: Vatable | H91: =SUM(B91:G91) -> 0
A92: - Other: Vatable | H92: =SUM(B92:G92) -> 0
A93: - Printing & Stationery | H93: =SUM(B93:G93) -> 0
A94: - Retail: R & M | H94: =SUM(B94:G94) -> 0
A95: - Salaries | H95: =SUM(B95:G95) -> 0
A96: - Staff Transport | H96: =SUM(B96:G96) -> 0
A97: - Staff Welfare | H97: =SUM(B97:G97) -> 0
A98: - Wages | H98: =SUM(B98:G98) -> 0
A101: CREDITORS: EXISTING | B101: =SUM(B102:B132) -> 0 | C101: =SUM(C102:C132) -> 0 | D101: =SUM(D102:D132) -> 0 | E101: =SUM(E102:E132) -> 0 | F101: =SUM(F102:F132) -> 0 | G101: =SUM(G102:G132) -> 0 | H101: =SUM(H102:H132) -> 0
A102: =+Input!A55 -> - Aksia Sales | H102: =SUM(B102:G102) -> 0
A103: =+Input!A56 -> - Albany | H103: =SUM(B103:G103) -> 0
A104: =+Input!A57 -> - Atlantic Ice | H104: =SUM(B104:G104) -> 0
A105: =+Input!A58 -> - Bake It Easy | H105: =SUM(B105:G105) -> 0
A106: =+Input!A59 -> - Bamco Tabacco | H106: =SUM(B106:G106) -> 0
A107: =+Input!A60 -> - Blue Ribbon | H107: =SUM(B107:G107) -> 0
A108: =+Input!A61 -> - Catercorp | H108: =SUM(B108:G108) -> 0
A109: =+Input!A62 -> - Checkers | H109: =SUM(B109:G109) -> 0
A110: =+Input!A63 -> - Clover | H110: =SUM(B110:G110) -> 0
A111: =+Input!A64 -> - Cool Runnings | H111: =SUM(B111:G111) -> 0
A112: =+Input!A65 -> - Deep Frozen | H112: =SUM(B112:G112) -> 0
A113: =+Input!A66 -> - Digistics | H113: =SUM(B113:G113) -> 0
... A132: =+Input!A85 -> - W Convenience | H132: =SUM(B132:G132) -> 0
A135: CREDITORS: NEW (Update Input) | B135: =SUM(B136:B145) -> 0 | C135: =SUM(C136:C145) -> 0 | D135: =SUM(D136:D145) -> 0 | E135: =SUM(E136:E145) -> 0 | F135: =SUM(F136:F145) -> 0 | G135: =SUM(G136:G145) -> 0 | H135: =SUM(H136:H145) -> 0
A136: =+Input!A88 -> - Other 1 | H136: =SUM(B136:G136) -> 0
A137: =+Input!A89 -> - Other 2 | H137: =SUM(B137:G137) -> 0
A138: =+Input!A90 -> - Other 3 | H138: =SUM(B138:G138) -> 0
A139: =+Input!A91 -> - Other 4 | H139: =SUM(B139:G139) -> 0
A140: =+Input!A92 -> - Other 5 | H140: =SUM(B140:G140) -> 0
A141: =+Input!A93 -> - Other 6 | H141: =SUM(B141:G141) -> 0
A142: =+Input!A94 -> - Other 7 | H142: =SUM(B142:G142) -> 0
A143: =+Input!A95 -> - Other 8 | H143: =SUM(B143:G143) -> 0
A144: =+Input!A96 -> - Other 9 | H144: =SUM(B144:G144) -> 0
A145: =+Input!A97 -> - Other 10 | H145: =SUM(B145:G145) -> 0

Sheet 2
A1: =+Input!B2 -> ENGEN JETPARK
A3: Daily Analysis
B5: Day | C5: Date
A6: UNDER REVIEW | B6: =+Input!B11 -> Saturday | C6: =+Input!C11 -> 46144
I8: SUMMARY
B9: Tank: 1 | C9: Tank: 2 | D9: Tank: 3 | E9: Tank: 4 | F9: Tank: 5 | G9: TOTAL | I9: Diesel | J9: ULP: 95 | K9: ULP: 93 | L9: TOTAL
A10: DATA: LITRES | B10: Diesel | C10: ULP95 | D10: ULP93 | E10: ULP95 | F10: Diesel
A11: - Litres Purchased | G11: =SUM(B11:F11) -> 0
A12: - Litres Sold | G12: =SUM(B12:F12) -> 0 | I12: =+B12+F12 -> 0 | J12: =+C12+E12 -> 0 | K12: =+D12 -> 0 | L12: =SUM(I12:K12) -> 0
A13: - Closing Dip | G13: =SUM(B13:F13) -> 0 | I13: =+I12/L12 -> #DIV/0! | J13: =+J12/L12 -> #DIV/0! | K13: =+K12/L12 -> #DIV/0! | L13: =SUM(I13:K13) -> #DIV/0!
A14: - Selling Price | E14: =+C14 -> 0 | F14: =+B14 -> 0
A15: - Cost Price | E15: =+C15 -> 0 | F15: =+B15 -> 0
A16: - Gross Profit | B16: =+B14-B15 -> 0 | C16: =+C14-C15 -> 0 | D16: =+D14-D15 -> 0 | E16: =+E14-E15 -> 0 | F16: =+F14-F15 -> 0
A17: - Gross Profit % | B17: =+B16/B14 -> #DIV/0! | C17: =+C16/C14 -> #DIV/0! | D17: =+D16/D14 -> #DIV/0! | E17: =+E16/E14 -> #DIV/0! | F17: =+F16/F14 -> #DIV/0!
A20: DAY END REPORT
A21: - Total Sales
A22: - Less: Returns (Show as a negative)
A23: - Total Net Sales | B23: =SUM(B21:B22) -> 0
A26: SALES BY DIVISION | B26: =SUM(B27:B33) -> 0 | C26: =SUM(C27:C33) -> #DIV/0!
A27: - Bakery | C27: =+B27/$B$26 -> #DIV/0!
A28: - Bakpre | C28: =+B28/$B$26 -> #DIV/0!
A29: - Barist | C29: =+B29/$B$26 -> #DIV/0!
A30: - Fuel | C30: =+B30/$B$26 -> #DIV/0!
A31: - Lubes | C31: =+B31/$B$26 -> #DIV/0!
A32: - VV | C32: =+B32/$B$26 -> #DIV/0!
A33: - Quickshop | B33: =+B23-B27-B28-B29-B30-B31-B32 -> 0 | C33: =+B33/$B$26 -> #DIV/0!
A35: CONTROL TOTAL | B35: =+B23-B26 -> 0 | C35: - Must be zero
A38: CASHIERS RECONCILIATION
A40: Cashier Name | B40: =+Input!B44 -> Mandla | C40: =+Input!C44 -> Caroline | D40: =+Input!D44 -> Siyabonga | E40: =+Input!E44 -> Thumelo | F40: =+Input!F44 -> Cashier 5 | G40: =+Input!G44 -> Cashier 6 | H40: TOTAL | I40: CT
A41: Shift Number
A43: DAY END REPORT
A44: - Total Sales | H44: =SUM(B44:G44) -> 0
A45: - Less: Returns (Show as a negative) | H45: =SUM(B45:G45) -> 0
A46: - Total Net Sales | B46: =SUM(B44:B45) -> 0 | C46: =SUM(C44:C45) -> 0 | D46: =SUM(D44:D45) -> 0 | E46: =SUM(E44:E45) -> 0 | F46: =SUM(F44:F45) -> 0 | G46: =SUM(G44:G45) -> 0 | H46: =SUM(H44:H45) -> 0 | I46: =+B23-H46 -> 0 | J46: Must be Zero
A48: SUMMARY
A49: - Net Sales | B49: =+B46 -> 0 | C49: =+C46 -> 0 | D49: =+D46 -> 0 | E49: =+E46 -> 0 | F49: =+F46 -> 0 | G49: =+G46 -> 0 | H49: =SUM(B49:G49) -> 0
A50: - Banking | B50: =+B56+B63+B68 -> 0 | C50: =+C56+C63+C68 -> 0 | D50: =+D56+D63+D68 -> 0 | E50: =+E56+E63+E68 -> 0 | F50: =+F56+F63+F68 -> 0 | G50: =+G56+G63+G68 -> 0 | H50: =SUM(B50:G50) -> 0
A51: - Adjustments | B51: =+B73 -> 0 | C51: =+C73 -> 0 | D51: =+D73 -> 0 | E51: =+E73 -> 0 | F51: =+F73 -> 0 | G51: =+G73 -> 0 | H51: =SUM(B51:G51) -> 0
A52: - Petty Cash | B52: =-B82 -> 0 | C52: =-C82 -> 0 | D52: =-D82 -> 0 | E52: =-E82 -> 0 | F52: =-F82 -> 0 | G52: =-G82 -> 0 | H52: =SUM(B52:G52) -> 0
A53: - (OVER) / UNDER | B53: =+B49-B50-B51+B52 -> 0 | C53: =+C49-C50-C51+C52 -> 0 | D53: =+D49-D50-D51+D52 -> 0 | E53: =+E49-E50-E51+E52 -> 0 | F53: =+F49-F50-F51+F52 -> 0 | G53: =+G49-G50-G51+G52 -> 0 | H53: =+H49-H50-H51+H52 -> 0
A56: CASH | B56: =+B59+B60 -> 0 | C56: =+C59+C60 -> 0 | D56: =+D59+D60 -> 0 | E56: =+E59+E60 -> 0 | F56: =+F59+F60 -> 0 | G56: =+G59+G60 -> 0 | H56: =+H59+H60 -> 0
A57: - Cash: Coins | H57: =SUM(B57:G57) -> 0
A58: - Cash: Till | H58: =SUM(B58:G58) -> 0
A59: - Sub Total | B59: =SUM(B57:B58) -> 0 | C59: =SUM(C57:C58) -> 0 | D59: =SUM(D57:D58) -> 0 | E59: =SUM(E57:E58) -> 0 | F59: =SUM(F57:F58) -> 0 | G59: =SUM(G57:G58) -> 0 | H59: =SUM(H57:H58) -> 0
A60: - Cash drops | H60: =SUM(B60:G60) -> 0
A63: SPEDPOINTS | H63: =SUM(B63:G63) -> 0
A64: - Fleet Cards | H64: =SUM(B64:G64) -> 0
A65: - Net Speedpoints | B65: =+B63-B64 -> 0 | C65: =+C63-C64 -> 0 | D65: =+D63-D64 -> 0 | E65: =+E63-E64 -> 0 | F65: =+F63-F64 -> 0 | G65: =+G63-G64 -> 0 | H65: =+H63-H64 -> 0
A68: DEBTORS | B68: =SUM(B69:B70) -> 0 | C68: =SUM(C69:C70) -> 0 | D68: =SUM(D69:D70) -> 0 | E68: =SUM(E69:E70) -> 0 | F68: =SUM(F69:F70) -> 0 | G68: =SUM(G69:G70) -> 0 | H68: =SUM(H69:H70) -> 0
A69: - On Account | H69: =SUM(B69:G69) -> 0
A70: - Account Receipts (Show as a negative) | H70: =SUM(B70:G70) -> 0
A73: ADJUSTMENTS | B73: =SUM(B74:B79) -> 0 | C73: =SUM(C74:C79) -> 0 | D73: =SUM(D74:D79) -> 0 | E73: =SUM(E74:E79) -> 0 | F73: =SUM(F74:F79) -> 0 | G73: =SUM(G74:G79) -> 0 | H73: =SUM(H74:H79) -> 0 | J73: Comment
A74: - EFT | H74: =SUM(B74:G74) -> 0
A75: - Contamination | H75: =SUM(B75:G75) -> 0
A76: - Drive Off | H76: =SUM(B76:G76) -> 0
A77: - Loyalty | H77: =SUM(B77:G77) -> 0
A78: - Other | H78: =SUM(B78:G78) -> 0
A79: - To Settle | H79: =SUM(B79:G79) -> 0
A82: PETTY CASH | B82: =SUM(B83:B98) -> 0 | C82: =SUM(C83:C98) -> 0 | D82: =SUM(D83:D98) -> 0 | E82: =SUM(E83:E98) -> 0 | F82: =SUM(F83:F98) -> 0 | G82: =SUM(G83:G98) -> 0 | H82: =SUM(H83:H98) -> 0
A83: - Cleaning | H83: =SUM(B83:G83) -> 0
A84: - Creditors: Existing | B84: =+B101 -> 0 | C84: =+C101 -> 0 | D84: =+D101 -> 0 | E84: =+E101 -> 0 | F84: =+F101 -> 0 | G84: =+G101 -> 0 | H84: =SUM(B84:G84) -> 0
A85: - Creditors: New | B85: =+B135 -> 0 | C85: =+C135 -> 0 | D85: =+D135 -> 0 | E85: =+E135 -> 0 | F85: =+F135 -> 0 | G85: =+G135 -> 0 | H85: =SUM(B85:G85) -> 0
A86: - Forecourt: R & M | H86: =SUM(B86:G86) -> 0
A87: - Other: Non-Vatable | H87: =SUM(B87:G87) -> 0
A88: - Other: Non-Vatable | H88: =SUM(B88:G88) -> 0
A89: - Other: Non-Vatable | H89: =SUM(B89:G89) -> 0
A90: - Other: Vatable | H90: =SUM(B90:G90) -> 0
A91: - Other: Vatable | H91: =SUM(B91:G91) -> 0
A92: - Other: Vatable | H92: =SUM(B92:G92) -> 0
A93: - Printing & Stationery | H93: =SUM(B93:G93) -> 0
A94: - Retail: R & M | H94: =SUM(B94:G94) -> 0
A95: - Salaries | H95: =SUM(B95:G95) -> 0
A96: - Staff Transport | H96: =SUM(B96:G96) -> 0
A97: - Staff Welfare | H97: =SUM(B97:G97) -> 0
A98: - Wages | H98: =SUM(B98:G98) -> 0
A101: CREDITORS: EXISTING | B101: =SUM(B102:B132) -> 0 | C101: =SUM(C102:C132) -> 0 | D101: =SUM(D102:D132) -> 0 | E101: =SUM(E102:E132) -> 0 | F101: =SUM(F102:F132) -> 0 | G101: =SUM(G102:G132) -> 0 | H101: =SUM(H102:H132) -> 0
A102: =+Input!A55 -> - Aksia Sales | H102: =SUM(B102:G102) -> 0
A103: =+Input!A56 -> - Albany | H103: =SUM(B103:G103) -> 0
A104: =+Input!A57 -> - Atlantic Ice | H104: =SUM(B104:G104) -> 0
A105: =+Input!A58 -> - Bake It Easy | H105: =SUM(B105:G105) -> 0
A106: =+Input!A59 -> - Bamco Tabacco | H106: =SUM(B106:G106) -> 0
A107: =+Input!A60 -> - Blue Ribbon | H107: =SUM(B107:G107) -> 0
A108: =+Input!A61 -> - Catercorp | H108: =SUM(B108:G108) -> 0
A109: =+Input!A62 -> - Checkers | H109: =SUM(B109:G109) -> 0
A110: =+Input!A63 -> - Clover | H110: =SUM(B110:G110) -> 0
A111: =+Input!A64 -> - Cool Runnings | H111: =SUM(B111:G111) -> 0
A112: =+Input!A65 -> - Deep Frozen | H112: =SUM(B112:G112) -> 0
A113: =+Input!A66 -> - Digistics | H113: =SUM(B113:G113) -> 0
... A132: =+Input!A85 -> - W Convenience | H132: =SUM(B132:G132) -> 0
A135: CREDITORS: NEW (Update Input) | B135: =SUM(B136:B145) -> 0 | C135: =SUM(C136:C145) -> 0 | D135: =SUM(D136:D145) -> 0 | E135: =SUM(E136:E145) -> 0 | F135: =SUM(F136:F145) -> 0 | G135: =SUM(G136:G145) -> 0 | H135: =SUM(H136:H145) -> 0
A136: =+Input!A88 -> - Other 1 | H136: =SUM(B136:G136) -> 0
A137: =+Input!A89 -> - Other 2 | H137: =SUM(B137:G137) -> 0
A138: =+Input!A90 -> - Other 3 | H138: =SUM(B138:G138) -> 0
A139: =+Input!A91 -> - Other 4 | H139: =SUM(B139:G139) -> 0
A140: =+Input!A92 -> - Other 5 | H140: =SUM(B140:G140) -> 0
A141: =+Input!A93 -> - Other 6 | H141: =SUM(B141:G141) -> 0
A142: =+Input!A94 -> - Other 7 | H142: =SUM(B142:G142) -> 0
A143: =+Input!A95 -> - Other 8 | H143: =SUM(B143:G143) -> 0
A144: =+Input!A96 -> - Other 9 | H144: =SUM(B144:G144) -> 0
A145: =+Input!A97 -> - Other 10 | H145: =SUM(B145:G145) -> 0

Sheet 3
A1: =+Input!B2 -> ENGEN JETPARK
A3: Daily Analysis
B5: Day | C5: Date
A6: UNDER REVIEW | B6: =+Input!B12 -> Sunday | C6: =+Input!C12 -> 46145
I8: SUMMARY
B9: Tank: 1 | C9: Tank: 2 | D9: Tank: 3 | E9: Tank: 4 | F9: Tank: 5 | G9: TOTAL | I9: Diesel | J9: ULP: 95 | K9: ULP: 93 | L9: TOTAL
A10: DATA: LITRES | B10: Diesel | C10: ULP95 | D10: ULP93 | E10: ULP95 | F10: Diesel
A11: - Litres Purchased | G11: =SUM(B11:F11) -> 0
A12: - Litres Sold | G12: =SUM(B12:F12) -> 0 | I12: =+B12+F12 -> 0 | J12: =+C12+E12 -> 0 | K12: =+D12 -> 0 | L12: =SUM(I12:K12) -> 0
A13: - Closing Dip | G13: =SUM(B13:F13) -> 0 | I13: =+I12/L12 -> #DIV/0! | J13: =+J12/L12 -> #DIV/0! | K13: =+K12/L12 -> #DIV/0! | L13: =SUM(I13:K13) -> #DIV/0!
A14: - Selling Price | E14: =+C14 -> 0 | F14: =+B14 -> 0
A15: - Cost Price | E15: =+C15 -> 0 | F15: =+B15 -> 0
A16: - Gross Profit | B16: =+B14-B15 -> 0 | C16: =+C14-C15 -> 0 | D16: =+D14-D15 -> 0 | E16: =+E14-E15 -> 0 | F16: =+F14-F15 -> 0
A17: - Gross Profit % | B17: =+B16/B14 -> #DIV/0! | C17: =+C16/C14 -> #DIV/0! | D17: =+D16/D14 -> #DIV/0! | E17: =+E16/E14 -> #DIV/0! | F17: =+F16/F14 -> #DIV/0!
A20: DAY END REPORT
A21: - Total Sales
A22: - Less: Returns (Show as a negative)
A23: - Total Net Sales | B23: =SUM(B21:B22) -> 0
A26: SALES BY DIVISION | B26: =SUM(B27:B33) -> 0 | C26: =SUM(C27:C33) -> #DIV/0!
A27: - Bakery | C27: =+B27/$B$26 -> #DIV/0!
A28: - Bakpre | C28: =+B28/$B$26 -> #DIV/0!
A29: - Barist | C29: =+B29/$B$26 -> #DIV/0!
A30: - Fuel | C30: =+B30/$B$26 -> #DIV/0!
A31: - Lubes | C31: =+B31/$B$26 -> #DIV/0!
A32: - VV | C32: =+B32/$B$26 -> #DIV/0!
A33: - Quickshop | B33: =+B23-B27-B28-B29-B30-B31-B32 -> 0 | C33: =+B33/$B$26 -> #DIV/0!
A35: CONTROL TOTAL | B35: =+B23-B26 -> 0 | C35: - Must be zero
A38: CASHIERS RECONCILIATION
A40: Cashier Name | B40: =+Input!B44 -> Mandla | C40: =+Input!C44 -> Caroline | D40: =+Input!D44 -> Siyabonga | E40: =+Input!E44 -> Thumelo | F40: =+Input!F44 -> Cashier 5 | G40: =+Input!G44 -> Cashier 6 | H40: TOTAL | I40: CT
A41: Shift Number
A43: DAY END REPORT
A44: - Total Sales | H44: =SUM(B44:G44) -> 0
A45: - Less: Returns (Show as a negative) | H45: =SUM(B45:G45) -> 0
A46: - Total Net Sales | B46: =SUM(B44:B45) -> 0 | C46: =SUM(C44:C45) -> 0 | D46: =SUM(D44:D45) -> 0 | E46: =SUM(E44:E45) -> 0 | F46: =SUM(F44:F45) -> 0 | G46: =SUM(G44:G45) -> 0 | H46: =SUM(H44:H45) -> 0 | I46: =+B23-H46 -> 0 | J46: Must be Zero
A48: SUMMARY
A49: - Net Sales | B49: =+B46 -> 0 | C49: =+C46 -> 0 | D49: =+D46 -> 0 | E49: =+E46 -> 0 | F49: =+F46 -> 0 | G49: =+G46 -> 0 | H49: =SUM(B49:G49) -> 0
A50: - Banking | B50: =+B56+B63+B68 -> 0 | C50: =+C56+C63+C68 -> 0 | D50: =+D56+D63+D68 -> 0 | E50: =+E56+E63+E68 -> 0 | F50: =+F56+F63+F68 -> 0 | G50: =+G56+G63+G68 -> 0 | H50: =SUM(B50:G50) -> 0
A51: - Adjustments | B51: =+B73 -> 0 | C51: =+C73 -> 0 | D51: =+D73 -> 0 | E51: =+E73 -> 0 | F51: =+F73 -> 0 | G51: =+G73 -> 0 | H51: =SUM(B51:G51) -> 0
A52: - Petty Cash | B52: =-B82 -> 0 | C52: =-C82 -> 0 | D52: =-D82 -> 0 | E52: =-E82 -> 0 | F52: =-F82 -> 0 | G52: =-G82 -> 0 | H52: =SUM(B52:G52) -> 0
A53: - (OVER) / UNDER | B53: =+B49-B50-B51+B52 -> 0 | C53: =+C49-C50-C51+C52 -> 0 | D53: =+D49-D50-D51+D52 -> 0 | E53: =+E49-E50-E51+E52 -> 0 | F53: =+F49-F50-F51+F52 -> 0 | G53: =+G49-G50-G51+G52 -> 0 | H53: =+H49-H50-H51+H52 -> 0
A56: CASH | B56: =+B59+B60 -> 0 | C56: =+C59+C60 -> 0 | D56: =+D59+D60 -> 0 | E56: =+E59+E60 -> 0 | F56: =+F59+F60 -> 0 | G56: =+G59+G60 -> 0 | H56: =+H59+H60 -> 0
A57: - Cash: Coins | H57: =SUM(B57:G57) -> 0
A58: - Cash: Till | H58: =SUM(B58:G58) -> 0
A59: - Sub Total | B59: =SUM(B57:B58) -> 0 | C59: =SUM(C57:C58) -> 0 | D59: =SUM(D57:D58) -> 0 | E59: =SUM(E57:E58) -> 0 | F59: =SUM(F57:F58) -> 0 | G59: =SUM(G57:G58) -> 0 | H59: =SUM(H57:H58) -> 0
A60: - Cash drops | H60: =SUM(B60:G60) -> 0
A63: SPEDPOINTS | H63: =SUM(B63:G63) -> 0
A64: - Fleet Cards | H64: =SUM(B64:G64) -> 0
A65: - Net Speedpoints | B65: =+B63-B64 -> 0 | C65: =+C63-C64 -> 0 | D65: =+D63-D64 -> 0 | E65: =+E63-E64 -> 0 | F65: =+F63-F64 -> 0 | G65: =+G63-G64 -> 0 | H65: =+H63-H64 -> 0
A68: DEBTORS | B68: =SUM(B69:B70) -> 0 | C68: =SUM(C69:C70) -> 0 | D68: =SUM(D69:D70) -> 0 | E68: =SUM(E69:E70) -> 0 | F68: =SUM(F69:F70) -> 0 | G68: =SUM(G69:G70) -> 0 | H68: =SUM(H69:H70) -> 0
A69: - On Account | H69: =SUM(B69:G69) -> 0
A70: - Account Receipts (Show as a negative) | H70: =SUM(B70:G70) -> 0
A73: ADJUSTMENTS | B73: =SUM(B74:B79) -> 0 | C73: =SUM(C74:C79) -> 0 | D73: =SUM(D74:D79) -> 0 | E73: =SUM(E74:E79) -> 0 | F73: =SUM(F74:F79) -> 0 | G73: =SUM(G74:G79) -> 0 | H73: =SUM(H74:H79) -> 0 | J73: Comment
A74: - EFT | H74: =SUM(B74:G74) -> 0
A75: - Contamination | H75: =SUM(B75:G75) -> 0
A76: - Drive Off | H76: =SUM(B76:G76) -> 0
A77: - Loyalty | H77: =SUM(B77:G77) -> 0
A78: - Other | H78: =SUM(B78:G78) -> 0
A79: - To Settle | H79: =SUM(B79:G79) -> 0
A82: PETTY CASH | B82: =SUM(B83:B98) -> 0 | C82: =SUM(C83:C98) -> 0 | D82: =SUM(D83:D98) -> 0 | E82: =SUM(E83:E98) -> 0 | F82: =SUM(F83:F98) -> 0 | G82: =SUM(G83:G98) -> 0 | H82: =SUM(H83:H98) -> 0
A83: - Cleaning | H83: =SUM(B83:G83) -> 0
A84: - Creditors: Existing | B84: =+B101 -> 0 | C84: =+C101 -> 0 | D84: =+D101 -> 0 | E84: =+E101 -> 0 | F84: =+F101 -> 0 | G84: =+G101 -> 0 | H84: =SUM(B84:G84) -> 0
A85: - Creditors: New | B85: =+B135 -> 0 | C85: =+C135 -> 0 | D85: =+D135 -> 0 | E85: =+E135 -> 0 | F85: =+F135 -> 0 | G85: =+G135 -> 0 | H85: =SUM(B85:G85) -> 0
A86: - Forecourt: R & M | H86: =SUM(B86:G86) -> 0
A87: - Other: Non-Vatable | H87: =SUM(B87:G87) -> 0
A88: - Other: Non-Vatable | H88: =SUM(B88:G88) -> 0
A89: - Other: Non-Vatable | H89: =SUM(B89:G89) -> 0
A90: - Other: Vatable | H90: =SUM(B90:G90) -> 0
A91: - Other: Vatable | H91: =SUM(B91:G91) -> 0
A92: - Other: Vatable | H92: =SUM(B92:G92) -> 0
A93: - Printing & Stationery | H93: =SUM(B93:G93) -> 0
A94: - Retail: R & M | H94: =SUM(B94:G94) -> 0
A95: - Salaries | H95: =SUM(B95:G95) -> 0
A96: - Staff Transport | H96: =SUM(B96:G96) -> 0
A97: - Staff Welfare | H97: =SUM(B97:G97) -> 0
A98: - Wages | H98: =SUM(B98:G98) -> 0
A101: CREDITORS: EXISTING | B101: =SUM(B102:B132) -> 0 | C101: =SUM(C102:C132) -> 0 | D101: =SUM(D102:D132) -> 0 | E101: =SUM(E102:E132) -> 0 | F101: =SUM(F102:F132) -> 0 | G101: =SUM(G102:G132) -> 0 | H101: =SUM(H102:H132) -> 0
A102: =+Input!A55 -> - Aksia Sales | H102: =SUM(B102:G102) -> 0
A103: =+Input!A56 -> - Albany | H103: =SUM(B103:G103) -> 0
A104: =+Input!A57 -> - Atlantic Ice | H104: =SUM(B104:G104) -> 0
A105: =+Input!A58 -> - Bake It Easy | H105: =SUM(B105:G105) -> 0
A106: =+Input!A59 -> - Bamco Tabacco | H106: =SUM(B106:G106) -> 0
A107: =+Input!A60 -> - Blue Ribbon | H107: =SUM(B107:G107) -> 0
A108: =+Input!A61 -> - Catercorp | H108: =SUM(B108:G108) -> 0
A109: =+Input!A62 -> - Checkers | H109: =SUM(B109:G109) -> 0
A110: =+Input!A63 -> - Clover | H110: =SUM(B110:G110) -> 0
A111: =+Input!A64 -> - Cool Runnings | H111: =SUM(B111:G111) -> 0
A112: =+Input!A65 -> - Deep Frozen | H112: =SUM(B112:G112) -> 0
A113: =+Input!A66 -> - Digistics | H113: =SUM(B113:G113) -> 0
... A132: =+Input!A85 -> - W Convenience | H132: =SUM(B132:G132) -> 0
A135: CREDITORS: NEW (Update Input) | B135: =SUM(B136:B145) -> 0 | C135: =SUM(C136:C145) -> 0 | D135: =SUM(D136:D145) -> 0 | E135: =SUM(E136:E145) -> 0 | F135: =SUM(F136:F145) -> 0 | G135: =SUM(G136:G145) -> 0 | H135: =SUM(H136:H145) -> 0
A136: =+Input!A88 -> - Other 1 | H136: =SUM(B136:G136) -> 0
A137: =+Input!A89 -> - Other 2 | H137: =SUM(B137:G137) -> 0
A138: =+Input!A90 -> - Other 3 | H138: =SUM(B138:G138) -> 0
A139: =+Input!A91 -> - Other 4 | H139: =SUM(B139:G139) -> 0
A140: =+Input!A92 -> - Other 5 | H140: =SUM(B140:G140) -> 0
A141: =+Input!A93 -> - Other 6 | H141: =SUM(B141:G141) -> 0
A142: =+Input!A94 -> - Other 7 | H142: =SUM(B142:G142) -> 0
A143: =+Input!A95 -> - Other 8 | H143: =SUM(B143:G143) -> 0
A144: =+Input!A96 -> - Other 9 | H144: =SUM(B144:G144) -> 0
A145: =+Input!A97 -> - Other 10 | H145: =SUM(B145:G145) -> 0

Sheet 4
A1: =+Input!B2 -> ENGEN JETPARK
A3: Daily Analysis
B5: Day | C5: Date
A6: UNDER REVIEW | B6: =+Input!B13 -> Monday | C6: =+Input!C13 -> 46146
I8: SUMMARY
B9: Tank: 1 | C9: Tank: 2 | D9: Tank: 3 | E9: Tank: 4 | F9: Tank: 5 | G9: TOTAL | I9: Diesel | J9: ULP: 95 | K9: ULP: 93 | L9: TOTAL
A10: DATA: LITRES | B10: Diesel | C10: ULP95 | D10: ULP93 | E10: ULP95 | F10: Diesel
A11: - Litres Purchased | G11: =SUM(B11:F11) -> 0
A12: - Litres Sold | G12: =SUM(B12:F12) -> 0 | I12: =+B12+F12 -> 0 | J12: =+C12+E12 -> 0 | K12: =+D12 -> 0 | L12: =SUM(I12:K12) -> 0
A13: - Closing Dip | G13: =SUM(B13:F13) -> 0 | I13: =+I12/L12 -> #DIV/0! | J13: =+J12/L12 -> #DIV/0! | K13: =+K12/L12 -> #DIV/0! | L13: =SUM(I13:K13) -> #DIV/0!
A14: - Selling Price | E14: =+C14 -> 0 | F14: =+B14 -> 0
A15: - Cost Price | E15: =+C15 -> 0 | F15: =+B15 -> 0
A16: - Gross Profit | B16: =+B14-B15 -> 0 | C16: =+C14-C15 -> 0 | D16: =+D14-D15 -> 0 | E16: =+E14-E15 -> 0 | F16: =+F14-F15 -> 0
A17: - Gross Profit % | B17: =+B16/B14 -> #DIV/0! | C17: =+C16/C14 -> #DIV/0! | D17: =+D16/D14 -> #DIV/0! | E17: =+E16/E14 -> #DIV/0! | F17: =+F16/F14 -> #DIV/0!
A20: DAY END REPORT
A21: - Total Sales
A22: - Less: Returns (Show as a negative)
A23: - Total Net Sales | B23: =SUM(B21:B22) -> 0
A26: SALES BY DIVISION | B26: =SUM(B27:B33) -> 0 | C26: =SUM(C27:C33) -> #DIV/0!
A27: - Bakery | C27: =+B27/$B$26 -> #DIV/0!
A28: - Bakpre | C28: =+B28/$B$26 -> #DIV/0!
A29: - Barist | C29: =+B29/$B$26 -> #DIV/0!
A30: - Fuel | C30: =+B30/$B$26 -> #DIV/0!
A31: - Lubes | C31: =+B31/$B$26 -> #DIV/0!
A32: - VV | C32: =+B32/$B$26 -> #DIV/0!
A33: - Quickshop | B33: =+B23-B27-B28-B29-B30-B31-B32 -> 0 | C33: =+B33/$B$26 -> #DIV/0!
A35: CONTROL TOTAL | B35: =+B23-B26 -> 0 | C35: - Must be zero
A38: CASHIERS RECONCILIATION
A40: Cashier Name | B40: =+Input!B44 -> Mandla | C40: =+Input!C44 -> Caroline | D40: =+Input!D44 -> Siyabonga | E40: =+Input!E44 -> Thumelo | F40: =+Input!F44 -> Cashier 5 | G40: =+Input!G44 -> Cashier 6 | H40: TOTAL | I40: CT
A41: Shift Number
A43: DAY END REPORT
A44: - Total Sales | H44: =SUM(B44:G44) -> 0
A45: - Less: Returns (Show as a negative) | H45: =SUM(B45:G45) -> 0
A46: - Total Net Sales | B46: =SUM(B44:B45) -> 0 | C46: =SUM(C44:C45) -> 0 | D46: =SUM(D44:D45) -> 0 | E46: =SUM(E44:E45) -> 0 | F46: =SUM(F44:F45) -> 0 | G46: =SUM(G44:G45) -> 0 | H46: =SUM(H44:H45) -> 0 | I46: =+B23-H46 -> 0 | J46: Must be Zero
A48: SUMMARY
A49: - Net Sales | B49: =+B46 -> 0 | C49: =+C46 -> 0 | D49: =+D46 -> 0 | E49: =+E46 -> 0 | F49: =+F46 -> 0 | G49: =+G46 -> 0 | H49: =SUM(B49:G49) -> 0
A50: - Banking | B50: =+B56+B63+B68 -> 0 | C50: =+C56+C63+C68 -> 0 | D50: =+D56+D63+D68 -> 0 | E50: =+E56+E63+E68 -> 0 | F50: =+F56+F63+F68 -> 0 | G50: =+G56+G63+G68 -> 0 | H50: =SUM(B50:G50) -> 0
A51: - Adjustments | B51: =+B73 -> 0 | C51: =+C73 -> 0 | D51: =+D73 -> 0 | E51: =+E73 -> 0 | F51: =+F73 -> 0 | G51: =+G73 -> 0 | H51: =SUM(B51:G51) -> 0
A52: - Petty Cash | B52: =-B82 -> 0 | C52: =-C82 -> 0 | D52: =-D82 -> 0 | E52: =-E82 -> 0 | F52: =-F82 -> 0 | G52: =-G82 -> 0 | H52: =SUM(B52:G52) -> 0
A53: - (OVER) / UNDER | B53: =+B49-B50-B51+B52 -> 0 | C53: =+C49-C50-C51+C52 -> 0 | D53: =+D49-D50-D51+D52 -> 0 | E53: =+E49-E50-E51+E52 -> 0 | F53: =+F49-F50-F51+F52 -> 0 | G53: =+G49-G50-G51+G52 -> 0 | H53: =+H49-H50-H51+H52 -> 0
A56: CASH | B56: =+B59+B60 -> 0 | C56: =+C59+C60 -> 0 | D56: =+D59+D60 -> 0 | E56: =+E59+E60 -> 0 | F56: =+F59+F60 -> 0 | G56: =+G59+G60 -> 0 | H56: =+H59+H60 -> 0
A57: - Cash: Coins | H57: =SUM(B57:G57) -> 0
A58: - Cash: Till | H58: =SUM(B58:G58) -> 0
A59: - Sub Total | B59: =SUM(B57:B58) -> 0 | C59: =SUM(C57:C58) -> 0 | D59: =SUM(D57:D58) -> 0 | E59: =SUM(E57:E58) -> 0 | F59: =SUM(F57:F58) -> 0 | G59: =SUM(G57:G58) -> 0 | H59: =SUM(H57:H58) -> 0
A60: - Cash drops | H60: =SUM(B60:G60) -> 0
A63: SPEDPOINTS | H63: =SUM(B63:G63) -> 0
A64: - Fleet Cards | H64: =SUM(B64:G64) -> 0
A65: - Net Speedpoints | B65: =+B63-B64 -> 0 | C65: =+C63-C64 -> 0 | D65: =+D63-D64 -> 0 | E65: =+E63-E64 -> 0 | F65: =+F63-F64 -> 0 | G65: =+G63-G64 -> 0 | H65: =+H63-H64 -> 0
A68: DEBTORS | B68: =SUM(B69:B70) -> 0 | C68: =SUM(C69:C70) -> 0 | D68: =SUM(D69:D70) -> 0 | E68: =SUM(E69:E70) -> 0 | F68: =SUM(F69:F70) -> 0 | G68: =SUM(G69:G70) -> 0 | H68: =SUM(H69:H70) -> 0
A69: - On Account | H69: =SUM(B69:G69) -> 0
A70: - Account Receipts (Show as a negative) | H70: =SUM(B70:G70) -> 0
A73: ADJUSTMENTS | B73: =SUM(B74:B79) -> 0 | C73: =SUM(C74:C79) -> 0 | D73: =SUM(D74:D79) -> 0 | E73: =SUM(E74:E79) -> 0 | F73: =SUM(F74:F79) -> 0 | G73: =SUM(G74:G79) -> 0 | H73: =SUM(H74:H79) -> 0 | J73: Comment
A74: - EFT | H74: =SUM(B74:G74) -> 0
A75: - Contamination | H75: =SUM(B75:G75) -> 0
A76: - Drive Off | H76: =SUM(B76:G76) -> 0
A77: - Loyalty | H77: =SUM(B77:G77) -> 0
A78: - Other | H78: =SUM(B78:G78) -> 0
A79: - To Settle | H79: =SUM(B79:G79) -> 0
A82: PETTY CASH | B82: =SUM(B83:B98) -> 0 | C82: =SUM(C83:C98) -> 0 | D82: =SUM(D83:D98) -> 0 | E82: =SUM(E83:E98) -> 0 | F82: =SUM(F83:F98) -> 0 | G82: =SUM(G83:G98) -> 0 | H82: =SUM(H83:H98) -> 0
A83: - Cleaning | H83: =SUM(B83:G83) -> 0
A84: - Creditors: Existing | B84: =+B101 -> 0 | C84: =+C101 -> 0 | D84: =+D101 -> 0 | E84: =+E101 -> 0 | F84: =+F101 -> 0 | G84: =+G101 -> 0 | H84: =SUM(B84:G84) -> 0
A85: - Creditors: New | B85: =+B135 -> 0 | C85: =+C135 -> 0 | D85: =+D135 -> 0 | E85: =+E135 -> 0 | F85: =+F135 -> 0 | G85: =+G135 -> 0 | H85: =SUM(B85:G85) -> 0
A86: - Forecourt: R & M | H86: =SUM(B86:G86) -> 0
A87: - Other: Non-Vatable | H87: =SUM(B87:G87) -> 0
A88: - Other: Non-Vatable | H88: =SUM(B88:G88) -> 0
A89: - Other: Non-Vatable | H89: =SUM(B89:G89) -> 0
A90: - Other: Vatable | H90: =SUM(B90:G90) -> 0
A91: - Other: Vatable | H91: =SUM(B91:G91) -> 0
A92: - Other: Vatable | H92: =SUM(B92:G92) -> 0
A93: - Printing & Stationery | H93: =SUM(B93:G93) -> 0
A94: - Retail: R & M | H94: =SUM(B94:G94) -> 0
A95: - Salaries | H95: =SUM(B95:G95) -> 0
A96: - Staff Transport | H96: =SUM(B96:G96) -> 0
A97: - Staff Welfare | H97: =SUM(B97:G97) -> 0
A98: - Wages | H98: =SUM(B98:G98) -> 0
A101: CREDITORS: EXISTING | B101: =SUM(B102:B132) -> 0 | C101: =SUM(C102:C132) -> 0 | D101: =SUM(D102:D132) -> 0 | E101: =SUM(E102:E132) -> 0 | F101: =SUM(F102:F132) -> 0 | G101: =SUM(G102:G132) -> 0 | H101: =SUM(H102:H132) -> 0
A102: =+Input!A55 -> - Aksia Sales | H102: =SUM(B102:G102) -> 0
A103: =+Input!A56 -> - Albany | H103: =SUM(B103:G103) -> 0
A104: =+Input!A57 -> - Atlantic Ice | H104: =SUM(B104:G104) -> 0
A105: =+Input!A58 -> - Bake It Easy | H105: =SUM(B105:G105) -> 0
A106: =+Input!A59 -> - Bamco Tabacco | H106: =SUM(B106:G106) -> 0
A107: =+Input!A60 -> - Blue Ribbon | H107: =SUM(B107:G107) -> 0
A108: =+Input!A61 -> - Catercorp | H108: =SUM(B108:G108) -> 0
A109: =+Input!A62 -> - Checkers | H109: =SUM(B109:G109) -> 0
A110: =+Input!A63 -> - Clover | H110: =SUM(B110:G110) -> 0
A111: =+Input!A64 -> - Cool Runnings | H111: =SUM(B111:G111) -> 0
A112: =+Input!A65 -> - Deep Frozen | H112: =SUM(B112:G112) -> 0
A113: =+Input!A66 -> - Digistics | H113: =SUM(B113:G113) -> 0
... A132: =+Input!A85 -> - W Convenience | H132: =SUM(B132:G132) -> 0
A135: CREDITORS: NEW (Update Input) | B135: =SUM(B136:B145) -> 0 | C135: =SUM(C136:C145) -> 0 | D135: =SUM(D136:D145) -> 0 | E135: =SUM(E136:E145) -> 0 | F135: =SUM(F136:F145) -> 0 | G135: =SUM(G136:G145) -> 0 | H135: =SUM(H136:H145) -> 0
A136: =+Input!A88 -> - Other 1 | H136: =SUM(B136:G136) -> 0
A137: =+Input!A89 -> - Other 2 | H137: =SUM(B137:G137) -> 0
A138: =+Input!A90 -> - Other 3 | H138: =SUM(B138:G138) -> 0
A139: =+Input!A91 -> - Other 4 | H139: =SUM(B139:G139) -> 0
A140: =+Input!A92 -> - Other 5 | H140: =SUM(B140:G140) -> 0
A141: =+Input!A93 -> - Other 6 | H141: =SUM(B141:G141) -> 0
A142: =+Input!A94 -> - Other 7 | H142: =SUM(B142:G142) -> 0
A143: =+Input!A95 -> - Other 8 | H143: =SUM(B143:G143) -> 0
A144: =+Input!A96 -> - Other 9 | H144: =SUM(B144:G144) -> 0
A145: =+Input!A97 -> - Other 10 | H145: =SUM(B145:G145) -> 0

Sheet 5
A1: =+Input!B2 -> ENGEN JETPARK
A3: Daily Analysis
B5: Day | C5: Date
A6: UNDER REVIEW | B6: =+Input!B14 -> Tuesday | C6: =+Input!C14 -> 46147
I8: SUMMARY
B9: Tank: 1 | C9: Tank: 2 | D9: Tank: 3 | E9: Tank: 4 | F9: Tank: 5 | G9: TOTAL | I9: Diesel | J9: ULP: 95 | K9: ULP: 93 | L9: TOTAL
A10: DATA: LITRES | B10: Diesel | C10: ULP95 | D10: ULP93 | E10: ULP95 | F10: Diesel
A11: - Litres Purchased | G11: =SUM(B11:F11) -> 0
A12: - Litres Sold | G12: =SUM(B12:F12) -> 0 | I12: =+B12+F12 -> 0 | J12: =+C12+E12 -> 0 | K12: =+D12 -> 0 | L12: =SUM(I12:K12) -> 0
A13: - Closing Dip | G13: =SUM(B13:F13) -> 0 | I13: =+I12/L12 -> #DIV/0! | J13: =+J12/L12 -> #DIV/0! | K13: =+K12/L12 -> #DIV/0! | L13: =SUM(I13:K13) -> #DIV/0!
A14: - Selling Price | E14: =+C14 -> 0 | F14: =+B14 -> 0
A15: - Cost Price | E15: =+C15 -> 0 | F15: =+B15 -> 0
A16: - Gross Profit | B16: =+B14-B15 -> 0 | C16: =+C14-C15 -> 0 | D16: =+D14-D15 -> 0 | E16: =+E14-E15 -> 0 | F16: =+F14-F15 -> 0
A17: - Gross Profit % | B17: =+B16/B14 -> #DIV/0! | C17: =+C16/C14 -> #DIV/0! | D17: =+D16/D14 -> #DIV/0! | E17: =+E16/E14 -> #DIV/0! | F17: =+F16/F14 -> #DIV/0!
A20: DAY END REPORT
A21: - Total Sales
A22: - Less: Returns (Show as a negative)
A23: - Total Net Sales | B23: =SUM(B21:B22) -> 0
A26: SALES BY DIVISION | B26: =SUM(B27:B33) -> 0 | C26: =SUM(C27:C33) -> #DIV/0!
A27: - Bakery | C27: =+B27/$B$26 -> #DIV/0!
A28: - Bakpre | C28: =+B28/$B$26 -> #DIV/0!
A29: - Barist | C29: =+B29/$B$26 -> #DIV/0!
A30: - Fuel | C30: =+B30/$B$26 -> #DIV/0!
A31: - Lubes | C31: =+B31/$B$26 -> #DIV/0!
A32: - VV | C32: =+B32/$B$26 -> #DIV/0!
A33: - Quickshop | B33: =+B23-B27-B28-B29-B30-B31-B32 -> 0 | C33: =+B33/$B$26 -> #DIV/0!
A35: CONTROL TOTAL | B35: =+B23-B26 -> 0 | C35: - Must be zero
A38: CASHIERS RECONCILIATION
A40: Cashier Name | B40: =+Input!B44 -> Mandla | C40: =+Input!C44 -> Caroline | D40: =+Input!D44 -> Siyabonga | E40: =+Input!E44 -> Thumelo | F40: =+Input!F44 -> Cashier 5 | G40: =+Input!G44 -> Cashier 6 | H40: TOTAL | I40: CT
A41: Shift Number
A43: DAY END REPORT
A44: - Total Sales | H44: =SUM(B44:G44) -> 0
A45: - Less: Returns (Show as a negative) | H45: =SUM(B45:G45) -> 0
A46: - Total Net Sales | B46: =SUM(B44:B45) -> 0 | C46: =SUM(C44:C45) -> 0 | D46: =SUM(D44:D45) -> 0 | E46: =SUM(E44:E45) -> 0 | F46: =SUM(F44:F45) -> 0 | G46: =SUM(G44:G45) -> 0 | H46: =SUM(H44:H45) -> 0 | I46: =+B23-H46 -> 0 | J46: Must be Zero
A48: SUMMARY
A49: - Net Sales | B49: =+B46 -> 0 | C49: =+C46 -> 0 | D49: =+D46 -> 0 | E49: =+E46 -> 0 | F49: =+F46 -> 0 | G49: =+G46 -> 0 | H49: =SUM(B49:G49) -> 0
A50: - Banking | B50: =+B56+B63+B68 -> 0 | C50: =+C56+C63+C68 -> 0 | D50: =+D56+D63+D68 -> 0 | E50: =+E56+E63+E68 -> 0 | F50: =+F56+F63+F68 -> 0 | G50: =+G56+G63+G68 -> 0 | H50: =SUM(B50:G50) -> 0
A51: - Adjustments | B51: =+B73 -> 0 | C51: =+C73 -> 0 | D51: =+D73 -> 0 | E51: =+E73 -> 0 | F51: =+F73 -> 0 | G51: =+G73 -> 0 | H51: =SUM(B51:G51) -> 0
A52: - Petty Cash | B52: =-B82 -> 0 | C52: =-C82 -> 0 | D52: =-D82 -> 0 | E52: =-E82 -> 0 | F52: =-F82 -> 0 | G52: =-G82 -> 0 | H52: =SUM(B52:G52) -> 0
A53: - (OVER) / UNDER | B53: =+B49-B50-B51+B52 -> 0 | C53: =+C49-C50-C51+C52 -> 0 | D53: =+D49-D50-D51+D52 -> 0 | E53: =+E49-E50-E51+E52 -> 0 | F53: =+F49-F50-F51+F52 -> 0 | G53: =+G49-G50-G51+G52 -> 0 | H53: =+H49-H50-H51+H52 -> 0
A56: CASH | B56: =+B59+B60 -> 0 | C56: =+C59+C60 -> 0 | D56: =+D59+D60 -> 0 | E56: =+E59+E60 -> 0 | F56: =+F59+F60 -> 0 | G56: =+G59+G60 -> 0 | H56: =+H59+H60 -> 0
A57: - Cash: Coins | H57: =SUM(B57:G57) -> 0
A58: - Cash: Till | H58: =SUM(B58:G58) -> 0
A59: - Sub Total | B59: =SUM(B57:B58) -> 0 | C59: =SUM(C57:C58) -> 0 | D59: =SUM(D57:D58) -> 0 | E59: =SUM(E57:E58) -> 0 | F59: =SUM(F57:F58) -> 0 | G59: =SUM(G57:G58) -> 0 | H59: =SUM(H57:H58) -> 0
A60: - Cash drops | H60: =SUM(B60:G60) -> 0
A63: SPEDPOINTS | H63: =SUM(B63:G63) -> 0
A64: - Fleet Cards | H64: =SUM(B64:G64) -> 0
A65: - Net Speedpoints | B65: =+B63-B64 -> 0 | C65: =+C63-C64 -> 0 | D65: =+D63-D64 -> 0 | E65: =+E63-E64 -> 0 | F65: =+F63-F64 -> 0 | G65: =+G63-G64 -> 0 | H65: =+H63-H64 -> 0
A68: DEBTORS | B68: =SUM(B69:B70) -> 0 | C68: =SUM(C69:C70) -> 0 | D68: =SUM(D69:D70) -> 0 | E68: =SUM(E69:E70) -> 0 | F68: =SUM(F69:F70) -> 0 | G68: =SUM(G69:G70) -> 0 | H68: =SUM(H69:H70) -> 0
A69: - On Account | H69: =SUM(B69:G69) -> 0
A70: - Account Receipts (Show as a negative) | H70: =SUM(B70:G70) -> 0
A73: ADJUSTMENTS | B73: =SUM(B74:B79) -> 0 | C73: =SUM(C74:C79) -> 0 | D73: =SUM(D74:D79) -> 0 | E73: =SUM(E74:E79) -> 0 | F73: =SUM(F74:F79) -> 0 | G73: =SUM(G74:G79) -> 0 | H73: =SUM(H74:H79) -> 0 | J73: Comment
A74: - EFT | H74: =SUM(B74:G74) -> 0
A75: - Contamination | H75: =SUM(B75:G75) -> 0
A76: - Drive Off | H76: =SUM(B76:G76) -> 0
A77: - Loyalty | H77: =SUM(B77:G77) -> 0
A78: - Other | H78: =SUM(B78:G78) -> 0
A79: - To Settle | H79: =SUM(B79:G79) -> 0
A82: PETTY CASH | B82: =SUM(B83:B98) -> 0 | C82: =SUM(C83:C98) -> 0 | D82: =SUM(D83:D98) -> 0 | E82: =SUM(E83:E98) -> 0 | F82: =SUM(F83:F98) -> 0 | G82: =SUM(G83:G98) -> 0 | H82: =SUM(H83:H98) -> 0
A83: - Cleaning | H83: =SUM(B83:G83) -> 0
A84: - Creditors: Existing | B84: =+B101 -> 0 | C84: =+C101 -> 0 | D84: =+D101 -> 0 | E84: =+E101 -> 0 | F84: =+F101 -> 0 | G84: =+G101 -> 0 | H84: =SUM(B84:G84) -> 0
A85: - Creditors: New | B85: =+B135 -> 0 | C85: =+C135 -> 0 | D85: =+D135 -> 0 | E85: =+E135 -> 0 | F85: =+F135 -> 0 | G85: =+G135 -> 0 | H85: =SUM(B85:G85) -> 0
A86: - Forecourt: R & M | H86: =SUM(B86:G86) -> 0
A87: - Other: Non-Vatable | H87: =SUM(B87:G87) -> 0
A88: - Other: Non-Vatable | H88: =SUM(B88:G88) -> 0
A89: - Other: Non-Vatable | H89: =SUM(B89:G89) -> 0
A90: - Other: Vatable | H90: =SUM(B90:G90) -> 0
A91: - Other: Vatable | H91: =SUM(B91:G91) -> 0
A92: - Other: Vatable | H92: =SUM(B92:G92) -> 0
A93: - Printing & Stationery | H93: =SUM(B93:G93) -> 0
A94: - Retail: R & M | H94: =SUM(B94:G94) -> 0
A95: - Salaries | H95: =SUM(B95:G95) -> 0
A96: - Staff Transport | H96: =SUM(B96:G96) -> 0
A97: - Staff Welfare | H97: =SUM(B97:G97) -> 0
A98: - Wages | H98: =SUM(B98:G98) -> 0
A101: CREDITORS: EXISTING | B101: =SUM(B102:B132) -> 0 | C101: =SUM(C102:C132) -> 0 | D101: =SUM(D102:D132) -> 0 | E101: =SUM(E102:E132) -> 0 | F101: =SUM(F102:F132) -> 0 | G101: =SUM(G102:G132) -> 0 | H101: =SUM(H102:H132) -> 0
A102: =+Input!A55 -> - Aksia Sales | H102: =SUM(B102:G102) -> 0
A103: =+Input!A56 -> - Albany | H103: =SUM(B103:G103) -> 0
A104: =+Input!A57 -> - Atlantic Ice | H104: =SUM(B104:G104) -> 0
A105: =+Input!A58 -> - Bake It Easy | H105: =SUM(B105:G105) -> 0
A106: =+Input!A59 -> - Bamco Tabacco | H106: =SUM(B106:G106) -> 0
A107: =+Input!A60 -> - Blue Ribbon | H107: =SUM(B107:G107) -> 0
A108: =+Input!A61 -> - Catercorp | H108: =SUM(B108:G108) -> 0
A109: =+Input!A62 -> - Checkers | H109: =SUM(B109:G109) -> 0
A110: =+Input!A63 -> - Clover | H110: =SUM(B110:G110) -> 0
A111: =+Input!A64 -> - Cool Runnings | H111: =SUM(B111:G111) -> 0
A112: =+Input!A65 -> - Deep Frozen | H112: =SUM(B112:G112) -> 0
A113: =+Input!A66 -> - Digistics | H113: =SUM(B113:G113) -> 0
... A132: =+Input!A85 -> - W Convenience | H132: =SUM(B132:G132) -> 0
A135: CREDITORS: NEW (Update Input) | B135: =SUM(B136:B145) -> 0 | C135: =SUM(C136:C145) -> 0 | D135: =SUM(D136:D145) -> 0 | E135: =SUM(E136:E145) -> 0 | F135: =SUM(F136:F145) -> 0 | G135: =SUM(G136:G145) -> 0 | H135: =SUM(H136:H145) -> 0
A136: =+Input!A88 -> - Other 1 | H136: =SUM(B136:G136) -> 0
A137: =+Input!A89 -> - Other 2 | H137: =SUM(B137:G137) -> 0
A138: =+Input!A90 -> - Other 3 | H138: =SUM(B138:G138) -> 0
A139: =+Input!A91 -> - Other 4 | H139: =SUM(B139:G139) -> 0
A140: =+Input!A92 -> - Other 5 | H140: =SUM(B140:G140) -> 0
A141: =+Input!A93 -> - Other 6 | H141: =SUM(B141:G141) -> 0
A142: =+Input!A94 -> - Other 7 | H142: =SUM(B142:G142) -> 0
A143: =+Input!A95 -> - Other 8 | H143: =SUM(B143:G143) -> 0
A144: =+Input!A96 -> - Other 9 | H144: =SUM(B144:G144) -> 0
A145: =+Input!A97 -> - Other 10 | H145: =SUM(B145:G145) -> 0

Sheet 6
A1: =+Input!B2 -> ENGEN JETPARK
A3: Daily Analysis
B5: Day | C5: Date
A6: UNDER REVIEW | B6: Wed | C6: 46148
I8: SUMMARY
B9: Tank: 1 | C9: Tank: 2 | D9: Tank: 3 | E9: Tank: 4 | F9: Tank: 5 | G9: TOTAL | I9: Diesel | J9: ULP: 95 | K9: ULP: 93 | L9: TOTAL
A10: DATA: LITRES | B10: Diesel | C10: ULP95 | D10: ULP93 | E10: ULP95 | F10: Diesel
A11: - Litres Purchased | G11: =SUM(B11:F11) -> 0
A12: - Litres Sold | G12: =SUM(B12:F12) -> 0 | I12: =+B12+F12 -> 0 | J12: =+C12+E12 -> 0 | K12: =+D12 -> 0 | L12: =SUM(I12:K12) -> 0
A13: - Closing Dip | G13: =SUM(B13:F13) -> 0 | I13: =+I12/L12 -> #DIV/0! | J13: =+J12/L12 -> #DIV/0! | K13: =+K12/L12 -> #DIV/0! | L13: =SUM(I13:K13) -> #DIV/0!
A14: - Selling Price | E14: =+C14 -> 0 | F14: =+B14 -> 0
A15: - Cost Price | E15: =+C15 -> 0 | F15: =+B15 -> 0
A16: - Gross Profit | B16: =+B14-B15 -> 0 | C16: =+C14-C15 -> 0 | D16: =+D14-D15 -> 0 | E16: =+E14-E15 -> 0 | F16: =+F14-F15 -> 0
A17: - Gross Profit % | B17: =+B16/B14 -> #DIV/0! | C17: =+C16/C14 -> #DIV/0! | D17: =+D16/D14 -> #DIV/0! | E17: =+E16/E14 -> #DIV/0! | F17: =+F16/F14 -> #DIV/0!
A20: DAY END REPORT
A21: - Total Sales
A22: - Less: Returns (Show as a negative)
A23: - Total Net Sales | B23: =SUM(B21:B22) -> 0
A26: SALES BY DIVISION | B26: =SUM(B27:B33) -> 0 | C26: =SUM(C27:C33) -> #DIV/0!
A27: - Bakery | C27: =+B27/$B$26 -> #DIV/0!
A28: - Bakpre | C28: =+B28/$B$26 -> #DIV/0!
A29: - Barist | C29: =+B29/$B$26 -> #DIV/0!
A30: - Fuel | C30: =+B30/$B$26 -> #DIV/0!
A31: - Lubes | C31: =+B31/$B$26 -> #DIV/0!
A32: - VV | C32: =+B32/$B$26 -> #DIV/0!
A33: - Quickshop | B33: =+B23-B27-B28-B29-B30-B31-B32 -> 0 | C33: =+B33/$B$26 -> #DIV/0!
A35: CONTROL TOTAL | B35: =+B23-B26 -> 0 | C35: - Must be zero
A38: CASHIERS RECONCILIATION
A40: Cashier Name | B40: =+Input!B44 -> Mandla | C40: =+Input!C44 -> Caroline | D40: =+Input!D44 -> Siyabonga | E40: =+Input!E44 -> Thumelo | F40: =+Input!F44 -> Cashier 5 | G40: =+Input!G44 -> Cashier 6 | H40: TOTAL | I40: CT
A41: Shift Number
A43: DAY END REPORT
A44: - Total Sales | H44: =SUM(B44:G44) -> 0
A45: - Less: Returns (Show as a negative) | H45: =SUM(B45:G45) -> 0
A46: - Total Net Sales | B46: =SUM(B44:B45) -> 0 | C46: =SUM(C44:C45) -> 0 | D46: =SUM(D44:D45) -> 0 | E46: =SUM(E44:E45) -> 0 | F46: =SUM(F44:F45) -> 0 | G46: =SUM(G44:G45) -> 0 | H46: =SUM(H44:H45) -> 0 | I46: =+B23-H46 -> 0 | J46: Must be Zero
A48: SUMMARY
A49: - Net Sales | B49: =+B46 -> 0 | C49: =+C46 -> 0 | D49: =+D46 -> 0 | E49: =+E46 -> 0 | F49: =+F46 -> 0 | G49: =+G46 -> 0 | H49: =SUM(B49:G49) -> 0
A50: - Banking | B50: =+B56+B63+B68 -> 0 | C50: =+C56+C63+C68 -> 0 | D50: =+D56+D63+D68 -> 0 | E50: =+E56+E63+E68 -> 0 | F50: =+F56+F63+F68 -> 0 | G50: =+G56+G63+G68 -> 0 | H50: =SUM(B50:G50) -> 0
A51: - Adjustments | B51: =+B73 -> 0 | C51: =+C73 -> 0 | D51: =+D73 -> 0 | E51: =+E73 -> 0 | F51: =+F73 -> 0 | G51: =+G73 -> 0 | H51: =SUM(B51:G51) -> 0
A52: - Petty Cash | B52: =-B82 -> 0 | C52: =-C82 -> 0 | D52: =-D82 -> 0 | E52: =-E82 -> 0 | F52: =-F82 -> 0 | G52: =-G82 -> 0 | H52: =SUM(B52:G52) -> 0
A53: - (OVER) / UNDER | B53: =+B49-B50-B51+B52 -> 0 | C53: =+C49-C50-C51+C52 -> 0 | D53: =+D49-D50-D51+D52 -> 0 | E53: =+E49-E50-E51+E52 -> 0 | F53: =+F49-F50-F51+F52 -> 0 | G53: =+G49-G50-G51+G52 -> 0 | H53: =+H49-H50-H51+H52 -> 0
A56: CASH | B56: =+B59+B60 -> 0 | C56: =+C59+C60 -> 0 | D56: =+D59+D60 -> 0 | E56: =+E59+E60 -> 0 | F56: =+F59+F60 -> 0 | G56: =+G59+G60 -> 0 | H56: =+H59+H60 -> 0
A57: - Cash: Coins | H57: =SUM(B57:G57) -> 0
A58: - Cash: Till | H58: =SUM(B58:G58) -> 0
A59: - Sub Total | B59: =SUM(B57:B58) -> 0 | C59: =SUM(C57:C58) -> 0 | D59: =SUM(D57:D58) -> 0 | E59: =SUM(E57:E58) -> 0 | F59: =SUM(F57:F58) -> 0 | G59: =SUM(G57:G58) -> 0 | H59: =SUM(H57:H58) -> 0
A60: - Cash drops | H60: =SUM(B60:G60) -> 0
A63: SPEDPOINTS | H63: =SUM(B63:G63) -> 0
A64: - Fleet Cards | H64: =SUM(B64:G64) -> 0
A65: - Net Speedpoints | B65: =+B63-B64 -> 0 | C65: =+C63-C64 -> 0 | D65: =+D63-D64 -> 0 | E65: =+E63-E64 -> 0 | F65: =+F63-F64 -> 0 | G65: =+G63-G64 -> 0 | H65: =+H63-H64 -> 0
A68: DEBTORS | B68: =SUM(B69:B70) -> 0 | C68: =SUM(C69:C70) -> 0 | D68: =SUM(D69:D70) -> 0 | E68: =SUM(E69:E70) -> 0 | F68: =SUM(F69:F70) -> 0 | G68: =SUM(G69:G70) -> 0 | H68: =SUM(H69:H70) -> 0
A69: - On Account | H69: =SUM(B69:G69) -> 0
A70: - Account Receipts (Show as a negative) | H70: =SUM(B70:G70) -> 0
A73: ADJUSTMENTS | B73: =SUM(B74:B79) -> 0 | C73: =SUM(C74:C79) -> 0 | D73: =SUM(D74:D79) -> 0 | E73: =SUM(E74:E79) -> 0 | F73: =SUM(F74:F79) -> 0 | G73: =SUM(G74:G79) -> 0 | H73: =SUM(H74:H79) -> 0 | J73: Comment
A74: - EFT | H74: =SUM(B74:G74) -> 0
A75: - Contamination | H75: =SUM(B75:G75) -> 0
A76: - Drive Off | H76: =SUM(B76:G76) -> 0
A77: - Loyalty | H77: =SUM(B77:G77) -> 0
A78: - Other | H78: =SUM(B78:G78) -> 0
A79: - To Settle | H79: =SUM(B79:G79) -> 0
A82: PETTY CASH | B82: =SUM(B83:B98) -> 0 | C82: =SUM(C83:C98) -> 0 | D82: =SUM(D83:D98) -> 0 | E82: =SUM(E83:E98) -> 0 | F82: =SUM(F83:F98) -> 0 | G82: =SUM(G83:G98) -> 0 | H82: =SUM(H83:H98) -> 0
A83: - Cleaning | H83: =SUM(B83:G83) -> 0
A84: - Creditors: Existing | B84: =+B101 -> 0 | C84: =+C101 -> 0 | D84: =+D101 -> 0 | E84: =+E101 -> 0 | F84: =+F101 -> 0 | G84: =+G101 -> 0 | H84: =SUM(B84:G84) -> 0
A85: - Creditors: New | B85: =+B135 -> 0 | C85: =+C135 -> 0 | D85: =+D135 -> 0 | E85: =+E135 -> 0 | F85: =+F135 -> 0 | G85: =+G135 -> 0 | H85: =SUM(B85:G85) -> 0
A86: - Forecourt: R & M | H86: =SUM(B86:G86) -> 0
A87: - Other: Non-Vatable | H87: =SUM(B87:G87) -> 0
A88: - Other: Non-Vatable | H88: =SUM(B88:G88) -> 0
A89: - Other: Non-Vatable | H89: =SUM(B89:G89) -> 0
A90: - Other: Vatable | H90: =SUM(B90:G90) -> 0
A91: - Other: Vatable | H91: =SUM(B91:G91) -> 0
A92: - Other: Vatable | H92: =SUM(B92:G92) -> 0
A93: - Printing & Stationery | H93: =SUM(B93:G93) -> 0
A94: - Retail: R & M | H94: =SUM(B94:G94) -> 0
A95: - Salaries | H95: =SUM(B95:G95) -> 0
A96: - Staff Transport | H96: =SUM(B96:G96) -> 0
A97: - Staff Welfare | H97: =SUM(B97:G97) -> 0
A98: - Wages | H98: =SUM(B98:G98) -> 0
A101: CREDITORS: EXISTING | B101: =SUM(B102:B132) -> 0 | C101: =SUM(C102:C132) -> 0 | D101: =SUM(D102:D132) -> 0 | E101: =SUM(E102:E132) -> 0 | F101: =SUM(F102:F132) -> 0 | G101: =SUM(G102:G132) -> 0 | H101: =SUM(H102:H132) -> 0
A102: =+Input!A55 -> - Aksia Sales | H102: =SUM(B102:G102) -> 0
A103: =+Input!A56 -> - Albany | H103: =SUM(B103:G103) -> 0
A104: =+Input!A57 -> - Atlantic Ice | H104: =SUM(B104:G104) -> 0
A105: =+Input!A58 -> - Bake It Easy | H105: =SUM(B105:G105) -> 0
A106: =+Input!A59 -> - Bamco Tabacco | H106: =SUM(B106:G106) -> 0
A107: =+Input!A60 -> - Blue Ribbon | H107: =SUM(B107:G107) -> 0
A108: =+Input!A61 -> - Catercorp | H108: =SUM(B108:G108) -> 0
A109: =+Input!A62 -> - Checkers | H109: =SUM(B109:G109) -> 0
A110: =+Input!A63 -> - Clover | H110: =SUM(B110:G110) -> 0
A111: =+Input!A64 -> - Cool Runnings | H111: =SUM(B111:G111) -> 0
A112: =+Input!A65 -> - Deep Frozen | H112: =SUM(B112:G112) -> 0
A113: =+Input!A66 -> - Digistics | H113: =SUM(B113:G113) -> 0
... A132: =+Input!A85 -> - W Convenience | H132: =SUM(B132:G132) -> 0
A135: CREDITORS: NEW (Update Input) | B135: =SUM(B136:B145) -> 0 | C135: =SUM(C136:C145) -> 0 | D135: =SUM(D136:D145) -> 0 | E135: =SUM(E136:E145) -> 0 | F135: =SUM(F136:F145) -> 0 | G135: =SUM(G136:G145) -> 0 | H135: =SUM(H136:H145) -> 0
A136: =+Input!A88 -> - Other 1 | H136: =SUM(B136:G136) -> 0
A137: =+Input!A89 -> - Other 2 | H137: =SUM(B137:G137) -> 0
A138: =+Input!A90 -> - Other 3 | H138: =SUM(B138:G138) -> 0
A139: =+Input!A91 -> - Other 4 | H139: =SUM(B139:G139) -> 0
A140: =+Input!A92 -> - Other 5 | H140: =SUM(B140:G140) -> 0
A141: =+Input!A93 -> - Other 6 | H141: =SUM(B141:G141) -> 0
A142: =+Input!A94 -> - Other 7 | H142: =SUM(B142:G142) -> 0
A143: =+Input!A95 -> - Other 8 | H143: =SUM(B143:G143) -> 0
A144: =+Input!A96 -> - Other 9 | H144: =SUM(B144:G144) -> 0
A145: =+Input!A97 -> - Other 10 | H145: =SUM(B145:G145) -> 0

Sheet 7
A1: =+Input!B2 -> ENGEN JETPARK
A3: Daily Analysis
B5: Day | C5: Date
A6: UNDER REVIEW | B6: =+Input!B16 -> Thursday | C6: =+Input!C11 -> 46144
I8: SUMMARY
B9: Tank: 1 | C9: Tank: 2 | D9: Tank: 3 | E9: Tank: 4 | F9: Tank: 5 | G9: TOTAL | I9: Diesel | J9: ULP: 95 | K9: ULP: 93 | L9: TOTAL
A10: DATA: LITRES | B10: Diesel | C10: ULP95 | D10: ULP93 | E10: ULP95 | F10: Diesel
A11: - Litres Purchased | G11: =SUM(B11:F11) -> 0
A12: - Litres Sold | G12: =SUM(B12:F12) -> 0 | I12: =+B12+F12 -> 0 | J12: =+C12+E12 -> 0 | K12: =+D12 -> 0 | L12: =SUM(I12:K12) -> 0
A13: - Closing Dip | G13: =SUM(B13:F13) -> 0 | I13: =+I12/L12 -> #DIV/0! | J13: =+J12/L12 -> #DIV/0! | K13: =+K12/L12 -> #DIV/0! | L13: =SUM(I13:K13) -> #DIV/0!
A14: - Selling Price | E14: =+C14 -> 0 | F14: =+B14 -> 0
A15: - Cost Price | E15: =+C15 -> 0 | F15: =+B15 -> 0
A16: - Gross Profit | B16: =+B14-B15 -> 0 | C16: =+C14-C15 -> 0 | D16: =+D14-D15 -> 0 | E16: =+E14-E15 -> 0 | F16: =+F14-F15 -> 0
A17: - Gross Profit % | B17: =+B16/B14 -> #DIV/0! | C17: =+C16/C14 -> #DIV/0! | D17: =+D16/D14 -> #DIV/0! | E17: =+E16/E14 -> #DIV/0! | F17: =+F16/F14 -> #DIV/0!
A20: DAY END REPORT
A21: - Total Sales
A22: - Less: Returns (Show as a negative)
A23: - Total Net Sales | B23: =SUM(B21:B22) -> 0
A26: SALES BY DIVISION | B26: =SUM(B27:B33) -> 0 | C26: =SUM(C27:C33) -> #DIV/0!
A27: - Bakery | C27: =+B27/$B$26 -> #DIV/0!
A28: - Bakpre | C28: =+B28/$B$26 -> #DIV/0!
A29: - Barist | C29: =+B29/$B$26 -> #DIV/0!
A30: - Fuel | C30: =+B30/$B$26 -> #DIV/0!
A31: - Lubes | C31: =+B31/$B$26 -> #DIV/0!
A32: - VV | C32: =+B32/$B$26 -> #DIV/0!
A33: - Quickshop | B33: =+B23-B27-B28-B29-B30-B31-B32 -> 0 | C33: =+B33/$B$26 -> #DIV/0!
A35: CONTROL TOTAL | B35: =+B23-B26 -> 0 | C35: - Must be zero
A38: CASHIERS RECONCILIATION
A40: Cashier Name | B40: =+Input!B44 -> Mandla | C40: =+Input!C44 -> Caroline | D40: =+Input!D44 -> Siyabonga | E40: =+Input!E44 -> Thumelo | F40: =+Input!F44 -> Cashier 5 | G40: =+Input!G44 -> Cashier 6 | H40: TOTAL | I40: CT
A41: Shift Number
A43: DAY END REPORT
A44: - Total Sales | H44: =SUM(B44:G44) -> 0
A45: - Less: Returns (Show as a negative) | H45: =SUM(B45:G45) -> 0
A46: - Total Net Sales | B46: =SUM(B44:B45) -> 0 | C46: =SUM(C44:C45) -> 0 | D46: =SUM(D44:D45) -> 0 | E46: =SUM(E44:E45) -> 0 | F46: =SUM(F44:F45) -> 0 | G46: =SUM(G44:G45) -> 0 | H46: =SUM(H44:H45) -> 0 | I46: =+B23-H46 -> 0 | J46: Must be Zero
A48: SUMMARY
A49: - Net Sales | B49: =+B46 -> 0 | C49: =+C46 -> 0 | D49: =+D46 -> 0 | E49: =+E46 -> 0 | F49: =+F46 -> 0 | G49: =+G46 -> 0 | H49: =SUM(B49:G49) -> 0
A50: - Banking | B50: =+B56+B63+B68 -> 0 | C50: =+C56+C63+C68 -> 0 | D50: =+D56+D63+D68 -> 0 | E50: =+E56+E63+E68 -> 0 | F50: =+F56+F63+F68 -> 0 | G50: =+G56+G63+G68 -> 0 | H50: =SUM(B50:G50) -> 0
A51: - Adjustments | B51: =+B73 -> 0 | C51: =+C73 -> 0 | D51: =+D73 -> 0 | E51: =+E73 -> 0 | F51: =+F73 -> 0 | G51: =+G73 -> 0 | H51: =SUM(B51:G51) -> 0
A52: - Petty Cash | B52: =-B82 -> 0 | C52: =-C82 -> 0 | D52: =-D82 -> 0 | E52: =-E82 -> 0 | F52: =-F82 -> 0 | G52: =-G82 -> 0 | H52: =SUM(B52:G52) -> 0
A53: - (OVER) / UNDER | B53: =+B49-B50-B51+B52 -> 0 | C53: =+C49-C50-C51+C52 -> 0 | D53: =+D49-D50-D51+D52 -> 0 | E53: =+E49-E50-E51+E52 -> 0 | F53: =+F49-F50-F51+F52 -> 0 | G53: =+G49-G50-G51+G52 -> 0 | H53: =+H49-H50-H51+H52 -> 0
A56: CASH | B56: =+B59+B60 -> 0 | C56: =+C59+C60 -> 0 | D56: =+D59+D60 -> 0 | E56: =+E59+E60 -> 0 | F56: =+F59+F60 -> 0 | G56: =+G59+G60 -> 0 | H56: =+H59+H60 -> 0
A57: - Cash: Coins | H57: =SUM(B57:G57) -> 0
A58: - Cash: Till | H58: =SUM(B58:G58) -> 0
A59: - Sub Total | B59: =SUM(B57:B58) -> 0 | C59: =SUM(C57:C58) -> 0 | D59: =SUM(D57:D58) -> 0 | E59: =SUM(E57:E58) -> 0 | F59: =SUM(F57:F58) -> 0 | G59: =SUM(G57:G58) -> 0 | H59: =SUM(H57:H58) -> 0
A60: - Cash drops | H60: =SUM(B60:G60) -> 0
A63: SPEDPOINTS | H63: =SUM(B63:G63) -> 0
A64: - Fleet Cards | H64: =SUM(B64:G64) -> 0
A65: - Net Speedpoints | B65: =+B63-B64 -> 0 | C65: =+C63-C64 -> 0 | D65: =+D63-D64 -> 0 | E65: =+E63-E64 -> 0 | F65: =+F63-F64 -> 0 | G65: =+G63-G64 -> 0 | H65: =+H63-H64 -> 0
A68: DEBTORS | B68: =SUM(B69:B70) -> 0 | C68: =SUM(C69:C70) -> 0 | D68: =SUM(D69:D70) -> 0 | E68: =SUM(E69:E70) -> 0 | F68: =SUM(F69:F70) -> 0 | G68: =SUM(G69:G70) -> 0 | H68: =SUM(H69:H70) -> 0
A69: - On Account | H69: =SUM(B69:G69) -> 0
A70: - Account Receipts (Show as a negative) | H70: =SUM(B70:G70) -> 0
A73: ADJUSTMENTS | B73: =SUM(B74:B79) -> 0 | C73: =SUM(C74:C79) -> 0 | D73: =SUM(D74:D79) -> 0 | E73: =SUM(E74:E79) -> 0 | F73: =SUM(F74:F79) -> 0 | G73: =SUM(G74:G79) -> 0 | H73: =SUM(H74:H79) -> 0 | J73: Comment
A74: - EFT | H74: =SUM(B74:G74) -> 0
A75: - Contamination | H75: =SUM(B75:G75) -> 0
A76: - Drive Off | H76: =SUM(B76:G76) -> 0
A77: - Loyalty | H77: =SUM(B77:G77) -> 0
A78: - Other | H78: =SUM(B78:G78) -> 0
A79: - To Settle | H79: =SUM(B79:G79) -> 0
A82: PETTY CASH | B82: =SUM(B83:B98) -> 0 | C82: =SUM(C83:C98) -> 0 | D82: =SUM(D83:D98) -> 0 | E82: =SUM(E83:E98) -> 0 | F82: =SUM(F83:F98) -> 0 | G82: =SUM(G83:G98) -> 0 | H82: =SUM(H83:H98) -> 0
A83: - Cleaning | H83: =SUM(B83:G83) -> 0
A84: - Creditors: Existing | B84: =+B101 -> 0 | C84: =+C101 -> 0 | D84: =+D101 -> 0 | E84: =+E101 -> 0 | F84: =+F101 -> 0 | G84: =+G101 -> 0 | H84: =SUM(B84:G84) -> 0
A85: - Creditors: New | B85: =+B135 -> 0 | C85: =+C135 -> 0 | D85: =+D135 -> 0 | E85: =+E135 -> 0 | F85: =+F135 -> 0 | G85: =+G135 -> 0 | H85: =SUM(B85:G85) -> 0
A86: - Forecourt: R & M | H86: =SUM(B86:G86) -> 0
A87: - Other: Non-Vatable | H87: =SUM(B87:G87) -> 0
A88: - Other: Non-Vatable | H88: =SUM(B88:G88) -> 0
A89: - Other: Non-Vatable | H89: =SUM(B89:G89) -> 0
A90: - Other: Vatable | H90: =SUM(B90:G90) -> 0
A91: - Other: Vatable | H91: =SUM(B91:G91) -> 0
A92: - Other: Vatable | H92: =SUM(B92:G92) -> 0
A93: - Printing & Stationery | H93: =SUM(B93:G93) -> 0
A94: - Retail: R & M | H94: =SUM(B94:G94) -> 0
A95: - Salaries | H95: =SUM(B95:G95) -> 0
A96: - Staff Transport | H96: =SUM(B96:G96) -> 0
A97: - Staff Welfare | H97: =SUM(B97:G97) -> 0
A98: - Wages | H98: =SUM(B98:G98) -> 0
A101: CREDITORS: EXISTING | B101: =SUM(B102:B132) -> 0 | C101: =SUM(C102:C132) -> 0 | D101: =SUM(D102:D132) -> 0 | E101: =SUM(E102:E132) -> 0 | F101: =SUM(F102:F132) -> 0 | G101: =SUM(G102:G132) -> 0 | H101: =SUM(H102:H132) -> 0
A102: =+Input!A55 -> - Aksia Sales | H102: =SUM(B102:G102) -> 0
A103: =+Input!A56 -> - Albany | H103: =SUM(B103:G103) -> 0
A104: =+Input!A57 -> - Atlantic Ice | H104: =SUM(B104:G104) -> 0
A105: =+Input!A58 -> - Bake It Easy | H105: =SUM(B105:G105) -> 0
A106: =+Input!A59 -> - Bamco Tabacco | H106: =SUM(B106:G106) -> 0
A107: =+Input!A60 -> - Blue Ribbon | H107: =SUM(B107:G107) -> 0
A108: =+Input!A61 -> - Catercorp | H108: =SUM(B108:G108) -> 0
A109: =+Input!A62 -> - Checkers | H109: =SUM(B109:G109) -> 0
A110: =+Input!A63 -> - Clover | H110: =SUM(B110:G110) -> 0
A111: =+Input!A64 -> - Cool Runnings | H111: =SUM(B111:G111) -> 0
A112: =+Input!A65 -> - Deep Frozen | H112: =SUM(B112:G112) -> 0
A113: =+Input!A66 -> - Digistics | H113: =SUM(B113:G113) -> 0
... A132: =+Input!A85 -> - W Convenience | H132: =SUM(B132:G132) -> 0
A135: CREDITORS: NEW (Update Input) | B135: =SUM(B136:B145) -> 0 | C135: =SUM(C136:C145) -> 0 | D135: =SUM(D136:D145) -> 0 | E135: =SUM(E136:E145) -> 0 | F135: =SUM(F136:F145) -> 0 | G135: =SUM(G136:G145) -> 0 | H135: =SUM(H136:H145) -> 0
A136: =+Input!A88 -> - Other 1 | H136: =SUM(B136:G136) -> 0
A137: =+Input!A89 -> - Other 2 | H137: =SUM(B137:G137) -> 0
A138: =+Input!A90 -> - Other 3 | H138: =SUM(B138:G138) -> 0
A139: =+Input!A91 -> - Other 4 | H139: =SUM(B139:G139) -> 0
A140: =+Input!A92 -> - Other 5 | H140: =SUM(B140:G140) -> 0
A141: =+Input!A93 -> - Other 6 | H141: =SUM(B141:G141) -> 0
A142: =+Input!A94 -> - Other 7 | H142: =SUM(B142:G142) -> 0
A143: =+Input!A95 -> - Other 8 | H143: =SUM(B143:G143) -> 0
A144: =+Input!A96 -> - Other 9 | H144: =SUM(B144:G144) -> 0
A145: =+Input!A97 -> - Other 10 | H145: =SUM(B145:G145) -> 0

Sheet 8
A1: =+Input!B2 -> ENGEN JETPARK
A3: Daily Analysis
B5: Day | C5: Date
A6: UNDER REVIEW | B6: =+Input!B17 -> Friday | C6: =+Input!C17 -> 46150
I8: SUMMARY
B9: Tank: 1 | C9: Tank: 2 | D9: Tank: 3 | E9: Tank: 4 | F9: Tank: 5 | G9: TOTAL | I9: Diesel | J9: ULP: 95 | K9: ULP: 93 | L9: TOTAL
A10: DATA: LITRES | B10: Diesel | C10: ULP95 | D10: ULP93 | E10: ULP95 | F10: Diesel
A11: - Litres Purchased | G11: =SUM(B11:F11) -> 0
A12: - Litres Sold | G12: =SUM(B12:F12) -> 0 | I12: =+B12+F12 -> 0 | J12: =+C12+E12 -> 0 | K12: =+D12 -> 0 | L12: =SUM(I12:K12) -> 0
A13: - Closing Dip | G13: =SUM(B13:F13) -> 0 | I13: =+I12/L12 -> #DIV/0! | J13: =+J12/L12 -> #DIV/0! | K13: =+K12/L12 -> #DIV/0! | L13: =SUM(I13:K13) -> #DIV/0!
A14: - Selling Price | E14: =+C14 -> 0 | F14: =+B14 -> 0
A15: - Cost Price | E15: =+C15 -> 0 | F15: =+B15 -> 0
A16: - Gross Profit | B16: =+B14-B15 -> 0 | C16: =+C14-C15 -> 0 | D16: =+D14-D15 -> 0 | E16: =+E14-E15 -> 0 | F16: =+F14-F15 -> 0
A17: - Gross Profit % | B17: =+B16/B14 -> #DIV/0! | C17: =+C16/C14 -> #DIV/0! | D17: =+D16/D14 -> #DIV/0! | E17: =+E16/E14 -> #DIV/0! | F17: =+F16/F14 -> #DIV/0!
A20: DAY END REPORT
A21: - Total Sales
A22: - Less: Returns (Show as a negative)
A23: - Total Net Sales | B23: =SUM(B21:B22) -> 0
A26: SALES BY DIVISION | B26: =SUM(B27:B33) -> 0 | C26: =SUM(C27:C33) -> #DIV/0!
A27: - Bakery | C27: =+B27/$B$26 -> #DIV/0!
A28: - Bakpre | C28: =+B28/$B$26 -> #DIV/0!
A29: - Barist | C29: =+B29/$B$26 -> #DIV/0!
A30: - Fuel | C30: =+B30/$B$26 -> #DIV/0!
A31: - Lubes | C31: =+B31/$B$26 -> #DIV/0!
A32: - VV | C32: =+B32/$B$26 -> #DIV/0!
A33: - Quickshop | B33: =+B23-B27-B28-B29-B30-B31-B32 -> 0 | C33: =+B33/$B$26 -> #DIV/0!
A35: CONTROL TOTAL | B35: =+B23-B26 -> 0 | C35: - Must be zero
A38: CASHIERS RECONCILIATION
A40: Cashier Name | B40: =+Input!B44 -> Mandla | C40: =+Input!C44 -> Caroline | D40: =+Input!D44 -> Siyabonga | E40: =+Input!E44 -> Thumelo | F40: =+Input!F44 -> Cashier 5 | G40: =+Input!G44 -> Cashier 6 | H40: TOTAL | I40: CT
A41: Shift Number
A43: DAY END REPORT
A44: - Total Sales | H44: =SUM(B44:G44) -> 0
A45: - Less: Returns (Show as a negative) | H45: =SUM(B45:G45) -> 0
A46: - Total Net Sales | B46: =SUM(B44:B45) -> 0 | C46: =SUM(C44:C45) -> 0 | D46: =SUM(D44:D45) -> 0 | E46: =SUM(E44:E45) -> 0 | F46: =SUM(F44:F45) -> 0 | G46: =SUM(G44:G45) -> 0 | H46: =SUM(H44:H45) -> 0 | I46: =+B23-H46 -> 0 | J46: Must be Zero
A48: SUMMARY
A49: - Net Sales | B49: =+B46 -> 0 | C49: =+C46 -> 0 | D49: =+D46 -> 0 | E49: =+E46 -> 0 | F49: =+F46 -> 0 | G49: =+G46 -> 0 | H49: =SUM(B49:G49) -> 0
A50: - Banking | B50: =+B56+B63+B68 -> 0 | C50: =+C56+C63+C68 -> 0 | D50: =+D56+D63+D68 -> 0 | E50: =+E56+E63+E68 -> 0 | F50: =+F56+F63+F68 -> 0 | G50: =+G56+G63+G68 -> 0 | H50: =SUM(B50:G50) -> 0
A51: - Adjustments | B51: =+B73 -> 0 | C51: =+C73 -> 0 | D51: =+D73 -> 0 | E51: =+E73 -> 0 | F51: =+F73 -> 0 | G51: =+G73 -> 0 | H51: =SUM(B51:G51) -> 0
A52: - Petty Cash | B52: =-B82 -> 0 | C52: =-C82 -> 0 | D52: =-D82 -> 0 | E52: =-E82 -> 0 | F52: =-F82 -> 0 | G52: =-G82 -> 0 | H52: =SUM(B52:G52) -> 0
A53: - (OVER) / UNDER | B53: =+B49-B50-B51+B52 -> 0 | C53: =+C49-C50-C51+C52 -> 0 | D53: =+D49-D50-D51+D52 -> 0 | E53: =+E49-E50-E51+E52 -> 0 | F53: =+F49-F50-F51+F52 -> 0 | G53: =+G49-G50-G51+G52 -> 0 | H53: =+H49-H50-H51+H52 -> 0
A56: CASH | B56: =+B59+B60 -> 0 | C56: =+C59+C60 -> 0 | D56: =+D59+D60 -> 0 | E56: =+E59+E60 -> 0 | F56: =+F59+F60 -> 0 | G56: =+G59+G60 -> 0 | H56: =+H59+H60 -> 0
A57: - Cash: Coins | H57: =SUM(B57:G57) -> 0
A58: - Cash: Till | H58: =SUM(B58:G58) -> 0
A59: - Sub Total | B59: =SUM(B57:B58) -> 0 | C59: =SUM(C57:C58) -> 0 | D59: =SUM(D57:D58) -> 0 | E59: =SUM(E57:E58) -> 0 | F59: =SUM(F57:F58) -> 0 | G59: =SUM(G57:G58) -> 0 | H59: =SUM(H57:H58) -> 0
A60: - Cash drops | H60: =SUM(B60:G60) -> 0
A63: SPEDPOINTS | H63: =SUM(B63:G63) -> 0
A64: - Fleet Cards | H64: =SUM(B64:G64) -> 0
A65: - Net Speedpoints | B65: =+B63-B64 -> 0 | C65: =+C63-C64 -> 0 | D65: =+D63-D64 -> 0 | E65: =+E63-E64 -> 0 | F65: =+F63-F64 -> 0 | G65: =+G63-G64 -> 0 | H65: =+H63-H64 -> 0
A68: DEBTORS | B68: =SUM(B69:B70) -> 0 | C68: =SUM(C69:C70) -> 0 | D68: =SUM(D69:D70) -> 0 | E68: =SUM(E69:E70) -> 0 | F68: =SUM(F69:F70) -> 0 | G68: =SUM(G69:G70) -> 0 | H68: =SUM(H69:H70) -> 0
A69: - On Account | H69: =SUM(B69:G69) -> 0
A70: - Account Receipts (Show as a negative) | H70: =SUM(B70:G70) -> 0
